Workbook

Sheet Cover
A1: UNITED SPIRITS LIMITED (NSE: UNITDSPR) — Integrated Financial Model & Initiation
A3: Rating | B3: NEUTRAL / HOLD
A4: Current market price (10-Jun-2026) | B4: 1259
A5: 12-month target price (base, blended) | B5: 1160
A6: DCF value/share (live link) | B6: ='DCF'!$B$28
A7: FY26 Net Sales Value (live link) | B7: ='Revenue Buildup'!F5
A8: FY26 core EBITDA (live link) | B8: ='Income Statement'!F9
A9: FY26 PAT reported (live link) | B9: ='Income Statement'!F19
A10: FY30E Net Sales (live link) | B10: ='Revenue Buildup'!J5
A11: FY30E EBITDA (live link) | B11: ='Income Statement'!J9
A12: Shares outstanding (cr) | B12: ='Assumptions'!$B$28
A13: Market capitalisation (₹ cr) | B13: 91639
A14: Parent | B14: Diageo plc (~56%)
A15: Reporting basis | B15: Consolidated; topline = Net Sales Value (ex-excise)
A16: Colour key | B16: Blue = input | Black = calculation | Green = cross-sheet link
A17: Note | B17: FY26 = last actual; FY27E-FY30E forecast; RCB = discontinued/held-for-sale (optionality)
A19: Educational model — not investment advice. All forecast figures are live Excel formulas linked across sheets.

Sheet Sources & References
A1: SOURCES & REFERENCES — provenance of every hard-coded (blue) figure
A3: COLOUR KEY | B3: Blue = hard-coded input | Black = calculation (same-sheet formula) | Green = link to another sheet
A4: FY2022 & FY2023 actuals | B4: USL Annual Report 2022-23 (FY2023.pdf): Consolidated Balance Sheet (p.258-259), Statement of Profit & Loss (p.260-261), Cash Flows (p.263-264). Reported in ₹ million -> divided by 10 to ₹ crore.
A5: FY2024 & FY2025 actuals | B5: USL Integrated Annual Report 2024-25 (FY2025.pdf): Consolidated Balance Sheet (p.410-411), Statement of P&L (p.412-413), Cash Flows (p.415-416), PPE note 3.1, ROU/Lease note 3.2, Segment note (p.460-461). ₹ crore.
A6: FY2026 actuals | B6: USL Consolidated Financial Results for year ended 31-Mar-2026 (fy 2026.xlsx), filed 14-May-2026: P&L, Balance Sheet, Cash Flow, Segment. Continuing operations (RCB = discontinued/held-for-sale). ₹ crore.
A7: Volume / NSV-per-case / P&A salience | B7: FY2025 AR Key Performance Indicators (p.22-23) and Board's Report (p.92); FY2023 AR MD&A (p.34,48). Standalone NSV used as proxy for beverage-alcohol NSV (consolidation differences immaterial).
A8: Net Sales Value (NSV) | B8: Defined as Revenue from operations minus Excise duty. Excise is a pass-through state levy (~55% of gross). Driver of the model topline.
A9: PPE gross block / depreciation | B9: FY2025 AR note 3.1 (gross block, additions, disposals, accumulated depreciation, useful lives).
A10: Lease (Ind AS 116) | B10: FY2025 AR note 3.2 (ROU roll-forward, lease liability current/non-current, lease cash outflows, incremental borrowing rate).
A11: Market data (price, mkt cap, peers) | B11: Public market sources ~10-Jun-2026 (NSE/exchange data, company FY26 results). USL CMP ₹1,259; mkt cap ₹91,639 cr. Radico/ABDL/Tilaknagar/Globus FY26 net rev, EBITDA, PAT from public filings/results. Approximate; for relative context only.
A12: Forecast assumptions | B12: Analyst estimates (see Assumptions sheet, all blue). Justified in the accompanying report (USL_Equity_Research_Report.md).
A13: WACC / terminal growth | B13: WACC 10.25% (rf ~6.5%, ERP ~6.0%, beta ~0.65, net-cash); terminal g 6.25% (India nominal long-run consumption). Editable on Assumptions sheet.
A14: Note on RCB | B14: Sports/RCB classified by the company as discontinued/held-for-sale in FY26; excluded from the core forecast and valued separately as optionality (₹2,500 cr, conservative placeholder).
A15: Disclaimer | B15: Educational/analytical model. Not investment advice. Assumptions are the analyst's estimates and should be stress-tested against quarterly disclosures.

Sheet Assumptions
A1: ASSUMPTIONS — drivers, anchors & constants
A2: ₹ crore / % (blue = hard-coded analyst input) | B2: FY22 | C2: FY23 | D2: FY24 | E2: FY25 | F2: FY26 | G2: FY27E | H2: FY28E | I2: FY29E | J2: FY30E
A3: FORECAST DRIVERS (BASE CASE) — blue = analyst inputs
A4: Volume growth % | G4: 0.045 | H4: 0.045 | I4: 0.04 | J4: 0.04
A5: Realisation (NSV/case) growth % | G5: 0.053 | H5: 0.053 | I5: 0.053 | J5: 0.048
A6: Core EBITDA margin (% NSV) | G6: 0.188 | H6: 0.194 | I6: 0.2 | J6: 0.205
A7: Gross margin (% NSV) | G7: 0.47 | H7: 0.474 | I7: 0.478 | J7: 0.482
A8: A&P (% NSV) | G8: 0.103 | H8: 0.103 | I8: 0.102 | J8: 0.102
A9: Employee (% NSV) | G9: 0.05 | H9: 0.049 | I9: 0.048 | J9: 0.047
A10: Excise (% gross revenue) | G10: 0.552 | H10: 0.552 | I10: 0.551 | J10: 0.551
A11: Effective tax rate % | G11: 0.255 | H11: 0.255 | I11: 0.255 | J11: 0.255
A12: Dividend payout % | G12: 0.6 | H12: 0.6 | I12: 0.62 | J12: 0.62
A13: Treasury yield % | G13: 0.058 | H13: 0.059 | I13: 0.06 | J13: 0.06
A14: Capex (% NSV) | G14: 0.02 | H14: 0.02 | I14: 0.019 | J14: 0.019
A15: PPE depreciation rate % | G15: 0.115 | H15: 0.115 | I15: 0.115 | J15: 0.115
... A26: Other finance cost (₹ cr) | G26: 52 | H26: 55 | I26: 58 | J26: 60
A27: MODEL ANCHORS & CONSTANTS (value in column B)
A28: Shares outstanding (cr) | B28: 72.78
A29: FY26 owned PPE (₹ cr) | B29: 900
A30: FY26 ROU asset (₹ cr) | B30: 315
A31: Intangible amortisation /yr | B31: 15
A32: Treasury other income constant | B32: 60
A33: Cash split of treasury | B33: 0.27
A34: Deposit split of treasury | B34: 0.36
A35: Investment split of treasury | B35: 0.37
A36: Tax paid under protest (held flat) | B36: 1191
A37: Other op. assets base (FY26) | B37: 667
A38: Current tax liab growth | B38: 1.05
A39: RCB optionality value (₹ cr) | B39: 2500
... A41: Terminal growth g | B41: 0.0625

Sheet Revenue Buildup
A1: Revenue Buildup
A2: ₹ crore (unless stated) | B2: FY22 | C2: FY23 | D2: FY24 | E2: FY25 | F2: FY26 | G2: FY27E | H2: FY28E | I2: FY29E | J2: FY30E
A3: Volume (mn cases) | B3: 79.2 | C3: 72.5 | D3: 61.5 | E3: 64 | F3: 66.6 | G3: =F3*(1+'Assumptions'!G4) | H3: =G3*(1+'Assumptions'!H4) | I3: =H3*(1+'Assumptions'!I4) | J3: =I3*(1+'Assumptions'!J4)
A4: NSV per case (₹) - realisation | B4: 1459 | C4: 1605 | D4: 1740 | E4: 1810 | F4: 1872 | G4: =F4*(1+'Assumptions'!G5) | H4: =G4*(1+'Assumptions'!H5) | I4: =H4*(1+'Assumptions'!I5) | J4: =I4*(1+'Assumptions'!J5)
A5: Net Sales Value (NSV) = Vol x Realisation | B5: 9712.4 | C5: 10611.6 | D5: 11321 | E5: 12069 | F5: 12467 | G5: =G3*1000000*G4/10000000 | H5: =H3*1000000*H4/10000000 | I5: =I3*1000000*I4/10000000 | J5: =J3*1000000*J4/10000000
A6: Excise duty | B6: 21349 | C6: 17204 | D6: 14697 | E6: 15207 | F6: 15349 | G6: =G5/(1-'Assumptions'!G10)*'Assumptions'!G10 | H6: =H5/(1-'Assumptions'!H10)*'Assumptions'!H10 | I6: =I5/(1-'Assumptions'!I10)*'Assumptions'!I10 | J6: =J5/(1-'Assumptions'!J10)*'Assumptions'!J10
A7: Gross revenue (incl. excise) | B7: 31062 | C7: 27815 | D7: 26018 | E7: 27276 | F7: 27816 | G7: =G5+G6 | H7: =H5+H6 | I7: =I5+I6 | J7: =J5+J6
A8: P&A salience (% of NSV) | B8: 84 | C8: 87 | D8: 87 | E8: 89 | F8: 90 | G8: =MIN(95,F8+0.8) | H8: =MIN(95,G8+0.8) | I8: =MIN(95,H8+0.8) | J8: =MIN(95,I8+0.8)
A9: P&A salience (% of volume) | B9: 54 | C9: 66 | D9: 82 | E9: 83 | F9: 84 | G9: =MIN(92,F9+1.2) | H9: =MIN(92,G9+1.2) | I9: =MIN(92,H9+1.2) | J9: =MIN(92,I9+1.2)

Sheet Income Statement
A1: Income Statement
A2: ₹ crore (unless stated) | B2: FY22 | C2: FY23 | D2: FY24 | E2: FY25 | F2: FY26 | G2: FY27E | H2: FY28E | I2: FY29E | J2: FY30E
A3: Net Sales Value (NSV) | B3: ='Revenue Buildup'!B5 | C3: ='Revenue Buildup'!C5 | D3: ='Revenue Buildup'!D5 | E3: ='Revenue Buildup'!E5 | F3: ='Revenue Buildup'!F5 | G3: ='Revenue Buildup'!G5 | H3: ='Revenue Buildup'!H5 | I3: ='Revenue Buildup'!I5 | J3: ='Revenue Buildup'!J5
A4: Cost of goods sold | B4: 5291.5 | C4: 6064.1 | D4: 6048 | E4: 6397 | F4: 6674 | G4: =G3-G5 | H4: =H3-H5 | I4: =I3-I5 | J4: =J3-J5
A5: Gross Profit | B5: 4140 | C5: 4302 | D5: 4644 | E5: 5176 | F5: 5793 | G5: =G3*'Assumptions'!G7 | H5: =H3*'Assumptions'!H7 | I5: =I3*'Assumptions'!I7 | J5: =J3*'Assumptions'!J7
A6: Employee cost | B6: 653.1 | C6: 610 | D6: 547 | E6: 609 | F6: 635 | G6: =G3*'Assumptions'!G9 | H6: =H3*'Assumptions'!H9 | I6: =I3*'Assumptions'!I9 | J6: =J3*'Assumptions'!J9
A7: Advertising & promotion | B7: 694.9 | C7: 921.8 | D7: 1048 | E7: 1130 | F7: 1295 | G7: =G3*'Assumptions'!G8 | H7: =H3*'Assumptions'!H8 | I7: =I3*'Assumptions'!I8 | J7: =J3*'Assumptions'!J8
A8: Other operating expense | B8: 1464.8 | C8: 1598.8 | D8: 1677 | E8: 1690 | F8: 1577 | G8: =G5-G6-G7-G9 | H8: =H5-H6-H7-H9 | I8: =I5-I6-I7-I9 | J8: =J5-J6-J7-J9
A9: EBITDA (core) | B9: 1510 | C9: 1419 | D9: 1708 | E9: 2058 | F9: 2286 | G9: =G3*'Assumptions'!G6 | H9: =H3*'Assumptions'!H6 | I9: =I3*'Assumptions'!I6 | J9: =J3*'Assumptions'!J6
A10: Depreciation & amortisation | B10: 303.8 | C10: 282.5 | D10: 275 | E10: 283 | F10: 289 | G10: ='PPE Schedule'!G6+'PPE Schedule'!G11+'Assumptions'!$B$31 | H10: ='PPE Schedule'!H6+'PPE Schedule'!H11+'Assumptions'!$B$31 | I10: ='PPE Schedule'!I6+'PPE Schedule'!I11+'Assumptions'!$B$31 | J10: ='PPE Schedule'!J6+'PPE Schedule'!J11+'Assumptions'!$B$31
A11: EBIT | B11: =B9-B10 | C11: =C9-C10 | D11: =D9-D10 | E11: =E9-E10 | F11: =F9-F10 | G11: =G9-G10 | H11: =H9-H10 | I11: =I9-I10 | J11: =J9-J10
A12: Other income (treasury) | B12: 35.5 | C12: 73.1 | D12: 225 | E12: 336 | F12: 478 | G12: ='Balance Sheet'!F18*'Assumptions'!G13+'Assumptions'!$B$32 | H12: ='Balance Sheet'!G18*'Assumptions'!H13+'Assumptions'!$B$32 | I12: ='Balance Sheet'!H18*'Assumptions'!I13+'Assumptions'!$B$32 | J12: ='Balance Sheet'!I18*'Assumptions'!J13+'Assumptions'!$B$32
A13: Finance costs | B13: 88 | C13: 103.9 | D13: 76 | E13: 89 | F13: 158 | G13: ='Lease Schedule'!G5+'Assumptions'!G26 | H13: ='Lease Schedule'!H5+'Assumptions'!H26 | I13: ='Lease Schedule'!I5+'Assumptions'!I26 | J13: ='Lease Schedule'!J5+'Assumptions'!J26
A14: Exceptional / JV | B14: -165.2 | C14: 175 | D14: -18 | E14: -72 | F14: -98 | G14: 0 | H14: 0 | I14: 0 | J14: 0
A15: Profit before tax | B15: 1086.6 | C15: 1278.6 | D15: 1857 | E15: 2135 | F15: 2226 | G15: =G11+G12-G13+G14 | H15: =H11+H12-H13+H14 | I15: =I11+I12-I13+I14 | J15: =J11+J12-J13+J14
A16: Tax | B16: 276 | C16: 152.8 | D16: 449 | E16: 553 | F16: 510 | G16: =G15*'Assumptions'!G11 | H16: =H15*'Assumptions'!H11 | I16: =I15*'Assumptions'!I11 | J16: =J15*'Assumptions'!J11
A17: PAT (continuing) | B17: 810.6 | C17: 1125.8 | D17: 1408 | E17: 1582 | F17: 1716 | G17: =G15-G16 | H17: =H15-H16 | I17: =I15-I16 | J17: =J15-J16
A18: Discontinued ops (RCB) | B18: 0 | C18: 0 | D18: 0 | E18: 0 | F18: 129 | G18: 0 | H18: 0 | I18: 0 | J18: 0
A19: PAT (reported) | B19: 810.6 | C19: 1125.8 | D19: 1408 | E19: 1582 | F19: 1838 | G19: =G17+G18 | H19: =H17+H18 | I19: =I17+I18 | J19: =J17+J18
A20: EPS (₹) | B20: 11.68 | C20: 16.01 | D20: 19.83 | E20: 22.28 | F20: 25.89 | G20: =G19/'Assumptions'!$B$28 | H20: =H19/'Assumptions'!$B$28 | I20: =I19/'Assumptions'!$B$28 | J20: =J19/'Assumptions'!$B$28

Sheet Working Capital
A1: Working Capital
A2: ₹ crore (unless stated) | B2: FY22 | C2: FY23 | D2: FY24 | E2: FY25 | F2: FY26 | G2: FY27E | H2: FY28E | I2: FY29E | J2: FY30E
A3: Trade receivables (current) | B3: 2373.6 | C3: 2434 | D3: 3056 | E3: 3410 | F3: 3609 | G3: ='Assumptions'!G20/365*'Revenue Buildup'!G7 | H3: ='Assumptions'!H20/365*'Revenue Buildup'!H7 | I3: ='Assumptions'!I20/365*'Revenue Buildup'!I7 | J3: ='Assumptions'!J20/365*'Revenue Buildup'!J7
A4: Inventories | B4: 2156.7 | C4: 2230 | D4: 2063 | E4: 2305 | F4: 2668 | G4: ='Assumptions'!G21/365*'Income Statement'!G4 | H4: ='Assumptions'!H21/365*'Income Statement'!H4 | I4: ='Assumptions'!I21/365*'Income Statement'!I4 | J4: ='Assumptions'!J21/365*'Income Statement'!J4
A5: Trade payables | B5: 1582.1 | C5: 1782.5 | D5: 1954 | E5: 2239 | F5: 2383 | G5: ='Assumptions'!G22/365*'Income Statement'!G4 | H5: ='Assumptions'!H22/365*'Income Statement'!H4 | I5: ='Assumptions'!I22/365*'Income Statement'!I4 | J5: ='Assumptions'!J22/365*'Income Statement'!J4
A6: Trade receivables (non-current) | B6: 148.5 | C6: 146.2 | D6: 365 | E6: 340 | F6: 351 | G6: ='Revenue Buildup'!G5*'Assumptions'!G23 | H6: ='Revenue Buildup'!H5*'Assumptions'!H23 | I6: ='Revenue Buildup'!I5*'Assumptions'!I23 | J6: ='Revenue Buildup'!J5*'Assumptions'!J23
A7: Net trade working capital | B7: =B4+B3-B5 | C7: =C4+C3-C5 | D7: =D4+D3-D5 | E7: =E4+E3-E5 | F7: =F4+F3-F5 | G7: =G4+G3-G5 | H7: =H4+H3-H5 | I7: =I4+I3-I5 | J7: =J4+J3-J5
A8: Receivable days (gross rev) | B8: =B3/'Revenue Buildup'!B7*365 | C8: =C3/'Revenue Buildup'!C7*365 | D8: =D3/'Revenue Buildup'!D7*365 | E8: =E3/'Revenue Buildup'!E7*365 | F8: =F3/'Revenue Buildup'!F7*365 | G8: =G3/'Revenue Buildup'!G7*365 | H8: =H3/'Revenue Buildup'!H7*365 | I8: =I3/'Revenue Buildup'!I7*365 | J8: =J3/'Revenue Buildup'!J7*365
A9: Inventory days (COGS) | B9: =B4/'Income Statement'!B4*365 | C9: =C4/'Income Statement'!C4*365 | D9: =D4/'Income Statement'!D4*365 | E9: =E4/'Income Statement'!E4*365 | F9: =F4/'Income Statement'!F4*365 | G9: =G4/'Income Statement'!G4*365 | H9: =H4/'Income Statement'!H4*365 | I9: =I4/'Income Statement'!I4*365 | J9: =J4/'Income Statement'!J4*365
A10: Payable days (COGS) | B10: =B5/'Income Statement'!B4*365 | C10: =C5/'Income Statement'!C4*365 | D10: =D5/'Income Statement'!D4*365 | E10: =E5/'Income Statement'!E4*365 | F10: =F5/'Income Statement'!F4*365 | G10: =G5/'Income Statement'!G4*365 | H10: =H5/'Income Statement'!H4*365 | I10: =I5/'Income Statement'!I4*365 | J10: =J5/'Income Statement'!J4*365
A11: Cash conversion cycle (days) | B11: =B9+B8-B10 | C11: =C9+C8-C10 | D11: =D9+D8-D10 | E11: =E9+E8-E10 | F11: =F9+F8-F10 | G11: =G9+G8-G10 | H11: =H9+H8-H10 | I11: =I9+I8-I10 | J11: =J9+J8-J10

Sheet PPE Schedule
A1: PPE Schedule
A2: ₹ crore (unless stated) | B2: FY22 | C2: FY23 | D2: FY24 | E2: FY25 | F2: FY26 | G2: FY27E | H2: FY28E | I2: FY29E | J2: FY30E
A3: Owned PPE
A4: Opening (net) | G4: =F7 | H4: =G7 | I4: =H7 | J4: =I7
A5: + Capex | B5: 134 | C5: 136.6 | D5: 98 | E5: 162 | F5: 181 | G5: ='Revenue Buildup'!G5*'Assumptions'!G14 | H5: ='Revenue Buildup'!H5*'Assumptions'!H14 | I5: ='Revenue Buildup'!I5*'Assumptions'!I14 | J5: ='Revenue Buildup'!J5*'Assumptions'!J14
A6: - Depreciation | G6: =(G4+G5*0.5)*'Assumptions'!G15 | H6: =(H4+H5*0.5)*'Assumptions'!H15 | I6: =(I4+I5*0.5)*'Assumptions'!I15 | J6: =(J4+J5*0.5)*'Assumptions'!J15
A7: Closing owned PPE (net) | F7: ='Assumptions'!$B$29 | G7: =G4+G5-G6 | H7: =H4+H5-H6 | I7: =I4+I5-I6 | J7: =J4+J5-J6
A8: Right-of-use (ROU) asset
A9: Opening | G9: =F12 | H9: =G12 | I9: =H12 | J9: =I12
A10: + New leases | G10: ='Revenue Buildup'!G5*'Assumptions'!G16 | H10: ='Revenue Buildup'!H5*'Assumptions'!H16 | I10: ='Revenue Buildup'!I5*'Assumptions'!I16 | J10: ='Revenue Buildup'!J5*'Assumptions'!J16
A11: - ROU depreciation | G11: =(G9+G10*0.5)*'Assumptions'!G17 | H11: =(H9+H10*0.5)*'Assumptions'!H17 | I11: =(I9+I10*0.5)*'Assumptions'!I17 | J11: =(J9+J10*0.5)*'Assumptions'!J17
A12: Closing ROU | F12: ='Assumptions'!$B$30 | G12: =G9+G10-G11 | H12: =H9+H10-H11 | I12: =I9+I10-I11 | J12: =J9+J10-J11
A13: Reported Net PPE (owned + ROU) | B13: 1215.2 | C13: 978.3 | D13: 844 | E13: 850 | F13: =F7+F12 | G13: =G7+G12 | H13: =H7+H12 | I13: =I7+I12 | J13: =J7+J12
A14: Capital work-in-progress | B14: 87.7 | C14: 66.8 | D14: 37 | E14: 72 | F14: 77 | G14: =F14 | H14: =G14 | I14: =H14 | J14: =I14
A15: Capex / NSV % | B15: =B5/'Revenue Buildup'!B5 | C15: =C5/'Revenue Buildup'!C5 | D15: =D5/'Revenue Buildup'!D5 | E15: =E5/'Revenue Buildup'!E5 | F15: =F5/'Revenue Buildup'!F5 | G15: =G5/'Revenue Buildup'!G5 | H15: =H5/'Revenue Buildup'!H5 | I15: =I5/'Revenue Buildup'!I5 | J15: =J5/'Revenue Buildup'!J5
A16: Asset turnover (NSV/Net PPE) | B16: ='Revenue Buildup'!B5/B13 | C16: ='Revenue Buildup'!C5/C13 | D16: ='Revenue Buildup'!D5/D13 | E16: ='Revenue Buildup'!E5/E13 | F16: ='Revenue Buildup'!F5/F13 | G16: ='Revenue Buildup'!G5/G13 | H16: ='Revenue Buildup'!H5/H13 | I16: ='Revenue Buildup'!I5/I13 | J16: ='Revenue Buildup'!J5/J13

Sheet Lease Schedule
A1: Lease Schedule
A2: ₹ crore (unless stated) | B2: FY22 | C2: FY23 | D2: FY24 | E2: FY25 | F2: FY26 | G2: FY27E | H2: FY28E | I2: FY29E | J2: FY30E
A3: Lease liability - opening | G3: =F7 | H3: =G7 | I3: =H7 | J3: =I7
A4: + New leases | G4: ='PPE Schedule'!G10 | H4: ='PPE Schedule'!H10 | I4: ='PPE Schedule'!I10 | J4: ='PPE Schedule'!J10
A5: + Interest accretion | D5: 21 | E5: 40 | G5: =G3*'Assumptions'!G18 | H5: =H3*'Assumptions'!H18 | I5: =I3*'Assumptions'!I18 | J5: =J3*'Assumptions'!J18
A6: - Lease payments | D6: -126 | E6: -137 | G6: =-G3*'Assumptions'!G19 | H6: =-H3*'Assumptions'!H19 | I6: =-I3*'Assumptions'!I19 | J6: =-J3*'Assumptions'!J19
A7: Lease liability - closing | B7: 263.7 | C7: 182.2 | D7: 240 | E7: 480 | F7: 407 | G7: =G3+G4+G5+G6 | H7: =H3+H4+H5+H6 | I7: =I3+I4+I5+I6 | J7: =J3+J4+J5+J6
A8: ROU asset (memo) | B8: 260.6 | C8: 172.6 | D8: 227 | E8: 457 | F8: 0 | G8: ='PPE Schedule'!G12 | H8: ='PPE Schedule'!H12 | I8: ='PPE Schedule'!I12 | J8: ='PPE Schedule'!J12
A9: Lease interest in P&L | G9: =G5 | H9: =H5 | I9: =I5 | J9: =J5

Sheet Debt & Cash
A1: Debt & Cash
A2: ₹ crore (unless stated) | B2: FY22 | C2: FY23 | D2: FY24 | E2: FY25 | F2: FY26 | G2: FY27E | H2: FY28E | I2: FY29E | J2: FY30E
A3: Borrowings (gross debt) | B3: 341.7 | C3: 1.1 | D3: 25 | E3: 0 | F3: 6 | G3: 6 | H3: 6 | I3: 6 | J3: 6
A4: Lease liabilities | B4: ='Lease Schedule'!B7 | C4: ='Lease Schedule'!C7 | D4: ='Lease Schedule'!D7 | E4: ='Lease Schedule'!E7 | F4: ='Lease Schedule'!F7 | G4: ='Lease Schedule'!G7 | H4: ='Lease Schedule'!H7 | I4: ='Lease Schedule'!I7 | J4: ='Lease Schedule'!J7
A5: Total debt (incl leases) | B5: =B3+B4 | C5: =C3+C4 | D5: =D3+D4 | E5: =E3+E4 | F5: =F3+F4 | G5: =G3+G4 | H5: =H3+H4 | I5: =I3+I4 | J5: =J3+J4
A6: Cash & equivalents | B6: 54.5 | C6: 115.1 | D6: 1052 | E6: 1328 | F6: 859 | G6: =G9*'Assumptions'!$B$33 | H6: =H9*'Assumptions'!$B$33 | I6: =I9*'Assumptions'!$B$33 | J6: =J9*'Assumptions'!$B$33
A7: Bank deposits | B7: 5.8 | C7: 768.2 | D7: 217 | E7: 702 | F7: 1118 | G7: =G9*'Assumptions'!$B$34 | H7: =H9*'Assumptions'!$B$34 | I7: =I9*'Assumptions'!$B$34 | J7: =J9*'Assumptions'!$B$34
A8: Current investments | B8: 222.1 | C8: 255.8 | D8: 599 | E8: 873 | F8: 1157 | G8: =G9*'Assumptions'!$B$35 | H8: =H9*'Assumptions'!$B$35 | I8: =I9*'Assumptions'!$B$35 | J8: =J9*'Assumptions'!$B$35
A9: Total cash & treasury | B9: ='Balance Sheet'!B18 | C9: ='Balance Sheet'!C18 | D9: ='Balance Sheet'!D18 | E9: ='Balance Sheet'!E18 | F9: ='Balance Sheet'!F18 | G9: ='Balance Sheet'!G18 | H9: ='Balance Sheet'!H18 | I9: ='Balance Sheet'!I18 | J9: ='Balance Sheet'!J18
A10: Net debt / (net cash) | B10: =B5-B9 | C10: =C5-C9 | D10: =D5-D9 | E10: =E5-E9 | F10: =F5-F9 | G10: =G5-G9 | H10: =H5-H9 | I10: =I5-I9 | J10: =J5-J9

Sheet Balance Sheet
A1: Balance Sheet
A2: ₹ crore (unless stated) | B2: FY22 | C2: FY23 | D2: FY24 | E2: FY25 | F2: FY26 | G2: FY27E | H2: FY28E | I2: FY29E | J2: FY30E
A3: ASSETS
A4: Net PPE (incl ROU) | B4: ='PPE Schedule'!B13 | C4: ='PPE Schedule'!C13 | D4: ='PPE Schedule'!D13 | E4: ='PPE Schedule'!E13 | F4: ='PPE Schedule'!F13 | G4: ='PPE Schedule'!G13 | H4: ='PPE Schedule'!H13 | I4: ='PPE Schedule'!I13 | J4: ='PPE Schedule'!J13
A5: Capital work-in-progress | B5: ='PPE Schedule'!B14 | C5: ='PPE Schedule'!C14 | D5: ='PPE Schedule'!D14 | E5: ='PPE Schedule'!E14 | F5: ='PPE Schedule'!F14 | G5: ='PPE Schedule'!G14 | H5: ='PPE Schedule'!H14 | I5: ='PPE Schedule'!I14 | J5: ='PPE Schedule'!J14
A6: Goodwill | B6: 21 | C6: 1.3 | D6: 1 | E6: 1 | F6: 55 | G6: =F6 | H6: =G6 | I6: =H6 | J6: =I6
A7: Other intangible assets | B7: 358 | C7: 372.7 | D7: 349 | E7: 329 | F7: 76 | G7: =F7-'Assumptions'!$B$31 | H7: =G7-'Assumptions'!$B$31 | I7: =H7-'Assumptions'!$B$31 | J7: =I7-'Assumptions'!$B$31
A8: Investment property | B8: 0 | C8: 25.3 | D8: 139 | E8: 75 | F8: 58 | G8: =F8 | H8: =G8 | I8: =H8 | J8: =I8
A9: Investment in JVs | B9: 0 | C9: 10.1 | D9: 46 | E9: 50 | F9: 14 | G9: =F9 | H9: =G9 | I9: =H9 | J9: =I9
A10: Inventories | B10: ='Working Capital'!B4 | C10: ='Working Capital'!C4 | D10: ='Working Capital'!D4 | E10: ='Working Capital'!E4 | F10: ='Working Capital'!F4 | G10: ='Working Capital'!G4 | H10: ='Working Capital'!H4 | I10: ='Working Capital'!I4 | J10: ='Working Capital'!J4
A11: Trade receivables (current) | B11: ='Working Capital'!B3 | C11: ='Working Capital'!C3 | D11: ='Working Capital'!D3 | E11: ='Working Capital'!E3 | F11: ='Working Capital'!F3 | G11: ='Working Capital'!G3 | H11: ='Working Capital'!H3 | I11: ='Working Capital'!I3 | J11: ='Working Capital'!J3
A12: Trade receivables (non-current) | B12: ='Working Capital'!B6 | C12: ='Working Capital'!C6 | D12: ='Working Capital'!D6 | E12: ='Working Capital'!E6 | F12: ='Working Capital'!F6 | G12: ='Working Capital'!G6 | H12: ='Working Capital'!H6 | I12: ='Working Capital'!I6 | J12: ='Working Capital'!J6
A13: Other financial assets | B13: 225.7 | C13: 279.6 | D13: 148 | E13: 640 | F13: 368 | G13: =F13 | H13: =G13 | I13: =H13 | J13: =I13
A14: Deferred tax assets | B14: 147.8 | C14: 157.3 | D14: 177 | E14: 155 | F14: 284 | G14: =F14 | H14: =G14 | I14: =H14 | J14: =I14
A15: Current tax assets | B15: 1261.4 | C15: 1335.6 | D15: 1358 | E15: 1115 | F15: 0 | G15: 0 | H15: 0 | I15: 0 | J15: 0
A16: Other assets (incl tax under protest) | B16: 501.9 | C16: 519.9 | D16: 561 | E16: 524 | F16: 1858 | G16: ='Assumptions'!$B$36+'Assumptions'!$B$37*'Revenue Buildup'!G5/'Revenue Buildup'!F5 | H16: ='Assumptions'!$B$36+'Assumptions'!$B$37*'Revenue Buildup'!H5/'Revenue Buildup'!F5 | I16: ='Assumptions'!$B$36+'Assumptions'!$B$37*'Revenue Buildup'!I5/'Revenue Buildup'!F5 | J16: ='Assumptions'!$B$36+'Assumptions'!$B$37*'Revenue Buildup'!J5/'Revenue Buildup'!F5
A17: Assets held for sale (RCB) | B17: 0 | C17: 0 | D17: 0 | E17: 0 | F17: 701 | G17: 0 | H17: 0 | I17: 0 | J17: 0
A18: Cash + deposits + investments (treasury, PLUG) | B18: =B34-B19 | C18: =C34-C19 | D18: =D34-D19 | E18: =E34-E19 | F18: =F34-F19 | G18: =G34-G19 | H18: =H34-H19 | I18: =I34-I19 | J18: =J34-J19
A19: Non-cash assets subtotal | B19: =B4+B5+B6+B7+B8+B9+B10+B11+B12+B13+B14+B15+B16+B17 | C19: =C4+C5+C6+C7+C8+C9+C10+C11+C12+C13+C14+C15+C16+C17 | D19: =D4+D5+D6+D7+D8+D9+D10+D11+D12+D13+D14+D15+D16+D17 | E19: =E4+E5+E6+E7+E8+E9+E10+E11+E12+E13+E14+E15+E16+E17 | F19: =F4+F5+F6+F7+F8+F9+F10+F11+F12+F13+F14+F15+F16+F17 | G19: =G4+G5+G6+G7+G8+G9+G10+G11+G12+G13+G14+G15+G16+G17 | H19: =H4+H5+H6+H7+H8+H9+H10+H11+H12+H13+H14+H15+H16+H17 | I19: =I4+I5+I6+I7+I8+I9+I10+I11+I12+I13+I14+I15+I16+I17 | J19: =J4+J5+J6+J7+J8+J9+J10+J11+J12+J13+J14+J15+J16+J17
A20: TOTAL ASSETS | B20: =B19+B18 | C20: =C19+C18 | D20: =D19+D18 | E20: =E19+E18 | F20: =F19+F18 | G20: =G19+G18 | H20: =H19+H18 | I20: =I19+I18 | J20: =J19+J18
A21: EQUITY & LIABILITIES
A22: Total equity | B22: 4874.8 | C22: 5999.5 | D22: 7121 | E22: 8104 | F22: 8957 | G22: =F22+'Income Statement'!G19-G23 | H22: =G22+'Income Statement'!H19-H23 | I22: =H22+'Income Statement'!I19-I23 | J22: =I22+'Income Statement'!J19-J23
A23: Memo: dividend paid | G23: ='Income Statement'!G19*'Assumptions'!G12 | H23: ='Income Statement'!H19*'Assumptions'!H12 | I23: ='Income Statement'!I19*'Assumptions'!I12 | J23: ='Income Statement'!J19*'Assumptions'!J12
A24: Borrowings | B24: ='Debt & Cash'!B3 | C24: ='Debt & Cash'!C3 | D24: ='Debt & Cash'!D3 | E24: ='Debt & Cash'!E3 | F24: ='Debt & Cash'!F3 | G24: ='Debt & Cash'!G3 | H24: ='Debt & Cash'!H3 | I24: ='Debt & Cash'!I3 | J24: ='Debt & Cash'!J3
A25: Lease liabilities | B25: ='Lease Schedule'!B7 | C25: ='Lease Schedule'!C7 | D25: ='Lease Schedule'!D7 | E25: ='Lease Schedule'!E7 | F25: ='Lease Schedule'!F7 | G25: ='Lease Schedule'!G7 | H25: ='Lease Schedule'!H7 | I25: ='Lease Schedule'!I7 | J25: ='Lease Schedule'!J7
A26: Trade payables | B26: ='Working Capital'!B5 | C26: ='Working Capital'!C5 | D26: ='Working Capital'!D5 | E26: ='Working Capital'!E5 | F26: ='Working Capital'!F5 | G26: ='Working Capital'!G5 | H26: ='Working Capital'!H5 | I26: ='Working Capital'!I5 | J26: ='Working Capital'!J5
A27: Deferred tax liabilities | B27: 48.3 | C27: 45.1 | D27: 73 | E27: 72 | F27: 18 | G27: =F27 | H27: =G27 | I27: =H27 | J27: =I27
A28: Provisions | B28: 502.9 | C28: 385.4 | D28: 383 | E28: 391 | F28: 541 | G28: ='Revenue Buildup'!G5*'Assumptions'!G25 | H28: ='Revenue Buildup'!H5*'Assumptions'!H25 | I28: ='Revenue Buildup'!I5*'Assumptions'!I25 | J28: ='Revenue Buildup'!J5*'Assumptions'!J25
A29: Current tax liabilities | B29: 276.5 | C29: 282.9 | D29: 332 | E29: 380 | F29: 571 | G29: =F29*'Assumptions'!$B$38 | H29: =G29*'Assumptions'!$B$38 | I29: =H29*'Assumptions'!$B$38 | J29: =I29*'Assumptions'!$B$38
A30: Other financial liabilities | B30: 182.3 | C30: 284.6 | D30: 276 | E30: 477 | F30: 273 | G30: =F30 | H30: =G30 | I30: =H30 | J30: =I30
A31: Other current liabilities | B31: 839 | C31: 798.2 | D31: 845 | E31: 1105 | F31: 986 | G31: ='Revenue Buildup'!G5*'Assumptions'!G24 | H31: ='Revenue Buildup'!H5*'Assumptions'!H24 | I31: ='Revenue Buildup'!I5*'Assumptions'!I24 | J31: ='Revenue Buildup'!J5*'Assumptions'!J24
A32: Liabilities of disposal group (RCB) | B32: 0 | C32: 0 | D32: 0 | E32: 0 | F32: 327 | G32: 0 | H32: 0 | I32: 0 | J32: 0
A33: Total liabilities (excl equity) | B33: =B24+B25+B26+B27+B28+B29+B30+B31+B32 | C33: =C24+C25+C26+C27+C28+C29+C30+C31+C32 | D33: =D24+D25+D26+D27+D28+D29+D30+D31+D32 | E33: =E24+E25+E26+E27+E28+E29+E30+E31+E32 | F33: =F24+F25+F26+F27+F28+F29+F30+F31+F32 | G33: =G24+G25+G26+G27+G28+G29+G30+G31+G32 | H33: =H24+H25+H26+H27+H28+H29+H30+H31+H32 | I33: =I24+I25+I26+I27+I28+I29+I30+I31+I32 | J33: =J24+J25+J26+J27+J28+J29+J30+J31+J32
A34: TOTAL EQUITY & LIABILITIES | B34: =B22+B33 | C34: =C22+C33 | D34: =D22+D33 | E34: =E22+E33 | F34: =F22+F33 | G34: =G22+G33 | H34: =H22+H33 | I34: =I22+I33 | J34: =J22+J33
A35: Balance check (Assets - E&L) | B35: =B20-B34 | C35: =C20-C34 | D35: =D20-D34 | E35: =E20-E34 | F35: =F20-F34 | G35: =G20-G34 | H35: =H20-H34 | I35: =I20-I34 | J35: =J20-J34

Sheet Cash Flow
A1: Cash Flow
A2: ₹ crore (unless stated) | B2: FY22 | C2: FY23 | D2: FY24 | E2: FY25 | F2: FY26 | G2: FY27E | H2: FY28E | I2: FY29E | J2: FY30E
A3: PAT (reported) | G3: ='Income Statement'!G19 | H3: ='Income Statement'!H19 | I3: ='Income Statement'!I19 | J3: ='Income Statement'!J19
A4: + Depreciation & amortisation | G4: ='Income Statement'!G10 | H4: ='Income Statement'!H10 | I4: ='Income Statement'!I10 | J4: ='Income Statement'!J10
A5: + Lease interest (add back) | G5: ='Lease Schedule'!G5 | H5: ='Lease Schedule'!H5 | I5: ='Lease Schedule'!I5 | J5: ='Lease Schedule'!J5
A6: +/- Change in working capital | G6: =('Balance Sheet'!G26-'Balance Sheet'!F26)+('Balance Sheet'!G28-'Balance Sheet'!F28)+('Balance Sheet'!G29-'Balance Sheet'!F29)+('Balance Sheet'!G31-'Balance Sheet'!F31)-('Balance Sheet'!G10-'Balance Sheet'!F10)-('Balance Sheet'!G11-'Balance Sheet'!F11)-('Balance Sheet'!G12-'Balance Sheet'!F12)-('Balance Sheet'!G16-'Balance Sheet'!F16) | H6: =('Balance Sheet'!H26-'Balance Sheet'!G26)+('Balance Sheet'!H28-'Balance Sheet'!G28)+('Balance Sheet'!H29-'Balance Sheet'!G29)+('Balance Sheet'!H31-'Balance Sheet'!G31)-('Balance Sheet'!H10-'Balance Sheet'!G10)-('Balance Sheet'!H11-'Balance Sheet'!G11)-('Balance Sheet'!H12-'Balance Sheet'!G12)-('Balance Sheet'!H16-'Balance Sheet'!G16) | I6: =('Balance Sheet'!I26-'Balance Sheet'!H26)+('Balance Sheet'!I28-'Balance Sheet'!H28)+('Balance Sheet'!I29-'Balance Sheet'!H29)+('Balance Sheet'!I31-'Balance Sheet'!H31)-('Balance Sheet'!I10-'Balance Sheet'!H10)-('Balance Sheet'!I11-'Balance Sheet'!H11)-('Balance Sheet'!I12-'Balance Sheet'!H12)-('Balance Sheet'!I16-'Balance Sheet'!H16) | J6: =('Balance Sheet'!J26-'Balance Sheet'!I26)+('Balance Sheet'!J28-'Balance Sheet'!I28)+('Balance Sheet'!J29-'Balance Sheet'!I29)+('Balance Sheet'!J31-'Balance Sheet'!I31)-('Balance Sheet'!J10-'Balance Sheet'!I10)-('Balance Sheet'!J11-'Balance Sheet'!I11)-('Balance Sheet'!J12-'Balance Sheet'!I12)-('Balance Sheet'!J16-'Balance Sheet'!I16)
A7: Operating cash flow (CFO) | G7: =G3+G4+G5+G6 | H7: =H3+H4+H5+H6 | I7: =I3+I4+I5+I6 | J7: =J3+J4+J5+J6
A8: - Capex | G8: =-'PPE Schedule'!G5 | H8: =-'PPE Schedule'!H5 | I8: =-'PPE Schedule'!I5 | J8: =-'PPE Schedule'!J5
A9: + RCB / held-for-sale disposal | G9: =('Balance Sheet'!F17-'Balance Sheet'!G17)-('Balance Sheet'!F32-'Balance Sheet'!G32) | H9: =('Balance Sheet'!G17-'Balance Sheet'!H17)-('Balance Sheet'!G32-'Balance Sheet'!H32) | I9: =('Balance Sheet'!H17-'Balance Sheet'!I17)-('Balance Sheet'!H32-'Balance Sheet'!I32) | J9: =('Balance Sheet'!I17-'Balance Sheet'!J17)-('Balance Sheet'!I32-'Balance Sheet'!J32)
A10: Investing cash flow (CFI) | G10: =G8+G9 | H10: =H8+H9 | I10: =I8+I9 | J10: =J8+J9
A11: - Dividends paid | G11: =-'Balance Sheet'!G23 | H11: =-'Balance Sheet'!H23 | I11: =-'Balance Sheet'!I23 | J11: =-'Balance Sheet'!J23
A12: - Lease payments | G12: ='Lease Schedule'!G6 | H12: ='Lease Schedule'!H6 | I12: ='Lease Schedule'!I6 | J12: ='Lease Schedule'!J6
A13: +/- Change in borrowings | G13: ='Balance Sheet'!G24-'Balance Sheet'!F24 | H13: ='Balance Sheet'!H24-'Balance Sheet'!G24 | I13: ='Balance Sheet'!I24-'Balance Sheet'!H24 | J13: ='Balance Sheet'!J24-'Balance Sheet'!I24
A14: Financing cash flow (CFF) | G14: =G11+G12+G13 | H14: =H11+H12+H13 | I14: =I11+I12+I13 | J14: =J11+J12+J13
A15: Net change in cash & treasury | G15: =G7+G10+G14 | H15: =H7+H10+H14 | I15: =I7+I10+I14 | J15: =J7+J10+J14
A16: Opening treasury | G16: ='Balance Sheet'!F18 | H16: ='Balance Sheet'!G18 | I16: ='Balance Sheet'!H18 | J16: ='Balance Sheet'!I18
A17: Closing treasury (= opening + net) | G17: =G16+G15 | H17: =H16+H15 | I17: =I16+I15 | J17: =J16+J15
A18: Tie check vs Balance Sheet | G18: =G17-'Balance Sheet'!G18 | H18: =H17-'Balance Sheet'!H18 | I18: =I17-'Balance Sheet'!I18 | J18: =J17-'Balance Sheet'!J18

Sheet DCF
A1: DCF VALUATION — 2-stage FCFF (explicit FY27-30 + premiumisation fade FY31-36)
A3: ₹ crore | C3: FY27E | D3: FY28E | E3: FY29E | F3: FY30E | G3: FY31 | H3: FY32 | I3: FY33 | J3: FY34 | K3: FY35 | L3: FY36
A4: NSV growth % (fade inputs) | G4: 0.085 | H4: 0.08 | I4: 0.075 | J4: 0.07 | K4: 0.065 | L4: 0.06
A5: Net Sales Value | C5: ='Revenue Buildup'!G5 | D5: ='Revenue Buildup'!H5 | E5: ='Revenue Buildup'!I5 | F5: ='Revenue Buildup'!J5 | G5: ='Revenue Buildup'!J5*(1+G4) | H5: =G5*(1+H4) | I5: =H5*(1+I4) | J5: =I5*(1+J4) | K5: =J5*(1+K4) | L5: =K5*(1+L4)
A6: EBITDA margin % | C6: ='Income Statement'!G9/'Income Statement'!G3 | D6: ='Income Statement'!H9/'Income Statement'!H3 | E6: ='Income Statement'!I9/'Income Statement'!I3 | F6: ='Income Statement'!J9/'Income Statement'!J3 | G6: 0.2083 | H6: 0.2117 | I6: 0.215 | J6: 0.2183 | K6: 0.2217 | L6: 0.225
A7: EBITDA | C7: ='Income Statement'!G9 | D7: ='Income Statement'!H9 | E7: ='Income Statement'!I9 | F7: ='Income Statement'!J9 | G7: =G5*G6 | H7: =H5*H6 | I7: =I5*I6 | J7: =J5*J6 | K7: =K5*K6 | L7: =L5*L6
A8: Depreciation & amortisation | C8: ='Income Statement'!G10 | D8: ='Income Statement'!H10 | E8: ='Income Statement'!I10 | F8: ='Income Statement'!J10 | G8: =G5*('Income Statement'!J10/'Revenue Buildup'!J5) | H8: =H5*('Income Statement'!J10/'Revenue Buildup'!J5) | I8: =I5*('Income Statement'!J10/'Revenue Buildup'!J5) | J8: =J5*('Income Statement'!J10/'Revenue Buildup'!J5) | K8: =K5*('Income Statement'!J10/'Revenue Buildup'!J5) | L8: =L5*('Income Statement'!J10/'Revenue Buildup'!J5)
A9: EBIT | C9: =C7-C8 | D9: =D7-D8 | E9: =E7-E8 | F9: =F7-F8 | G9: =G7-G8 | H9: =H7-H8 | I9: =I7-I8 | J9: =J7-J8 | ... L9: =L7-L8
A10: Tax on EBIT | C10: =C9*'Assumptions'!G11 | D10: =D9*'Assumptions'!H11 | E10: =E9*'Assumptions'!I11 | F10: =F9*'Assumptions'!J11 | G10: =G9*0.255 | H10: =H9*0.255 | I10: =I9*0.255 | J10: =J9*0.255 | K10: =K9*0.255 | L10: =L9*0.255
A11: NOPAT | C11: =C9-C10 | D11: =D9-D10 | E11: =E9-E10 | F11: =F9-F10 | G11: =G9-G10 | H11: =H9-H10 | I11: =I9-I10 | J11: =J9-J10 | ... L11: =L9-L10
A12: Capex | C12: ='PPE Schedule'!G5 | D12: ='PPE Schedule'!H5 | E12: ='PPE Schedule'!I5 | F12: ='PPE Schedule'!J5 | G12: =G5*0.018 | H12: =H5*0.018 | I12: =I5*0.018 | J12: =J5*0.018 | K12: =K5*0.018 | L12: =L5*0.018
A13: New leases | C13: ='PPE Schedule'!G10 | D13: ='PPE Schedule'!H10 | E13: ='PPE Schedule'!I10 | F13: ='PPE Schedule'!J10 | G13: =G5*0.016 | H13: =H5*0.016 | I13: =I5*0.016 | J13: =J5*0.016 | K13: =K5*0.016 | L13: =L5*0.016
A14: Increase in working capital | C14: =('Balance Sheet'!G10+'Balance Sheet'!G11+'Balance Sheet'!G12-'Balance Sheet'!G26-'Balance Sheet'!G31)-('Balance Sheet'!F10+'Balance Sheet'!F11+'Balance Sheet'!F12-'Balance Sheet'!F26-'Balance Sheet'!F31) | D14: =('Balance Sheet'!H10+'Balance Sheet'!H11+'Balance Sheet'!H12-'Balance Sheet'!H26-'Balance Sheet'!H31)-('Balance Sheet'!G10+'Balance Sheet'!G11+'Balance Sheet'!G12-'Balance Sheet'!G26-'Balance Sheet'!G31) | E14: =('Balance Sheet'!I10+'Balance Sheet'!I11+'Balance Sheet'!I12-'Balance Sheet'!I26-'Balance Sheet'!I31)-('Balance Sheet'!H10+'Balance Sheet'!H11+'Balance Sheet'!H12-'Balance Sheet'!H26-'Balance Sheet'!H31) | F14: =('Balance Sheet'!J10+'Balance Sheet'!J11+'Balance Sheet'!J12-'Balance Sheet'!J26-'Balance Sheet'!J31)-('Balance Sheet'!I10+'Balance Sheet'!I11+'Balance Sheet'!I12-'Balance Sheet'!I26-'Balance Sheet'!I31) | G14: =G5*G4*0.16 | H14: =H5*H4*0.16 | I14: =I5*I4*0.16 | J14: =J5*J4*0.16 | K14: =K5*K4*0.16 | L14: =L5*L4*0.16
A15: Free Cash Flow to Firm (FCFF) | C15: =C11+C8-C12-C13-C14 | D15: =D11+D8-D12-D13-D14 | E15: =E11+E8-E12-E13-E14 | F15: =F11+F8-F12-F13-F14 | G15: =G11+G8-G12-G13-G14 | H15: =H11+H8-H12-H13-H14 | I15: =I11+I8-I12-I13-I14 | J15: =J11+J8-J12-J13-J14 | ... L15: =L11+L8-L12-L13-L14
A16: Discount period | C16: 1 | D16: 2 | E16: 3 | F16: 4 | G16: 5 | H16: 6 | I16: 7 | J16: 8 | K16: 9 | L16: 10
A18: DCF BRIDGE
A19: WACC | B19: ='Assumptions'!$B$40
A20: Terminal growth (g) | B20: ='Assumptions'!$B$41
A21: PV of explicit + fade FCFF | B21: =SUMPRODUCT($C$15:$L$15,(1+$B$19)^(-$C$16:$L$16))
A22: Terminal value (FY36) | B22: =$L$15*(1+$B$20)/($B$19-$B$20)
A23: PV of terminal value | B23: =$B$22/(1+$B$19)^10
A24: Enterprise Value | B24: =$B$21+$B$23
A25: Add: Net cash | B25: =-'Debt & Cash'!F10
A26: Add: RCB optionality | B26: ='Assumptions'!$B$39
A27: Equity Value | B27: =$B$24+$B$25+$B$26
A28: DCF value per share (₹) | B28: =$B$27/'Assumptions'!$B$28
A30: SENSITIVITY — DCF value/share (₹): WACC (rows) x terminal g (cols)
A31: WACC \ g | B31: 0.05 | C31: 0.055 | D31: 0.06 | E31: 0.065 | F31: 0.07
A32: 0.095 | B32: =(SUMPRODUCT($C$15:$L$15,(1+$A$32)^(-$C$16:$L$16))+($L$15*(1+B$31)/($A$32-B$31))/(1+$A$32)^10+-'Debt & Cash'!F10+'Assumptions'!$B$39)/'Assumptions'!$B$28 | C32: =(SUMPRODUCT($C$15:$L$15,(1+$A$32)^(-$C$16:$L$16))+($L$15*(1+C$31)/($A$32-C$31))/(1+$A$32)^10+-'Debt & Cash'!F10+'Assumptions'!$B$39)/'Assumptions'!$B$28 | D32: =(SUMPRODUCT($C$15:$L$15,(1+$A$32)^(-$C$16:$L$16))+($L$15*(1+D$31)/($A$32-D$31))/(1+$A$32)^10+-'Debt & Cash'!F10+'Assumptions'!$B$39)/'Assumptions'!$B$28 | E32: =(SUMPRODUCT($C$15:$L$15,(1+$A$32)^(-$C$16:$L$16))+($L$15*(1+E$31)/($A$32-E$31))/(1+$A$32)^10+-'Debt & Cash'!F10+'Assumptions'!$B$39)/'Assumptions'!$B$28 | F32: =(SUMPRODUCT($C$15:$L$15,(1+$A$32)^(-$C$16:$L$16))+($L$15*(1+F$31)/($A$32-F$31))/(1+$A$32)^10+-'Debt & Cash'!F10+'Assumptions'!$B$39)/'Assumptions'!$B$28
A33: 0.1 | B33: =(SUMPRODUCT($C$15:$L$15,(1+$A$33)^(-$C$16:$L$16))+($L$15*(1+B$31)/($A$33-B$31))/(1+$A$33)^10+-'Debt & Cash'!F10+'Assumptions'!$B$39)/'Assumptions'!$B$28 | C33: =(SUMPRODUCT($C$15:$L$15,(1+$A$33)^(-$C$16:$L$16))+($L$15*(1+C$31)/($A$33-C$31))/(1+$A$33)^10+-'Debt & Cash'!F10+'Assumptions'!$B$39)/'Assumptions'!$B$28 | D33: =(SUMPRODUCT($C$15:$L$15,(1+$A$33)^(-$C$16:$L$16))+($L$15*(1+D$31)/($A$33-D$31))/(1+$A$33)^10+-'Debt & Cash'!F10+'Assumptions'!$B$39)/'Assumptions'!$B$28 | E33: =(SUMPRODUCT($C$15:$L$15,(1+$A$33)^(-$C$16:$L$16))+($L$15*(1+E$31)/($A$33-E$31))/(1+$A$33)^10+-'Debt & Cash'!F10+'Assumptions'!$B$39)/'Assumptions'!$B$28 | F33: =(SUMPRODUCT($C$15:$L$15,(1+$A$33)^(-$C$16:$L$16))+($L$15*(1+F$31)/($A$33-F$31))/(1+$A$33)^10+-'Debt & Cash'!F10+'Assumptions'!$B$39)/'Assumptions'!$B$28
A34: 0.105 | B34: =(SUMPRODUCT($C$15:$L$15,(1+$A$34)^(-$C$16:$L$16))+($L$15*(1+B$31)/($A$34-B$31))/(1+$A$34)^10+-'Debt & Cash'!F10+'Assumptions'!$B$39)/'Assumptions'!$B$28 | C34: =(SUMPRODUCT($C$15:$L$15,(1+$A$34)^(-$C$16:$L$16))+($L$15*(1+C$31)/($A$34-C$31))/(1+$A$34)^10+-'Debt & Cash'!F10+'Assumptions'!$B$39)/'Assumptions'!$B$28 | D34: =(SUMPRODUCT($C$15:$L$15,(1+$A$34)^(-$C$16:$L$16))+($L$15*(1+D$31)/($A$34-D$31))/(1+$A$34)^10+-'Debt & Cash'!F10+'Assumptions'!$B$39)/'Assumptions'!$B$28 | E34: =(SUMPRODUCT($C$15:$L$15,(1+$A$34)^(-$C$16:$L$16))+($L$15*(1+E$31)/($A$34-E$31))/(1+$A$34)^10+-'Debt & Cash'!F10+'Assumptions'!$B$39)/'Assumptions'!$B$28 | F34: =(SUMPRODUCT($C$15:$L$15,(1+$A$34)^(-$C$16:$L$16))+($L$15*(1+F$31)/($A$34-F$31))/(1+$A$34)^10+-'Debt & Cash'!F10+'Assumptions'!$B$39)/'Assumptions'!$B$28
A35: 0.11 | B35: =(SUMPRODUCT($C$15:$L$15,(1+$A$35)^(-$C$16:$L$16))+($L$15*(1+B$31)/($A$35-B$31))/(1+$A$35)^10+-'Debt & Cash'!F10+'Assumptions'!$B$39)/'Assumptions'!$B$28 | C35: =(SUMPRODUCT($C$15:$L$15,(1+$A$35)^(-$C$16:$L$16))+($L$15*(1+C$31)/($A$35-C$31))/(1+$A$35)^10+-'Debt & Cash'!F10+'Assumptions'!$B$39)/'Assumptions'!$B$28 | D35: =(SUMPRODUCT($C$15:$L$15,(1+$A$35)^(-$C$16:$L$16))+($L$15*(1+D$31)/($A$35-D$31))/(1+$A$35)^10+-'Debt & Cash'!F10+'Assumptions'!$B$39)/'Assumptions'!$B$28 | E35: =(SUMPRODUCT($C$15:$L$15,(1+$A$35)^(-$C$16:$L$16))+($L$15*(1+E$31)/($A$35-E$31))/(1+$A$35)^10+-'Debt & Cash'!F10+'Assumptions'!$B$39)/'Assumptions'!$B$28 | F35: =(SUMPRODUCT($C$15:$L$15,(1+$A$35)^(-$C$16:$L$16))+($L$15*(1+F$31)/($A$35-F$31))/(1+$A$35)^10+-'Debt & Cash'!F10+'Assumptions'!$B$39)/'Assumptions'!$B$28
A36: 0.115 | B36: =(SUMPRODUCT($C$15:$L$15,(1+$A$36)^(-$C$16:$L$16))+($L$15*(1+B$31)/($A$36-B$31))/(1+$A$36)^10+-'Debt & Cash'!F10+'Assumptions'!$B$39)/'Assumptions'!$B$28 | C36: =(SUMPRODUCT($C$15:$L$15,(1+$A$36)^(-$C$16:$L$16))+($L$15*(1+C$31)/($A$36-C$31))/(1+$A$36)^10+-'Debt & Cash'!F10+'Assumptions'!$B$39)/'Assumptions'!$B$28 | D36: =(SUMPRODUCT($C$15:$L$15,(1+$A$36)^(-$C$16:$L$16))+($L$15*(1+D$31)/($A$36-D$31))/(1+$A$36)^10+-'Debt & Cash'!F10+'Assumptions'!$B$39)/'Assumptions'!$B$28 | E36: =(SUMPRODUCT($C$15:$L$15,(1+$A$36)^(-$C$16:$L$16))+($L$15*(1+E$31)/($A$36-E$31))/(1+$A$36)^10+-'Debt & Cash'!F10+'Assumptions'!$B$39)/'Assumptions'!$B$28 | F36: =(SUMPRODUCT($C$15:$L$15,(1+$A$36)^(-$C$16:$L$16))+($L$15*(1+F$31)/($A$36-F$31))/(1+$A$36)^10+-'Debt & Cash'!F10+'Assumptions'!$B$39)/'Assumptions'!$B$28
A38: Live formulas: every figure recalculates from the Assumptions sheet. Green = links to other sheets; black = calculations; blue = inputs.

Sheet Comps
A1: TRADING COMPARABLES (market data ~10-Jun-2026)
A2: Company | B2: MktCap | C2: EV | D2: NetRev FY26 | E2: EBITDA FY26 | F2: PAT FY26 | G2: EV/EBITDA | H2: EV/Sales | I2: P/E | J2: EBITDA mgn
A3: United Spirits (USL) | B3: 91639 | C3: 88918 | D3: ='Revenue Buildup'!F5 | E3: ='Income Statement'!F9 | F3: ='Income Statement'!F17 | G3: =C3/E3 | H3: =C3/D3 | I3: =B3/F3 | J3: =E3/D3
A4: Radico Khaitan | B4: 46854 | C4: 47264 | D4: 6050 | E4: 1033 | F4: 604 | G4: =C4/E4 | H4: =C4/D4 | I4: =B4/F4 | J4: =E4/D4
A5: Allied Blenders (ABDL) | B5: 11500 | C5: 12100 | D5: 3949 | E5: 568 | F5: 266 | G5: =C5/E5 | H5: =C5/D5 | I5: =B5/F5 | J5: =E5/D5
A6: Tilaknagar Inds | B6: 10500 | C6: 14400 | D6: 2346 | E6: 445 | F6: 145 | G6: =C6/E6 | H6: =C6/D6 | I6: =B6/F6 | J6: =E6/D6
A7: Globus Spirits | B7: 2839 | C7: 3198 | D7: 3625 | E7: 360 | F7: 91 | G7: =C7/E7 | H7: =C7/D7 | I7: =B7/F7 | J7: =E7/D7
A8: Peer median (ex-USL) | G8: =MEDIAN(G4:G7) | H8: =MEDIAN(H4:H7) | I8: =MEDIAN(I4:I7) | J8: =MEDIAN(J4:J7)
A10: USL NetRev/EBITDA/PAT linked live to model (green). Peers hard-coded from public data; Tilaknagar PAT normalised; ABDL figures approximate.

Sheet Historical Valuation
A1: HISTORICAL VALUATION (FY22-FY26)
A2: ₹ crore / x | B2: FY22 | C2: FY23 | D2: FY24 | E2: FY25 | F2: FY26
A3: Market capitalisation | B3: 64607 | C3: 55010 | D3: 82500 | E3: 101924 | F3: 91639
A4: PAT (reported) | B4: ='Income Statement'!B19 | C4: ='Income Statement'!C19 | D4: ='Income Statement'!D19 | E4: ='Income Statement'!E19 | F4: ='Income Statement'!F19
A5: P/E (x) | B5: =B3/B4 | C5: =C3/C4 | D5: =D3/D4 | E5: =E3/E4 | F5: =F3/F4
A6: Net cash | B6: -323 | C6: 955.8 | D6: 1603 | E6: 2423 | F6: 2721
A7: Enterprise value | B7: =B3-B6 | C7: =C3-C6 | D7: =D3-D6 | E7: =E3-E6 | F7: =F3-F6
A8: Core EBITDA | B8: ='Income Statement'!B9 | C8: ='Income Statement'!C9 | D8: ='Income Statement'!D9 | E8: ='Income Statement'!E9 | F8: ='Income Statement'!F9
A9: EV/EBITDA (x) | B9: =B7/B8 | C9: =C7/C8 | D9: =D7/D8 | E9: =E7/E8 | F9: =F7/F8
A11: 5-yr avg P/E ~60x; current ~50x (below average). PAT & EBITDA linked live to Income Statement (green).

Sheet Scenarios
A1: SCENARIO ANALYSIS (FY30E outcomes & 12-m target)
A2: Metric | B2: Bear | C2: Base | D2: Bull
A3: FY30E Net Sales | B3: 15836 | C3: 18019 | D3: 19591
A4: FY30E EBITDA | B4: 2977 | C4: 3694 | D4: 4310
A5: FY30E PAT | B5: 2072 | C5: 2592 | D5: 3047
A6: FY30E EPS (₹) | B6: 28.47 | C6: 35.62 | D6: 41.86
A7: NSV CAGR FY26-30 | B7: 0.0616 | C7: 0.0965 | D7: 0.1196
A8: EPS CAGR FY26-30 | B8: 0.024 | C8: 0.083 | D8: 0.1276
A9: DCF value (₹) | B9: 454 | C9: 743 | D9: 1024
A10: Relative value (₹) | B10: 978 | C10: 1430 | D10: 1811
A11: Target price (₹) | B11: 768 | C11: 1155 | D11: 1496
A12: Upside/(downside) vs ₹1,259 | B12: -0.3898 | C12: -0.0824 | D12: 0.1883
A14: Scenario outputs from separate runs of the model engine (bull/base/bear assumption sets). Base ties to the live DCF & relative valuation.
