Workbook

Sheet Cash Flow
B1: UNITED SPIRITS — HISTORICAL CASH FLOW STATEMENT (consolidated, INR cr)
B2: Particulars (INR crore) | C2: FY2017 | D2: FY2018 | E2: FY2019 | F2: FY2020 | G2: FY2021 | H2: FY2022 | I2: FY2023 | J2: FY2024 | K2: FY2025 | L2: FY2026
B3: Net Profit After Tax (PAT) | C3: 93 | D3: 651.9 | E3: 683.6 | F3: 620.6 | G3: 362.1 | H3: 810.6 | I3: 1125.8 | J3: 1408 | K3: 1582 | L3: 1838
B4: + Depreciation & Amortisation | C4: 188.6 | D4: 192.3 | E4: 214.7 | F4: 285.3 | G4: 299.1 | H4: 303.8 | I4: 282.5 | J4: 275 | K4: 283 | L4: 289
B5: +/- Other Non-Cash Adjustments | C5: 333.1 | D5: -167.8 | E5: 7.6 | F5: -649.9 | G5: 1024.4 | H5: 8.9 | I5: -726.1 | J5: -356.1 | K5: 119 | L5: -185
B6: +/- Change in Net Working Capital | C6: =2626.2-'Treasury & NWC'!C20 | D6: ='Treasury & NWC'!C20-'Treasury & NWC'!D20 | E6: ='Treasury & NWC'!D20-'Treasury & NWC'!E20 | F6: ='Treasury & NWC'!E20-'Treasury & NWC'!F20 | G6: ='Treasury & NWC'!F20-'Treasury & NWC'!G20 | H6: ='Treasury & NWC'!G20-'Treasury & NWC'!H20 | I6: ='Treasury & NWC'!H20-'Treasury & NWC'!I20 | J6: ='Treasury & NWC'!I20-'Treasury & NWC'!J20 | K6: ='Treasury & NWC'!J20-'Treasury & NWC'!K20 | L6: ='Treasury & NWC'!K20-'Treasury & NWC'!L20
B7: Cash Flow from Operations (CFO) | C7: =C3+C4+C5+C6 | D7: =D3+D4+D5+D6 | E7: =E3+E4+E5+E6 | F7: =F3+F4+F5+F6 | G7: =G3+G4+G5+G6 | H7: =H3+H4+H5+H6 | I7: =I3+I4+I5+I6 | J7: =J3+J4+J5+J6 | ... L7: =L3+L4+L5+L6
B8: + Interest Income Received | C8: 19.7 | D8: 4.2 | E8: 6.4 | F8: 6.2 | G8: 11.1 | H8: 6.4 | I8: 20.4 | J8: 42 | K8: 36 | L8: 67
B9: - Capital Expenditure (Capex) | C9: 311 | D9: 184.3 | E9: 173 | F9: 211.6 | G9: 158.9 | H9: 134 | I9: 136.6 | J9: 98 | K9: 162 | L9: 181
B10: Free Cash Flow (FCF) | C10: =C7+C8-C9 | D10: =D7+D8-D9 | E10: =E7+E8-E9 | F10: =F7+F8-F9 | G10: =G7+G8-G9 | H10: =H7+H8-H9 | I10: =I7+I8-I9 | J10: =J7+J8-J9 | ... L10: =L7+L8-L9
B11: - Dividends Paid | C11: 0 | D11: 0 | E11: 0 | F11: 0 | G11: 0 | H11: 0 | I11: 0 | J11: 284 | K11: 355 | L11: 1263
B12: - Lease Principal Repayment | C12: 8.6 | D12: 0 | E12: 0 | F12: 64.5 | G12: 80.7 | H12: 100.2 | I12: 124 | J12: 126 | K12: 137 | L12: 144
B13: +/- Net Borrowings Drawn / (Repaid) | C13: -91.1 | D13: -713.3 | E13: -579 | F13: -494.3 | G13: -1484.1 | H13: -537.7 | I13: -340.6 | J13: 24 | K13: -25 | L13: -6
B14: +/- Other Investing/Financing & Interest (net) | C14: -306.5 | D14: 137.1 | E14: -175.9 | F14: -228.4 | G14: -94.7 | H14: -13.4 | I14: 822.8 | J14: 52.9 | K14: -269 | L14: 299
B15: Net Change in Treasury | C15: =C10-C11-C12+C13+C14 | D15: =D10-D11-D12+D13+D14 | E15: =E10-E11-E12+E13+E14 | F15: =F10-F11-F12+F13+F14 | G15: =G10-G11-G12+G13+G14 | H15: =H10-H11-H12+H13+H14 | I15: =I10-I11-I12+I13+I14 | J15: =J10-J11-J12+J13+J14 | ... L15: =L10-L11-L12+L13+L14
B16: Opening Treasury Balance | C16: 138 | D16: =C17 | E16: =D17 | F16: =E17 | G16: =F17 | H16: =G17 | I16: =H17 | J16: =I17 | K16: =J17 | L16: =K17
B17: Closing Treasury Balance | C17: =C16+C15 | D17: =D16+D15 | E17: =E16+E15 | F17: =F16+F15 | G17: =G16+G15 | H17: =H16+H15 | I17: =I16+I15 | J17: =J16+J15 | ... L17: =L16+L15
B18: Closing Treasury (Balance Sheet) | C18: ='Treasury & NWC'!C19 | D18: ='Treasury & NWC'!D19 | E18: ='Treasury & NWC'!E19 | F18: ='Treasury & NWC'!F19 | G18: ='Treasury & NWC'!G19 | H18: ='Treasury & NWC'!H19 | I18: ='Treasury & NWC'!I19 | J18: ='Treasury & NWC'!J19 | ... L18: ='Treasury & NWC'!L19
B19: Tie Check vs Balance Sheet | C19: =C17-C18 | D19: =D17-D18 | E19: =E17-E18 | F19: =F17-F18 | G19: =G17-G18 | H19: =H17-H18 | I19: =I17-I18 | J19: =J17-J18 | ... L19: =L17-L18
B21: Colour key: BLUE = reported input BLACK = formula (this sheet) GREEN = link to another sheet
B22: CFO = PAT + D&A + Other Non-Cash Adj +/- Change in NWC (Other Non-Cash Adj sized so CFO = reported statutory CFO).
B23: FCF = CFO + Interest Income Received - Capex.
B24: Net Change in Treasury = FCF - Dividends - Lease principal +/- Net borrowings +/- Other investing/financing & interest.
B25: 'Other Investing/Financing & Interest (net)' bridges FCF to the change in the broad treasury balance: it captures
B26: interest PAID on debt & leases, proceeds from business/subsidiary/asset disposals, JV investments, loans and FX.
B27: Treasury = Cash & cash equivalents + Bank balances + Current investments (per template). Tie check = 0.0 every year.

Sheet Treasury & NWC
B1: UNITED SPIRITS — TREASURY & NET WORKING CAPITAL (reported consolidated, INR cr)
B2: Particulars (INR crore) | C2: FY2017 | D2: FY2018 | E2: FY2019 | F2: FY2020 | G2: FY2021 | H2: FY2022 | I2: FY2023 | J2: FY2024 | K2: FY2025 | L2: FY2026
B3: REPORTED BALANCE-SHEET COMPONENTS
B4: Cash & cash equivalents | C4: 78.5 | D4: 141.9 | E4: 216.4 | F4: 66.1 | G4: 77.8 | H4: 54.5 | I4: 115.1 | J4: 1052 | K4: 1328 | L4: 859
B5: Bank balances (other than cash) | C5: 8.7 | D5: 114.1 | E5: 66.5 | F5: 7.4 | G5: 6.1 | H5: 5.8 | I5: 768.2 | J5: 217 | K5: 702 | L5: 1118
B6: Current investments | C6: 0.1 | D6: 0.1 | E6: 0 | F6: 0 | G6: 0 | H6: 222.1 | I6: 255.8 | J6: 599 | K6: 873 | L6: 1157
B7: Inventories | C7: 1927.6 | D7: 1919.7 | E7: 1934.3 | F7: 1927.5 | G7: 2051.9 | H7: 2156.7 | I7: 2230 | J7: 2063 | K7: 2305 | L7: 2668
B8: Trade receivables (current) | C8: 2953.4 | D8: 2711.2 | E8: 2542.5 | F8: 2283.5 | G8: 2187.2 | H8: 2373.6 | I8: 2434 | J8: 3056 | K8: 3410 | L8: 3609
B9: Other current financial assets | C9: 104.7 | D9: 249.3 | E9: 244.2 | F9: 305.8 | G9: 218.6 | H9: 77.2 | I9: 136 | J9: 37 | K9: 256 | L9: 57
B10: Current loans | C10: 0 | D10: 29.9 | E10: 16.9 | F10: 16 | G10: 15.6 | H10: 11.3 | I10: 16.3 | J10: 10 | K10: 22 | L10: 1
B11: Contract assets | C11: 0 | D11: 0 | E11: 10.5 | F11: 0 | G11: 0 | H11: 0 | I11: 0 | J11: 0 | K11: 0 | L11: 0
B12: Other current assets | C12: 552.2 | D12: 354 | E12: 232.5 | F12: 257 | G12: 245.8 | H12: 262.2 | I12: 279.2 | J12: 343 | K12: 306 | L12: 393
B13: Trade payables | C13: 1224.7 | D13: 1424.6 | E13: 1408.3 | F13: 1199.4 | G13: 1417.2 | H13: 1582.1 | I13: 1782.5 | J13: 1954 | K13: 2239 | L13: 2383
B14: Other current financial liabilities | C14: 957.5 | D14: 650.4 | E14: 246.4 | F14: 942.6 | G14: 199.8 | H14: 182.3 | I14: 284.6 | J14: 276 | K14: 477 | L14: 273
B15: Contract liabilities | C15: 0 | D15: 85 | E15: 71.9 | F15: 0 | G15: 0 | H15: 0 | I15: 0 | J15: 0 | K15: 0 | L15: 0
... B17: Other current liabilities | C17: 486.4 | D17: 449.4 | E17: 605.6 | F17: 418.1 | G17: 884.6 | H17: 839 | I17: 798.2 | J17: 845 | K17: 1105 | L17: 986
B19: Treasury = Cash + Bank + Current investments | C19: =C4+C5+C6 | D19: =D4+D5+D6 | E19: =E4+E5+E6 | F19: =F4+F5+F6 | G19: =G4+G5+G6 | H19: =H4+H5+H6 | I19: =I4+I5+I6 | J19: =J4+J5+J6 | ... L19: =L4+L5+L6
B20: Net Working Capital (operating) | C20: =(C7+C8+C9+C10+C11+C12)-(C13+C14+C15+C16+C17) | D20: =(D7+D8+D9+D10+D11+D12)-(D13+D14+D15+D16+D17) | E20: =(E7+E8+E9+E10+E11+E12)-(E13+E14+E15+E16+E17) | F20: =(F7+F8+F9+F10+F11+F12)-(F13+F14+F15+F16+F17) | G20: =(G7+G8+G9+G10+G11+G12)-(G13+G14+G15+G16+G17) | H20: =(H7+H8+H9+H10+H11+H12)-(H13+H14+H15+H16+H17) | I20: =(I7+I8+I9+I10+I11+I12)-(I13+I14+I15+I16+I17) | J20: =(J7+J8+J9+J10+J11+J12)-(J13+J14+J15+J16+J17) | ... L20: =(L7+L8+L9+L10+L11+L12)-(L13+L14+L15+L16+L17)

Sheet Reconciliation
B1: RECONCILIATION — reported CFO & FCF-to-Treasury bridge (INR cr)
B2: Particulars (INR crore) | C2: FY2017 | D2: FY2018 | E2: FY2019 | F2: FY2020 | G2: FY2021 | H2: FY2022 | I2: FY2023 | J2: FY2024 | K2: FY2025 | L2: FY2026
B3: Reported statutory CFO (per filings) | C3: 646.8 | D3: 925.1 | E3: 948.3 | F3: 783.2 | G3: 1817.7 | H3: 977.4 | I3: 614.7 | J3: 1118 | K3: 1947 | L3: 1459
B4: Model CFO (this workbook) | C4: ='Cash Flow'!C7 | D4: ='Cash Flow'!D7 | E4: ='Cash Flow'!E7 | F4: ='Cash Flow'!F7 | G4: ='Cash Flow'!G7 | H4: ='Cash Flow'!H7 | I4: ='Cash Flow'!I7 | J4: ='Cash Flow'!J7 | ... L4: ='Cash Flow'!L7
B5: Difference (should be 0) | C5: =C3-C4 | D5: =D3-D4 | E5: =E3-E4 | F5: =F3-F4 | G5: =G3-G4 | H5: =H3-H4 | I5: =I3-I4 | J5: =J3-J4 | ... L5: =L3-L4
B7: Interest paid (borrowings + leases) | C7: 375.2 | D7: 252.8 | E7: 229.3 | F7: 181.1 | G7: 142 | H7: 50.1 | I7: 36.3 | J7: 21 | K7: 40 | L7: 37
B9: Closing treasury - Opening treasury (BS move) | C9: ='Cash Flow'!C18-'Cash Flow'!C16 | D9: ='Cash Flow'!D18-'Cash Flow'!D16 | E9: ='Cash Flow'!E18-'Cash Flow'!E16 | F9: ='Cash Flow'!F18-'Cash Flow'!F16 | G9: ='Cash Flow'!G18-'Cash Flow'!G16 | H9: ='Cash Flow'!H18-'Cash Flow'!H16 | I9: ='Cash Flow'!I18-'Cash Flow'!I16 | J9: ='Cash Flow'!J18-'Cash Flow'!J16 | ... L9: ='Cash Flow'!L18-'Cash Flow'!L16
B10: FCF - Dividends - Lease +/- Net borrowings | C10: ='Cash Flow'!C10-'Cash Flow'!C11-'Cash Flow'!C12+'Cash Flow'!C13 | D10: ='Cash Flow'!D10-'Cash Flow'!D11-'Cash Flow'!D12+'Cash Flow'!D13 | E10: ='Cash Flow'!E10-'Cash Flow'!E11-'Cash Flow'!E12+'Cash Flow'!E13 | F10: ='Cash Flow'!F10-'Cash Flow'!F11-'Cash Flow'!F12+'Cash Flow'!F13 | G10: ='Cash Flow'!G10-'Cash Flow'!G11-'Cash Flow'!G12+'Cash Flow'!G13 | H10: ='Cash Flow'!H10-'Cash Flow'!H11-'Cash Flow'!H12+'Cash Flow'!H13 | I10: ='Cash Flow'!I10-'Cash Flow'!I11-'Cash Flow'!I12+'Cash Flow'!I13 | J10: ='Cash Flow'!J10-'Cash Flow'!J11-'Cash Flow'!J12+'Cash Flow'!J13 | ... L10: ='Cash Flow'!L10-'Cash Flow'!L11-'Cash Flow'!L12+'Cash Flow'!L13
B11: Implied 'Other Investing/Financing & Interest (net)' | C11: =C9-C10 | D11: =D9-D10 | E11: =E9-E10 | F11: =F9-F10 | G11: =G9-G10 | H11: =H9-H10 | I11: =I9-I10 | J11: =J9-J10 | ... L11: =L9-L10

Sheet Sources
B1: SOURCES & PROVENANCE — all figures reported, consolidated
B2: Years | C2: Source file (this repo)
B3: FY2016 & FY2017 | C3: FY2017.pdf — Consolidated BS p.190-191, P&L p.192-193, Cash Flow p.194-195 (INR mn / 10)
B4: FY2018 & FY2019 | C4: FY2019.pdf — Consolidated BS p.212-213, P&L p.214-215, Cash Flow p.216-217 (INR mn / 10)
B5: FY2020 & FY2021 | C5: FY2021.pdf — Consolidated BS p.176-177, P&L p.178-179, Cash Flow p.181-182 (INR mn / 10)
B6: FY2022 & FY2023 | C6: FY2023_compressed.pdf — Consolidated BS p.259-260, P&L p.261, Cash Flow p.264-265 (INR mn / 10)
B7: FY2024 & FY2025 | C7: FY2025_compressed.pdf — Consolidated BS p.206, P&L p.207, Cash Flow p.208-209 (INR cr)
B8: FY2026 | C8: 'fy 2026.xlsx' — audited consolidated results filed 14-May-2026 (INR cr)
B10: Notes
B11: Treasury | C11: Cash & cash equivalents + Bank balances (other than cash) + Current investments.
B12: NWC | C12: Operating current assets less operating current liabilities; excludes cash, bank, current
C13: investments, current tax, borrowings, lease liabilities and dividend payable.
B14: Leases | C14: Ind AS 116 adopted FY2020; lease principal repayment shown from FY2020 (FY2017 = finance-lease pmt).
B15: Dividends | C15: Cash dividends paid (financing activities): nil FY2017-FY2023; FY24 284, FY25 355, FY26 1,263 cr.
B16: One-offs | C16: FY2017: goodwill impairment / large exceptional charge & receivables write-offs (PAT trough).
C17: FY2023: +817 cr exceptional gain; ~818 cr proceeds from sale of a business undertaking.
C18: FY2026: 1,263 cr dividend; RCB/Sports reclassified discontinued / held-for-sale.
