Workbook

Sheet Scenarios
C2: United Spirits Economic Scenarios
C4: Scenario Switch | D4: 1
C8: Sales Growth % Scenarios | H8: 2027 | I8: =H8+1 -> 2028 | J8: =I8+1 -> 2029 | K8: =J8+1 -> 2030 | L8: =K8+1 -> 2031 | M8: =L8+1 -> 2032 | N8: =M8+1 -> 2033 | O8: =N8+1 -> 2034
C10: Sales Growth % | H10: =CHOOSE($D$4,H12,H13,H14) -> 0.09 | I10: =CHOOSE($D$4,I12,I13,I14) -> 0.09 | J10: =CHOOSE($D$4,J12,J13,J14) -> 0.08 | K10: =CHOOSE($D$4,K12,K13,K14) -> 0.07 | L10: =CHOOSE($D$4,L12,L13,L14) -> 0.065 | M10: =CHOOSE($D$4,M12,M13,M14) -> 0.065 | N10: =CHOOSE($D$4,N12,N13,N14) -> 0.065 | O10: =CHOOSE($D$4,O12,O13,O14) -> 0.065
C12: Base | H12: 0.09 | I12: 0.09 | J12: 0.08 | K12: 0.07 | L12: 0.065 | M12: 0.065 | N12: 0.065 | O12: 0.065
C13: Best | H13: 0.11 | I13: 0.11 | J13: 0.1 | K13: 0.09 | L13: 0.08 | M13: 0.07 | N13: 0.07 | O13: 0.07
C14: Bear | H14: 0.06 | I14: 0.06 | J14: 0.05 | K14: 0.05 | L14: 0.05 | M14: 0.05 | N14: 0.05 | O14: 0.05
C17: Gross Profit Margin % Scenarios | H17: 2027 | I17: =H17+1 -> 2028 | J17: =I17+1 -> 2029 | K17: =J17+1 -> 2030 | L17: =K17+1 -> 2031 | M17: =L17+1 -> 2032 | N17: =M17+1 -> 2033 | O17: =N17+1 -> 2034
C19: Gross Profi Margin % | H19: =CHOOSE($D$4,H21,H22,H23) -> 0.455 | I19: =CHOOSE($D$4,I21,I22,I23) -> 0.46 | J19: =CHOOSE($D$4,J21,J22,J23) -> 0.465 | K19: =CHOOSE($D$4,K21,K22,K23) -> 0.47 | L19: =CHOOSE($D$4,L21,L22,L23) -> 0.47 | M19: =CHOOSE($D$4,M21,M22,M23) -> 0.47 | N19: =CHOOSE($D$4,N21,N22,N23) -> 0.47 | O19: =CHOOSE($D$4,O21,O22,O23) -> 0.47
C21: Base | H21: 0.455 | I21: 0.46 | J21: 0.465 | K21: 0.47 | L21: 0.47 | M21: 0.47 | N21: 0.47 | O21: 0.47
C22: Best | H22: 0.46720587 | I22: 0.48156147 | J22: 0.49591708 | K22: 0.51027268 | L22: 0.51027268 | M22: 0.51027268 | N22: 0.51027268 | O22: 0.51027268
C23: Bear | H23: 0.435 | I23: 0.435 | J23: 0.44 | K23: 0.44 | L23: 0.44 | M23: 0.44 | N23: 0.44 | O23: 0.44

Sheet PPT Sheet
B2: NSE CODE | C2: UNITDSPR
B3: BSE CODE | C3: 532432 | H3: Particulars | I3: Value
B4: CMP | C4: 1345
B5: Share Capital (Rs in Cr.) | C5: 145
B6: Shares Outstanding (Cr.) | C6: 72.74
B7: Face Value | C7: 2
B8: Market Cap (Rs in Cr.) | C8: 96453.24
B9: Enterprice Value (Rs in Cr.) | C9: 93726.24
B10: 52 Week High | C10: 1489
B11: 52 Week Low | C11: 1210

Sheet Valuation Summary
B2: Peer Comparison | M2: =PL!T2 -> CURRENTLY RUNNING: BASE SCENARIO | Q2: Valuation Summary
A3: x | C3: Assumptions
C4: Revenue | D4: EBITDA | E4: EBIT | F4: PAT | Q4: Method | S4: Implied | T4: Weight | U4: Contribution
B5: United Breweries | C5: 0.08 | D5: 0.089177489 | E5: 0.062662338 | F5: 0.04469697
B6: Radico Khaitan Ltd | C6: 0.25 | D6: 0.17157025 | E6: 0.14644628 | F6: 0.10198347 | Q6: EV/EBITDA | S6: =(K29*K13+S14-S13)/S15 -> 1410.824 | T6: 0.6 | U6: =T6*S6 -> 846.49438
B7: Allied Blenders | C7: 0.08 | D7: 0.13815957 | E7: 0.12413969 | F7: 0.058373694 | Q7: P/E | S7: =M29*M13/S15 -> 1675.3907 | T7: 0.2 | U7: =T7*S7 -> 335.07813
Q8: EV/EBIT | S8: =(L29*L13+S14-S13)/S15 -> 1408.3011 | T8: 0.05 | U8: =T8*S8 -> 70.415053
Q9: DCF | S9: =DCF!C28 -> 642.24 | T9: 0.15 | U9: =T9*S9 -> 96.336
C10: 2026 | J10: =C10+1 -> 2027 | Q10: Per Share Value | U10: =SUM(U6:U9) -> 1348.3236
A12: x | B12: Particulars | C12: Mkt Cap | D12: EV | E12: Revenue | F12: EBITDA | G12: EBIT | H12: PAT | J12: Revenue | K12: EBITDA | L12: EBIT | M12: PAT
B13: United Spirits | C13: ='Ratio Analysis'!L34 -> 96453.24 | D13: ='Ratio Analysis'!L37 -> 93726.24 | E13: =PL!L5 -> 12467 | F13: =PL!L12 -> 2279 | G13: =PL!L14 -> 1990 | H13: =PL!L22 -> 1838 | J13: =PL!M5 -> 13589.03 | K13: =PL!M12 -> 2547.3242 | L13: =PL!M14 -> 2170.3113 | M13: =PL!M22 -> 1708.6379 | Q13: Debt | S13: 407
B14: United Breweries | C14: 35605 | D14: 36350 | E14: 9240 | F14: 824 | G14: 579 | H14: 413 | J14: =E14*(1+C5) -> 9979.2 | K14: =J14*D5 -> 889.92 | L14: =J14*E5 -> 625.32 | M14: =J14*F5 -> 446.04 | Q14: Cash | S14: 3134
B15: Radico Khaitan Ltd | C15: 50274 | D15: 50883 | E15: 6050 | F15: 1038 | G15: 886 | H15: 617 | J15: =E15*(1+C6) -> 7562.5 | K15: =J15*D6 -> 1297.5 | L15: =J15*E6 -> 1107.5 | M15: =J15*F6 -> 771.25 | Q15: Shares O/S | S15: 72.74
B16: Allied Blenders | C16: 17640 | D16: 18635 | E16: 3923 | F16: 542 | G16: 487 | H16: 229 | J16: =E16*(1+C7) -> 4236.84 | K16: =J16*D7 -> 585.36 | L16: =J16*E7 -> 525.96 | M16: =J16*F7 -> 247.32
A19: x | B19: Multiples
E20: 2026 | J20: =1+E20 -> 2027
B22: Particulars | E22: EV/Revenue | F22: EV/EBITDA | G22: EV/EBIT | H22: P/E | J22: EV/Revenue | K22: EV/EBITDA | L22: EV/EBIT | M22: P/E
A23: x | B23: United Spirits | E23: =$D$13/E13 -> 7.5179466 | F23: =$D$13/F13 -> 41.126038 | G23: =$D$13/G13 -> 47.098613 | H23: =$C$13/H13 -> 52.47728 | J23: =$D$13/J13 -> 6.8971987 | K23: =$D$13/K13 -> 36.793998 | L23: =$D$13/L13 -> 43.185621 | M23: =$C$13/M13 -> 56.450368
B24: United Breweries | E24: =$D$14/E14 -> 3.9339827 | F24: =$D$14/F14 -> 44.114078 | G24: =$D$14/G14 -> 62.780656 | H24: =$C$14/H14 -> 86.210654 | J24: =$D$14/J14 -> 3.6425766 | K24: =$D$14/K14 -> 40.846368 | L24: =$D$14/L14 -> 58.130237 | M24: =$C$14/M14 -> 79.824679
B25: Radico Khaitan Ltd | E25: =$D$15/E15 -> 8.4104132 | F25: =$D$15/F15 -> 49.020231 | G25: =$D$15/G15 -> 57.430023 | H25: =$C$15/H15 -> 81.481361 | J25: =$D$15/J15 -> 6.7283306 | K25: =$D$15/K15 -> 39.216185 | L25: =$D$15/L15 -> 45.944018 | M25: =$C$15/M15 -> 65.185089
B26: Allied Blenders | E26: =$D$16/E16 -> 4.7501912 | F26: =$D$16/F16 -> 34.381919 | G26: =$D$16/G16 -> 38.264887 | H26: =$C$16/H16 -> 77.030568 | J26: =$D$16/J16 -> 4.3983252 | K26: =$D$16/K16 -> 31.83511 | L26: =$D$16/L16 -> 35.430451 | M26: =$C$16/M16 -> 71.3246
B28: Mean | E28: =AVERAGE(E24:E26) -> 5.6981957 | F28: =AVERAGE(F24:F26) -> 42.505409 | G28: =AVERAGE(G24:G26) -> 52.825189 | H28: =AVERAGE(H24:H26) -> 81.574194 | J28: =AVERAGE(J24:J26) -> 4.9230774 | K28: =AVERAGE(K24:K26) -> 37.299221 | L28: =AVERAGE(L24:L26) -> 46.501569 | M28: =AVERAGE(M24:M26) -> 72.111456
B29: Median | E29: =MEDIAN(E24:E26) -> 4.7501912 | F29: =MEDIAN(F24:F26) -> 44.114078 | G29: =MEDIAN(G24:G26) -> 57.430023 | H29: =MEDIAN(H24:H26) -> 81.481361 | J29: =MEDIAN(J24:J26) -> 4.3983252 | K29: =MEDIAN(K24:K26) -> 39.216185 | L29: =MEDIAN(L24:L26) -> 45.944018 | M29: =MEDIAN(M24:M26) -> 71.3246
A32: x | B32: Valuation using Mean Multiples
E33: 2026 | J33: =1+E33 -> 2027
E35: EV/Revenue | F35: EV/EBITDA | G35: EV/EBIT | H35: P/E | J35: EV/Revenue | K35: EV/EBITDA | L35: EV/EBIT | M35: P/E
B36: Enterprise Value & Market Cap(P/E) | E36: =E28*E13 -> 71039.406 | F36: =F28*F13 -> 96869.828 | G36: =G28*G13 -> 105122.13 | H36: =H28*H13 -> 149933.37 | J36: =J28*J13 -> 66899.847 | K36: =K28*K13 -> 95013.207 | L36: =L28*L13 -> 100922.88 | M36: =M28*M13 -> 123212.37
B37: Debt | E37: 407 | F37: 407 | G37: 407 | J37: 407 | K37: 407 | L37: 407
B38: Cash | E38: 3134 | F38: 3134 | G38: 3134 | J38: 3134 | K38: 3134 | L38: 3134
B39: Equity Value | E39: =E36-E37+E38 -> 73766.406 | F39: =F36-F37+F38 -> 99596.828 | G39: =G36-G37+G38 -> 107849.13 | J39: =J36-J37+J38 -> 69626.847 | K39: =K36-K37+K38 -> 97740.207 | L39: =L36-L37+L38 -> 103649.88
B40: Shares O/S | E40: 72.74 | F40: 72.74 | G40: 72.74 | H40: 72.74 | J40: 72.74 | K40: 72.74 | L40: 72.74 | M40: 72.74
A41: x | B41: Per Share Value | E41: =E39/E40 -> 1014.1106 | F41: =F39/F40 -> 1369.2168 | G41: =G39/G40 -> 1482.666 | H41: =H36/H40 -> 2061.2231 | J41: =J39/J40 -> 957.20164 | K41: =K39/K40 -> 1343.6927 | L41: =L39/L40 -> 1424.9365 | M41: =M36/M40 -> 1693.8736
B44: Valuation using Median Multiples
E45: 2026 | J45: =1+E45 -> 2027
E47: EV/Revenue | F47: EV/EBITDA | G47: EV/EBIT | H47: P/E | J47: EV/Revenue | K47: EV/EBITDA | L47: EV/EBIT | M47: P/E
B48: Enterprise Value & Market Cap(P/E) | E48: =E29*E13 -> 59220.633 | F48: =F29*F13 -> 100535.98 | G48: =G29*G13 -> 114285.74 | H48: =H29*H13 -> 149762.74 | J48: =J29*J13 -> 59768.973 | K48: =K29*K13 -> 99896.335 | L48: =L29*L13 -> 99712.819 | M48: =M29*M13 -> 121867.92
B49: Debt | E49: 407 | F49: 407 | G49: 407 | J49: 407 | K49: 407 | L49: 407
B50: Cash | E50: 3134 | F50: 3134 | G50: 3134 | J50: 3134 | K50: 3134 | L50: 3134
B51: Equity Value | E51: =E48-E49+E50 -> 61947.633 | F51: =F48-F49+F50 -> 103262.98 | G51: =G48-G49+G50 -> 117012.74 | J51: =J48-J49+J50 -> 62495.973 | K51: =K48-K49+K50 -> 102623.34 | L51: =L48-L49+L50 -> 102439.82
B52: Shares O/S | E52: 72.74 | F52: 72.74 | G52: 72.74 | H52: 72.74 | J52: 72.74 | K52: 72.74 | L52: 72.74 | M52: 72.74
A53: x | B53: Per Share Value | E53: =E51/E52 -> 851.63092 | F53: =F51/F52 -> 1419.6176 | G53: =G51/G52 -> 1608.6437 | H53: =H48/H52 -> 2058.8774 | J53: =J51/J52 -> 859.16927 | K53: =K51/K52 -> 1410.824 | L53: =L51/L52 -> 1408.3011 | M53: =M48/M52 -> 1675.3907

Sheet Summary
B1: United Spirits Ltd
B2: Summary Outputs Base Case
B4: Particulars | D4: 2017 | E4: 2018 | F4: 2019 | G4: 2020 | H4: 2021 | I4: 2022 | J4: 2023 | K4: 2024 | L4: 2025 | M4: 2026 | N4: 2027 | O4: 2028 | P4: 2029 | Q4: 2030 | R4: 2031 | S4: 2032 | T4: 2033 | U4: 2034
B6: Net Revenue | D6: 8817.5 | E6: 8590.6 | F6: 9340.8 | G6: 9325.4 | H6: 8131.3 | I6: 9712.4 | J6: 10612 | K6: 11321 | L6: 12069 | M6: 12467 | N6: 13589.03 | O6: 14812.043 | P6: 15997.006 | Q6: 17116.797 | R6: 18229.388 | S6: 19414.299 | T6: 20676.228 | U6: 22020.183
B7: Growth | E7: -0.025732917 | F7: 0.08732801 | G7: -0.0016486811 | H7: -0.12804813 | I7: 0.19444615 | J7: 0.092623862 | K7: 0.066811157 | L7: 0.066071902 | M7: 0.032977049 | N7: 0.09 | O7: 0.09 | P7: 0.08 | Q7: 0.07 | R7: 0.065 | S7: 0.065 | T7: 0.065 | U7: 0.065
B10: COGS | D10: 5151.3 | E10: 4557.3 | F10: 4966.4 | G10: 5370 | H10: 4807.5 | I10: 5680.9 | J10: 6503 | K10: 6542 | L10: 6860 | M10: 6674 | N10: 7406.0213 | O10: 7998.5031 | P10: 8558.3983 | Q10: 9071.9022 | R10: 9661.5758 | S10: 10289.578 | T10: 10958.401 | U10: 11670.697
B11: Growth | E11: -0.1153107 | F11: 0.089768064 | G11: 0.081266108 | H11: -0.1047486 | I11: 0.18167447 | J11: 0.14471299 | K11: 0.005997232 | L11: 0.048608988 | M11: -0.027113703 | N11: 0.10968255 | O11: 0.08 | P11: 0.07 | Q11: 0.06 | R11: 0.065 | S11: 0.065 | T11: 0.065 | U11: 0.065
B14: Gross Profit | D14: 3666.2 | E14: 4033.3 | F14: 4374.4 | G14: 3955.4 | H14: 3323.8 | I14: 4031.5 | J14: 4109 | K14: 4779 | L14: 5209 | M14: 5793 | N14: 6183.0087 | O14: 6813.5396 | P14: 7438.6078 | Q14: 8044.8944 | R14: 8567.8125 | S14: 9124.7203 | T14: 9717.8271 | U14: 10349.486
B15: Gross Profit Margin | D15: 0.41578679 | E15: 0.46950155 | F15: 0.46831107 | G15: 0.42415339 | H15: 0.40876613 | I15: 0.41508793 | J15: 0.38720317 | K15: 0.42213585 | L15: 0.43160162 | M15: 0.46466672 | N15: 0.455 | O15: 0.46 | P15: 0.465 | Q15: 0.47 | R15: 0.47 | S15: 0.47 | T15: 0.47 | U15: 0.47
B16: Growth | E16: 0.10013093 | F16: 0.084570947 | G16: -0.095784565 | H16: -0.15968044 | I16: 0.21291895 | J16: 0.019223614 | K16: 0.1630567 | L16: 0.089976983 | M16: 0.11211365 | N16: 0.067324124 | O16: 0.10197802 | P16: 0.09173913 | Q16: 0.081505376 | R16: 0.065 | S16: 0.065 | T16: 0.065 | U16: 0.065
B19: EBIDTA | D19: 991.4 | E19: 1209.2 | F19: 1393.8 | G19: 1571 | H19: 1051.4 | I19: 1595.2 | J19: 1417 | K19: 2000 | L19: 2236 | M19: 2279 | N19: 2547.3242 | O19: 2850.6435 | P19: 3158.6801 | Q19: 3465.3716 | R19: 3690.6208 | S19: 3930.5111 | T19: 4185.9944 | U19: 4458.084
B20: EBIDTA Margin | D20: 0.1124355 | E20: 0.1407585 | F20: 0.14921634 | G20: 0.16846462 | H20: 0.12930282 | I20: 0.16424365 | J20: 0.13352808 | K20: 0.17666284 | L20: 0.18526804 | M20: 0.1828026 | N20: 0.18745445 | O20: 0.19245445 | P20: 0.19745445 | Q20: 0.20245445 | R20: 0.20245445 | S20: 0.20245445 | T20: 0.20245445 | U20: 0.20245445
B21: Growth | E21: 0.21968933 | F21: 0.15266292 | G21: 0.12713445 | H21: -0.33074475 | I21: 0.51721514 | J21: -0.11171013 | K21: 0.4114326 | L21: 0.118 | M21: 0.019230769 | N21: 0.11773767 | O21: 0.11907373 | P21: 0.10805859 | Q21: 0.097094856 | R21: 0.065 | S21: 0.065 | T21: 0.065 | U21: 0.065
B24: EBIT | D24: 802.8 | E24: 1016.9 | F24: 1179.1 | G24: 1285.7 | H24: 752.3 | I24: 1291.4 | J24: 1134 | K24: 1725 | L24: 1953 | M24: 1990 | N24: 2170.3113 | O24: 2433.4848 | P24: 2700.3359 | Q24: 2965.1879 | R24: 3148.079 | S24: 3344.665 | T24: 3555.2941 | U24: 3780.4994
B25: EBIT Margin | D25: 0.091046215 | E25: 0.11837357 | F25: 0.12623116 | G25: 0.13787076 | H25: 0.092519031 | I25: 0.13296405 | J25: 0.10686016 | K25: 0.1523717 | L25: 0.16181954 | M25: 0.1596214 | N25: 0.15971053 | O25: 0.16429097 | P25: 0.16880258 | Q25: 0.17323264 | R25: 0.17269252 | S25: 0.17227844 | T25: 0.17195081 | U25: 0.17168338
B26: Growth | E26: 0.26669158 | F26: 0.15950438 | G26: 0.090407938 | H26: -0.41487128 | I26: 0.71660242 | J26: -0.12188323 | K26: 0.52116402 | L26: 0.13217391 | M26: 0.018945212 | N26: 0.090608669 | O26: 0.12126074 | P26: 0.10965801 | Q26: 0.09808111 | R26: 0.061679435 | S26: 0.062446352 | T26: 0.062974633 | U26: 0.06334367
B29: Profit After Tax | D29: 93 | E29: 651.9 | F29: 683.6 | G29: 620.6 | H29: 362.1 | I29: 810.6 | J29: 1125.8 | K29: 1408 | L29: 1582 | M29: 1838 | N29: 1708.6379 | O29: 1891.2508 | P29: 2118.6321 | Q29: 2317.6542 | R29: 2489.1953 | S29: 2641.163 | T29: 2836.3987 | U29: 3013.605
B30: PAT Margin | D30: 0.010547207 | E30: 0.07588527 | F30: 0.07318431 | G30: 0.066549424 | H30: 0.044531625 | I30: 0.083460319 | J30: 0.10608745 | K30: 0.12437064 | L30: 0.13107963 | M30: 0.14742921 | N30: 0.12573656 | O30: 0.12768332 | P30: 0.13243929 | Q30: 0.13540233 | R30: 0.13654848 | S30: 0.13604215 | T30: 0.13718163 | U30: 0.1368565
B31: Growth | E31: 6.0096774 | F31: 0.04862709 | G31: -0.092159157 | H31: -0.41653239 | I31: 1.2386081 | J31: 0.38884777 | K31: 0.25066619 | L31: 0.12357955 | M31: 0.16182048 | N31: -0.070381975 | O31: 0.10687629 | P31: 0.12022798 | Q31: 0.093938966 | R31: 0.074014973 | S31: 0.061050923 | T31: 0.073920376 | U31: 0.06247582
B33: Summary Outputs Best Case
B35: Particulars | D35: 2017 | E35: 2018 | F35: 2019 | G35: 2020 | H35: 2021 | I35: 2022 | J35: 2023 | K35: 2024 | L35: 2025 | M35: 2026 | N35: 2027 | O35: 2028 | P35: 2029 | Q35: 2030 | R35: 2031 | S35: 2032 | T35: 2033 | U35: 2034
B37: Net Revenue | D37: 8817.5 | E37: 8590.6 | F37: 9340.8 | G37: 9325.4 | H37: 8131.3 | I37: 9712.4 | J37: 10612 | K37: 11321 | L37: 12069 | M37: 12467 | N37: 13838.37 | O37: 15360.591 | P37: 16896.65 | Q37: 18417.348 | R37: 19890.736 | S37: 21283.088 | T37: 22772.904 | U37: 24367.007
B38: Growth | E38: -0.025732917 | F38: 0.08732801 | G38: -0.0016486811 | H38: -0.12804813 | I38: 0.19444615 | J38: 0.092623862 | K38: 0.066811157 | L38: 0.066071902 | M38: 0.032977049 | N38: 0.11 | O38: 0.11 | P38: 0.1 | Q38: 0.09 | R38: 0.08 | S38: 0.07 | T38: 0.07 | U38: 0.07
B41: COGS | D41: 5151.3 | E41: 4557.3 | F41: 4966.4 | G41: 5370 | H41: 4807.5 | I41: 5680.9 | J41: 6503 | K41: 6542 | L41: 6860 | M41: 6674 | N41: 7373.0023 | O41: 7963.522 | P41: 8517.3126 | Q41: 9019.4785 | R41: 9741.0368 | S41: 10422.909 | T41: 11152.513 | U41: 11933.189
B42: Growth | E42: -0.1153107 | F42: 0.089768064 | G42: 0.081266108 | H42: -0.1047486 | I42: 0.18167447 | J42: 0.14471299 | K42: 0.005997232 | L42: 0.048608988 | M42: -0.027113703 | N42: 0.10473514 | O42: 0.080092162 | P42: 0.069540912 | Q42: 0.058958265 | R42: 0.08 | S42: 0.07 | T42: 0.07 | U42: 0.07
B45: Gross Profit | D45: 3666.2 | E45: 4033.3 | F45: 4374.4 | G45: 3955.4 | H45: 3323.8 | I45: 4031.5 | J45: 4109 | K45: 4779 | L45: 5209 | M45: 5793 | N45: 6465.3677 | O45: 7397.0687 | P45: 8379.3372 | Q45: 9397.8697 | R45: 10149.699 | S45: 10860.178 | T45: 11620.391 | U45: 12433.818
B46: Gross Profit Margin | D46: 0.41578679 | E46: 0.46950155 | F46: 0.46831107 | G46: 0.42415339 | H46: 0.40876613 | I46: 0.41508793 | J46: 0.38720317 | K46: 0.42213585 | L46: 0.43160162 | M46: 0.46466672 | N46: 0.46720587 | O46: 0.48156147 | P46: 0.49591708 | Q46: 0.51027268 | R46: 0.51027268 | S46: 0.51027268 | T46: 0.51027268 | U46: 0.51027268
B47: Growth | E47: 0.10013093 | F47: 0.084570947 | G47: -0.095784565 | H47: -0.15968044 | I47: 0.21291895 | J47: 0.019223614 | K47: 0.1630567 | L47: 0.089976983 | M47: 0.11211365 | N47: 0.11606555 | O47: 0.14410642 | P47: 0.13279159 | Q47: 0.12155287 | R47: 0.08 | S47: 0.07 | T47: 0.07 | U47: 0.07
B50: EBIDTA | D50: 991.4 | E50: 1209.2 | F50: 1393.8 | G50: 1571 | H50: 1051.4 | I50: 1595.2 | J50: 1417 | K50: 2000 | L50: 2236 | M50: 2279 | N50: 2762.9734 | O50: 3287.411 | P50: 3858.7137 | Q50: 4470.3901 | R50: 4828.0214 | S50: 5165.9828 | T50: 5527.6016 | U50: 5914.5338
B51: EBIDTA Margin | D51: 0.1124355 | E51: 0.1407585 | F51: 0.14921634 | G51: 0.16846462 | H51: 0.12930282 | I51: 0.16424365 | J51: 0.13352808 | K51: 0.17666284 | L51: 0.18526804 | M51: 0.1828026 | N51: 0.19966032 | O51: 0.21401593 | P51: 0.22837153 | Q51: 0.24272713 | R51: 0.24272713 | S51: 0.24272713 | T51: 0.24272713 | U51: 0.24272713
B52: Growth | E52: 0.21968933 | F52: 0.15266292 | G52: 0.12713445 | H52: -0.33074475 | I52: 0.51721514 | J52: -0.11171013 | K52: 0.4114326 | L52: 0.118 | M52: 0.019230769 | N52: 0.21236218 | O52: 0.18980915 | P52: 0.173785 | Q52: 0.15851821 | R52: 0.08 | S52: 0.07 | T52: 0.07 | U52: 0.07
B55: EBIT | D55: 802.8 | E55: 1016.9 | F55: 1179.1 | G55: 1285.7 | H55: 752.3 | I55: 1291.4 | J55: 1134 | K55: 1725 | L55: 1953 | M55: 1990 | N55: 2384.9195 | O55: 2866.3352 | P55: 3391.827 | Q55: 3955.3368 | R55: 4262.9835 | S55: 4549.7793 | T55: 4858.8862 | U55: 5191.1953
B56: EBIT Margin | D56: 0.091046215 | E56: 0.11837357 | F56: 0.12623116 | G56: 0.13787076 | H56: 0.092519031 | I56: 0.13296405 | J56: 0.10686016 | K56: 0.1523717 | L56: 0.16181954 | M56: 0.1596214 | N56: 0.17234107 | O56: 0.18660319 | P56: 0.20073962 | Q56: 0.21476147 | R56: 0.21432005 | S56: 0.2137744 | T56: 0.21336261 | U56: 0.21304198
B57: Growth | E57: 0.26669158 | F57: 0.15950438 | G57: 0.090407938 | H57: -0.41487128 | I57: 0.71660242 | J57: -0.12188323 | K57: 0.52116402 | L57: 0.13217391 | M57: 0.018945212 | N57: 0.19845201 | O57: 0.20185824 | P57: 0.18333231 | Q57: 0.16613752 | R57: 0.077780157 | S57: 0.06727585 | T57: 0.067938878 | U57: 0.068392039
B60: Profit After Tax | D60: 93 | E60: 651.9 | F60: 683.6 | G60: 620.6 | H60: 362.1 | I60: 810.6 | J60: 1125.8 | K60: 1408 | L60: 1582 | M60: 1838 | N60: 1869.4193 | O60: 2213.9017 | P60: 2640.6547 | Q60: 3066.2782 | R60: 3342.3167 | S60: 3569.0167 | T60: 3854.2562 | U60: 4119.4045
B61: PAT Margin | D61: 0.010547207 | E61: 0.07588527 | F61: 0.07318431 | G61: 0.066549424 | H61: 0.044531625 | I61: 0.083460319 | J61: 0.10608745 | K61: 0.12437064 | L61: 0.13107963 | M61: 0.14742921 | N61: 0.13508956 | O61: 0.14412868 | P61: 0.15628274 | Q61: 0.16648858 | R61: 0.16803384 | S61: 0.16769262 | T61: 0.16924747 | U61: 0.16905665
B62: Growth | E62: 6.0096774 | F62: 0.04862709 | G62: -0.092159157 | H62: -0.41653239 | I62: 1.2386081 | J62: 0.38884777 | K62: 0.25066619 | L62: 0.12357955 | M62: 0.16182048 | N62: 0.017094271 | O62: 0.18427241 | P62: 0.19276063 | Q62: 0.16118104 | R62: 0.09002396 | S62: 0.067827206 | T62: 0.079921039 | U62: 0.068793634
B64: Summary Outputs Bear Case
B66: Particulars | D66: 2017 | E66: 2018 | F66: 2019 | G66: 2020 | H66: 2021 | I66: 2022 | J66: 2023 | K66: 2024 | L66: 2025 | M66: 2026 | N66: 2027 | O66: 2028 | P66: 2029 | Q66: 2030 | R66: 2031 | S66: 2032 | T66: 2033 | U66: 2034
B68: Net Revenue | D68: 8817.5 | E68: 8590.6 | F68: 9340.8 | G68: 9325.4 | H68: 8131.3 | I68: 9712.4 | J68: 10612 | K68: 11321 | L68: 12069 | M68: 12467 | N68: 13215.02 | O68: 14007.921 | P68: 14708.317 | Q68: 15443.733 | R68: 16215.92 | S68: 17026.716 | T68: 17878.052 | U68: 18771.954
B69: Growth | E69: -0.025732917 | F69: 0.08732801 | G69: -0.0016486811 | H69: -0.12804813 | I69: 0.19444615 | J69: 0.092623862 | K69: 0.066811157 | L69: 0.066071902 | M69: 0.032977049 | N69: 0.06 | O69: 0.06 | P69: 0.05 | Q69: 0.05 | R69: 0.05 | S69: 0.05 | T69: 0.05 | U69: 0.05
B72: COGS | D72: 5151.3 | E72: 4557.3 | F72: 4966.4 | G72: 5370 | H72: 4807.5 | I72: 5680.9 | J72: 6503 | K72: 6542 | L72: 6860 | M72: 6674 | N72: 7466.4863 | O72: 7914.4755 | P72: 8236.6577 | Q72: 8648.4905 | R72: 9080.9151 | S72: 9534.9608 | T72: 10011.709 | U72: 10512.294
B73: Growth | E73: -0.1153107 | F73: 0.089768064 | G73: 0.081266108 | H73: -0.1047486 | I73: 0.18167447 | J73: 0.14471299 | K73: 0.005997232 | L73: 0.048608988 | M73: -0.027113703 | N73: 0.11874233 | O73: 0.06 | P73: 0.040707965 | Q73: 0.05 | R73: 0.05 | S73: 0.05 | T73: 0.05 | U73: 0.05
B76: Gross Profit | D76: 3666.2 | E76: 4033.3 | F76: 4374.4 | G76: 3955.4 | H76: 3323.8 | I76: 4031.5 | J76: 4109 | K76: 4779 | L76: 5209 | M76: 5793 | N76: 5748.5337 | O76: 6093.4457 | P76: 6471.6596 | Q76: 6795.2426 | R76: 7135.0047 | S76: 7491.7549 | T76: 7866.3427 | U76: 8259.6598
B77: Gross Profit Margin | D77: 0.41578679 | E77: 0.46950155 | F77: 0.46831107 | G77: 0.42415339 | H77: 0.40876613 | I77: 0.41508793 | J77: 0.38720317 | K77: 0.42213585 | L77: 0.43160162 | M77: 0.46466672 | N77: 0.435 | O77: 0.435 | P77: 0.44 | Q77: 0.44 | R77: 0.44 | S77: 0.44 | T77: 0.44 | U77: 0.44
B78: Growth | E78: 0.10013093 | F78: 0.084570947 | G78: -0.095784565 | H78: -0.15968044 | I78: 0.21291895 | J78: 0.019223614 | K78: 0.1630567 | L78: 0.089976983 | M78: 0.11211365 | N78: -0.0076758674 | O78: 0.06 | P78: 0.062068966 | Q78: 0.05 | R78: 0.05 | S78: 0.05 | T78: 0.05 | U78: 0.05
B81: EBIDTA | D81: 991.4 | E81: 1209.2 | F81: 1393.8 | G81: 1571 | H81: 1051.4 | I81: 1595.2 | J81: 1417 | K81: 2000 | L81: 2236 | M81: 2279 | N81: 2212.9139 | O81: 2345.6887 | P81: 2536.5148 | Q81: 2663.3405 | R81: 2796.5075 | S81: 2936.3329 | T81: 3083.1496 | U81: 3237.307
B82: EBIDTA Margin | D82: 0.1124355 | E82: 0.1407585 | F82: 0.14921634 | G82: 0.16846462 | H82: 0.12930282 | I82: 0.16424365 | J82: 0.13352808 | K82: 0.17666284 | L82: 0.18526804 | M82: 0.1828026 | N82: 0.16745445 | O82: 0.16745445 | P82: 0.17245445 | Q82: 0.17245445 | R82: 0.17245445 | S82: 0.17245445 | T82: 0.17245445 | U82: 0.17245445
B83: Growth | E83: 0.21968933 | F83: 0.15266292 | G83: 0.12713445 | H83: -0.33074475 | I83: 0.51721514 | J83: -0.11171013 | K83: 0.4114326 | L83: 0.118 | M83: 0.019230769 | N83: -0.028997845 | O83: 0.06 | P83: 0.081351809 | Q83: 0.05 | R83: 0.05 | S83: 0.05 | T83: 0.05 | U83: 0.05
B86: EBIT | D86: 802.8 | E86: 1016.9 | F86: 1179.1 | G86: 1285.7 | H86: 752.3 | I86: 1291.4 | J86: 1134 | K86: 1725 | L86: 1953 | M86: 1990 | N86: 1837.4625 | O86: 1934.3276 | P86: 2090.6088 | Q86: 2183.8144 | R86: 2283.5366 | S86: 2389.5445 | T86: 2501.7624 | U86: 2620.228
B87: EBIT Margin | D87: 0.091046215 | E87: 0.11837357 | F87: 0.12623116 | G87: 0.13787076 | H87: 0.092519031 | I87: 0.13296405 | J87: 0.10686016 | K87: 0.1523717 | L87: 0.16181954 | M87: 0.1596214 | N87: 0.13904349 | O87: 0.13808813 | P87: 0.14213786 | Q87: 0.14140456 | R87: 0.14082067 | S87: 0.14034089 | T87: 0.13993485 | U87: 0.13958206
B88: Growth | E88: 0.26669158 | F88: 0.15950438 | G88: 0.090407938 | H88: -0.41487128 | I88: 0.71660242 | J88: -0.12188323 | K88: 0.52116402 | L88: 0.13217391 | M88: 0.018945212 | N88: -0.076652008 | O88: 0.052716791 | P88: 0.080793513 | Q88: 0.044582994 | R88: 0.045664265 | S88: 0.046422673 | T88: 0.046962048 | U88: 0.047352836
B91: Profit After Tax | D91: 93 | E91: 651.9 | F91: 683.6 | G91: 620.6 | H91: 362.1 | I91: 810.6 | J91: 1125.8 | K91: 1408 | L91: 1582 | M91: 1838 | N91: 1459.2636 | O91: 1519.6277 | P91: 1658.7493 | Q91: 1730.6054 | R91: 1828.7329 | S91: 1912.5676 | T91: 2022.4715 | U91: 2118.1172
B92: PAT Margin | D92: 0.010547207 | E92: 0.07588527 | F92: 0.07318431 | G92: 0.066549424 | H92: 0.044531625 | I92: 0.083460319 | J92: 0.10608745 | K92: 0.12437064 | L92: 0.13107963 | M92: 0.14742921 | N92: 0.11042463 | O92: 0.10848345 | P92: 0.11277628 | Q92: 0.11205875 | R92: 0.11277392 | S92: 0.11232745 | T92: 0.11312595 | U92: 0.11283413
B93: Growth | E93: 6.0096774 | F93: 0.04862709 | G93: -0.092159157 | H93: -0.41653239 | I93: 1.2386081 | J93: 0.38884777 | K93: 0.25066619 | L93: 0.12357955 | M93: 0.16182048 | N93: -0.20605895 | O93: 0.041366079 | P93: 0.091549825 | Q93: 0.043319438 | R93: 0.056701262 | S93: 0.045843037 | T93: 0.057464082 | U93: 0.047291464

Sheet DCF
B2: DCF Valuation | J2: =PL!T2 -> CURRENTLY RUNNING: BASE SCENARIO | N2: WACC Calculation
B4: Particulars | C4: 2027 | D4: =C4+1 -> 2028 | E4: =D4+1 -> 2029 | F4: =E4+1 -> 2030 | G4: =F4+1 -> 2031 | H4: =G4+1 -> 2032 | I4: =H4+1 -> 2033 | J4: =I4+1 -> 2034 | N4: Risk Free Rate | Q4: 0.07 | R4: (10-yr G-Sec)
N5: Rm | Q5: 0.11 | R5: Nifty50 5 Year Monthly Return
B6: EBIT | C6: =PL!M14 -> 2170.3113 | D6: =PL!N14 -> 2433.4848 | E6: =PL!O14 -> 2700.3359 | F6: =PL!P14 -> 2965.1879 | G6: =PL!Q14 -> 3148.079 | H6: =PL!R14 -> 3344.665 | I6: =PL!S14 -> 3555.2941 | J6: =PL!T14 -> 3780.4994 | N6: Market Risk Premium | Q6: =Q5-Q4 -> 0.04 | R6: Rm-Rf
B7: Tax | C7: =Assumptions!E10 -> 0.25 | D7: =Assumptions!F10 -> 0.25 | E7: =Assumptions!G10 -> 0.25 | F7: =Assumptions!H10 -> 0.25 | G7: =Assumptions!I10 -> 0.25 | H7: =Assumptions!J10 -> 0.25 | I7: =Assumptions!K10 -> 0.25 | J7: =Assumptions!L10 -> 0.25 | N7: Beta | Q7: 0.92 | R7: Rf​+β×ERP
B8: NOPAT | C8: =C6*(1-C7) -> 1627.7334 | D8: =D6*(1-D7) -> 1825.1136 | E8: =E6*(1-E7) -> 2025.2519 | F8: =F6*(1-F7) -> 2223.8909 | G8: =G6*(1-G7) -> 2361.0592 | H8: =H6*(1-H7) -> 2508.4988 | I8: =I6*(1-I7) -> 2666.4706 | J8: =J6*(1-J7) -> 2835.3746 | N8: CAPM | Q8: =Q4+Q7*Q6 -> 0.1068
B9: Dep & Amor. | C9: =-PL!M13 -> 377.0129 | D9: =-PL!N13 -> 417.15874 | E9: =-PL!O13 -> 458.34414 | F9: =-PL!P13 -> 500.18378 | G9: =-PL!Q13 -> 542.54183 | H9: =-PL!R13 -> 585.84613 | I9: =-PL!S13 -> 630.7003 | J9: =-PL!T13 -> 677.58456 | N9: WACC | Q9: =Q8 -> 0.1068 | R9: Debt is almost negligible, therefore no impact on WACC
B10: Capex | C10: =-'Working Schedules'!H42 -> -203.83545 | D10: =-'Working Schedules'!I42 -> -222.18064 | E10: =-'Working Schedules'!J42 -> -239.95509 | F10: =-'Working Schedules'!K42 -> -256.75195 | G10: =-'Working Schedules'!L42 -> -273.44082 | H10: =-'Working Schedules'!M42 -> -291.21448 | I10: =-'Working Schedules'!N42 -> -310.14342 | J10: =-'Working Schedules'!O42 -> -330.30274
B11: Changes in NWC | C11: =-'Working Capital Schedule'!M21 -> -685.86951 | D11: =-'Working Capital Schedule'!N21 -> 124.64106 | E11: =-'Working Capital Schedule'!O21 -> -495.70166 | F11: =-'Working Capital Schedule'!P21 -> 138.54864 | G11: =-'Working Capital Schedule'!Q21 -> -527.54843 | H11: =-'Working Capital Schedule'!R21 -> 98.47563 | I11: =-'Working Capital Schedule'!S21 -> -553.82515 | J11: =-'Working Capital Schedule'!T21 -> 70.579636
B12: Free Cash Flow | C12: =SUM(C8:C11) -> 1115.0414 | D12: =SUM(D8:D11) -> 2144.7328 | E12: =SUM(E8:E11) -> 1747.9393 | F12: =SUM(F8:F11) -> 2605.8714 | G12: =SUM(G8:G11) -> 2102.6118 | H12: =SUM(H8:H11) -> 2901.606 | I12: =SUM(I8:I11) -> 2433.2023 | J12: =SUM(J8:J11) -> 3253.236
B13: Discount Period | C13: 1 | D13: =C13+1 -> 2 | E13: =D13+1 -> 3 | F13: =E13+1 -> 4 | G13: =F13+1 -> 5 | H13: =G13+1 -> 6 | I13: =H13+1 -> 7 | J13: =I13+1 -> 8
B15: PV of FCF | C15: =C12/(1+$Q$9)^C13 -> 1007.4461 | D15: =D12/(1+$Q$9)^D13 -> 1750.7933 | E15: =E12/(1+$Q$9)^E13 -> 1289.1959 | F15: =F12/(1+$Q$9)^F13 -> 1736.5063 | G15: =G12/(1+$Q$9)^G13 -> 1265.9406 | H15: =H12/(1+$Q$9)^H13 -> 1578.4235 | I15: =I12/(1+$Q$9)^I13 -> 1195.8981 | J15: =J12/(1+$Q$9)^J13 -> 1444.6491
N16: Sensitivity Analysis | U16: Horizontal axis | W16: WACC
U17: Vertical axis | W17: Terminal Growth
B18: Terminal Growth Rate (g) | C18: 0.06 | N18: =IF(C28<0,"",C28) -> 642.24 | O18: 0.08 | P18: =O18+0.5% -> 0.085 | Q18: =P18+0.5% -> 0.09 | R18: =Q18+0.5% -> 0.095 | S18: =R18+0.5% -> 0.1 | T18: 0.1068 | U18: 0.12 | V18: =U18+0.5% -> 0.125 | W18: =V18+0.5% -> 0.13
B19: Terminal Year FCF | C19: =J12 -> 3253.236 | N19: 0.05 | O19: 1056.569 | P19: 905.78038 | Q19: 792.81642 | R19: 705.06463 | S19: 634.9577 | T19: 559.5479 | U19: 455.30914 | V19: 425.50339 | W19: 399.4706
B20: Terminal Value | C20: =C19*(1+C18)/(Q9-C18) -> 73684.406 | N20: =N19+0.5% -> 0.055 | O20: 1230.5431 | P20: 1026.094 | Q20: 880.19375 | R20: 770.88207 | S20: 685.95897 | T20: 596.90302 | U20: 477.54094 | V20: 444.17945 | W20: 415.31267
B21: PV of Terminal Value | C21: =C20/(1+Q9)^J13 -> 32720.685 | N21: =N20+0.5% -> 0.06 | O21: 1491.5044 | P21: 1194.5331 | Q21: 996.69685 | R21: 855.50448 | S21: 749.71055 | T21: 642.24 | U21: 503.47805 | V21: 465.72876 | W21: 433.4179
B22: Sum of OV of FCF | C22: =SUM(C15:J15) -> 11268.853 | N22: =N21+0.5% -> 0.065 | O22: 1926.4397 | P22: 1447.1917 | Q22: 1159.8012 | R22: 968.33437 | S22: 831.67687 | T22: 698.42315 | U22: 534.13099 | V22: 490.86961 | W22: 454.30854
B23: Enterprise Value | C23: =C21+C22 -> 43989.538 | N23: =N22+0.5% -> 0.07 | O23: 2796.3105 | P23: 1868.2894 | Q23: 1404.4577 | R23: 1126.2962 | S23: 940.9653 | T23: 769.87346 | U23: 570.91452 | V23: 520.58153 | W23: 478.68095
B24: Cash | C24: =BS!L43 -> 3134 | N24: =N23+0.5% -> 0.075 | O24: 5405.9228 | P24: 2710.4848 | Q24: 1812.2186 | R24: 1363.239 | S24: 1093.9691 | T24: 863.79243 | U24: 615.87217 | V24: 556.23583 | W24: 507.48472
B25: Debt | C25: =-BS!L15 -> -407 | N25: =N24+0.5% -> 0.08 | P25: 5237.0709 | Q25: 2627.7403 | R25: 1758.1436 | S25: 1323.4748 | T25: 992.75578 | U25: 672.06924 | V25: 599.81331 | W25: 542.04923
B26: Equity Value | C26: =SUM(C23:C25) -> 46716.538 | N26: =N25+0.5% -> 0.085 | Q26: 5074.3055 | R26: 2547.9528 | S26: 1705.9843 | T26: 1180.8766 | U26: 744.3226 | V26: 654.28516 | W26: 584.29475
B27: Shares Outstanding | C27: 72.74 | N27: =N26+0.5% -> 0.09 | R27: 4917.3804 | S27: 2471.0033 | T27: 1480.9742 | U27: 840.66042 | V27: 724.32039 | W27: 637.10165
B28: Per Share Value | C28: =C26/C27 -> 642.24

Sheet Ratio Analysis
B2: Ratio Analysis
B4: Particulars | C4: 2017 | D4: =C4+1 -> 2018 | E4: =D4+1 -> 2019 | F4: =E4+1 -> 2020 | G4: =F4+1 -> 2021 | H4: =G4+1 -> 2022 | I4: =H4+1 -> 2023 | J4: =I4+1 -> 2024 | K4: =J4+1 -> 2025 | ... T4: =S4+1 -> 2034
B6: Profitability Ratios
B7: Gross Margin | C7: =PL!C7/PL!C5 -> 0.41578679 | D7: =PL!D7/PL!D5 -> 0.46950155 | E7: =PL!E7/PL!E5 -> 0.46831107 | F7: =PL!F7/PL!F5 -> 0.42415339 | G7: =PL!G7/PL!G5 -> 0.40876613 | H7: =PL!H7/PL!H5 -> 0.41508793 | I7: =PL!I7/PL!I5 -> 0.38720317 | J7: =PL!J7/PL!J5 -> 0.42213585 | ... T7: =PL!T7/PL!T5 -> 0.47
B8: EBITDA Margin | C8: =PL!C12/PL!C5 -> 0.1124355 | D8: =PL!D12/PL!D5 -> 0.1407585 | E8: =PL!E12/PL!E5 -> 0.14921634 | F8: =PL!F12/PL!F5 -> 0.16846462 | G8: =PL!G12/PL!G5 -> 0.12930282 | H8: =PL!H12/PL!H5 -> 0.16424365 | I8: =PL!I12/PL!I5 -> 0.13352808 | J8: =PL!J12/PL!J5 -> 0.17666284 | ... T8: =PL!T12/PL!T5 -> 0.20245445
B9: EBIT Margin | C9: =PL!C14/PL!C5 -> 0.091046215 | D9: =PL!D14/PL!D5 -> 0.11837357 | E9: =PL!E14/PL!E5 -> 0.12623116 | F9: =PL!F14/PL!F5 -> 0.13787076 | G9: =PL!G14/PL!G5 -> 0.092519031 | H9: =PL!H14/PL!H5 -> 0.13296405 | I9: =PL!I14/PL!I5 -> 0.10686016 | J9: =PL!J14/PL!J5 -> 0.1523717 | ... T9: =PL!T14/PL!T5 -> 0.17168338
B10: Net Profit Margin | C10: =PL!C22/PL!C5 -> 0.010547207 | D10: =PL!D22/PL!D5 -> 0.07588527 | E10: =PL!E22/PL!E5 -> 0.07318431 | F10: =PL!F22/PL!F5 -> 0.066549424 | G10: =PL!G22/PL!G5 -> 0.044531625 | H10: =PL!H22/PL!H5 -> 0.083460319 | I10: =PL!I22/PL!I5 -> 0.10608745 | J10: =PL!J22/PL!J5 -> 0.12437064 | ... T10: =PL!T22/PL!T5 -> 0.1368565
B11: Retrun on Equity (ROE) | C11: =PL!C22/(AVERAGE(BS!C10,1634)) -> 0.054392327 | D11: =PL!D22/AVERAGE(BS!C10,BS!D10) -> 0.31008158 | E11: =PL!E22/AVERAGE(BS!D10,BS!E10) -> 0.24815769 | F11: =PL!F22/AVERAGE(BS!E10,BS!F10) -> 0.18203951 | G11: =PL!G22/AVERAGE(BS!F10,BS!G10) -> 0.092280639 | H11: =PL!H22/AVERAGE(BS!G10,BS!H10) -> 0.17867416 | I11: =PL!I22/AVERAGE(BS!H10,BS!I10) -> 0.2055655 | J11: =PL!J22/AVERAGE(BS!I10,BS!J10) -> 0.21462597 | K11: =PL!K22/AVERAGE(BS!J10,BS!K10) -> 0.20781609 | ... T11: =PL!T22/AVERAGE(BS!S10,BS!T10) -> 0.20457278
B12: Return on Capital Employed (ROCE) | C12: =PL!C14/(BS!C46-BS!C23) -> 0.30080935 | D12: =PL!D14/(BS!D46-BS!D23) -> 0.31888739 | E12: =PL!E14/(BS!E46-BS!E23) -> 0.30275253 | F12: =PL!F14/(BS!F46-BS!F23) -> 0.32575758 | G12: =PL!G14/(BS!G46-BS!G23) -> 0.17471376 | H12: =PL!H14/(BS!H46-BS!H23) -> 0.24519632 | I12: =PL!I14/(BS!I46-BS!I23) -> 0.18210139 | J12: =PL!J14/(BS!J46-BS!J23) -> 0.23202948 | ... T12: =PL!T14/(BS!T46-BS!T23) -> 0.2198676
B13: Liquidity Ratios
B14: Current Ratio | C14: =BS!C44/BS!C23 -> 0.92323875 | D14: =BS!D44/BS!D23 -> 0.99459028 | E14: =BS!E44/BS!E23 -> 1.0094931 | F14: =BS!F44/BS!F23 -> 0.99302681 | G14: =BS!G44/BS!G23 -> 1.1351658 | H14: =BS!H44/BS!H23 -> 1.416765 | I14: =BS!I44/BS!I23 -> 1.7640767 | J14: =BS!J44/BS!J23 -> 1.9338856 | ... T14: =BS!T44/BS!T23 -> 2.4776957
B15: Quick Ratio | C15: =(BS!C44-BS!C41)/BS!C23 -> 0.61368855 | D15: =(BS!D44-BS!D41)/BS!D23 -> 0.66173666 | E15: =(BS!E44-BS!E41)/BS!E23 -> 0.6385325 | F15: =(BS!F44-BS!F41)/BS!F23 -> 0.60002039 | G15: =(BS!G44-BS!G41)/BS!G23 -> 0.65020917 | H15: =(BS!H44-BS!H41)/BS!H23 -> 0.82499657 | I15: =(BS!I44-BS!I41)/BS!I23 -> 1.1330994 | J15: =(BS!J44-BS!J41)/BS!J23 -> 1.3930687 | ... T15: =(BS!T44-BS!T41)/BS!T23 -> 1.9366092
B16: Leverage Ratios
B17: Debt Equity Ratio | C17: =(BS!C16+BS!C20)/BS!C10 -> 2.1225918 | D17: =(BS!D16+BS!D20)/BS!D10 -> 1.2695217 | E17: =(BS!E16+BS!E20)/BS!E10 -> 0.93638158 | F17: =(BS!F16+BS!F20)/BS!F10 -> 0.48948498 | G17: =(BS!G16+BS!G20)/BS!G10 -> 0.25743968 | H17: =(BS!H16+BS!H20)/BS!H10 -> 0.13200234 | I17: =(BS!I16+BS!I20)/BS!I10 -> 0.038103175 | J17: =(BS!J16+BS!J20)/BS!J10 -> 0.047521416 | ... T17: =(BS!T16+BS!T20)/BS!T10 -> 0.12949303
B18: Net debt to EBITDA | C18: =(BS!C13+BS!C15-BS!C43)/PL!C12 -> 0.80280412 | D18: =(BS!D13+BS!D15-BS!D43)/PL!D12 -> 0.42482633 | E18: =(BS!E13+BS!E15-BS!E43)/PL!E12 -> 0.37408523 | F18: =(BS!F13+BS!F15-BS!F43)/PL!F12 -> 0.087651178 | G18: =(BS!G13+BS!G15-BS!G43)/PL!G12 -> 0.072379684 | H18: =(BS!H13+BS!H15-BS!H43)/PL!H12 -> -0.011033099 | I18: =(BS!I13+BS!I15-BS!I43)/PL!I12 -> -0.67494707 | J18: =(BS!J13+BS!J15-BS!J43)/PL!J12 -> -0.8138 | ... T18: =(BS!T13+BS!T15-BS!T43)/PL!T12 -> -1.3708795
B19: Interest Coverage Ratio | C19: =PL!C14/-PL!C17 -> 2.1402293 | D19: =PL!D14/-PL!D17 -> 3.6645045 | E19: =PL!E14/-PL!E17 -> 4.9709106 | F19: =PL!F14/-PL!F17 -> 6.0646226 | G19: =PL!G14/-PL!G17 -> 4.0101279 | H19: =PL!H14/-PL!H17 -> 14.675 | I19: =PL!I14/-PL!I17 -> 10.903846 | J19: =PL!J14/-PL!J17 -> 22.697368 | ... T19: =PL!T14/-PL!T17 -> 17.959221
B20: Efficiency Ratios
B21: Asset Turnover Ratio | C21: =PL!C5/(AVERAGE(7889,BS!C46)) -> 1.0506467 | D21: =PL!D5/AVERAGE(BS!C46,BS!D46) -> 0.9624136 | E21: =PL!E5/AVERAGE(BS!D46,BS!E46) -> 1.0341209 | F21: =PL!F5/AVERAGE(BS!E46,BS!F46) -> 1.0384517 | G21: =PL!G5/AVERAGE(BS!F46,BS!G46) -> 0.93526107 | H21: =PL!H5/AVERAGE(BS!G46,BS!H46) -> 1.1132775 | I21: =PL!I5/AVERAGE(BS!H46,BS!I46) -> 1.1366265 | J21: =PL!J5/AVERAGE(BS!I46,BS!J46) -> 1.0776517 | K21: =PL!K5/AVERAGE(BS!J46,BS!K46) -> 0.98534514 | ... T21: =PL!T5/AVERAGE(BS!S46,BS!T46) -> 0.90748513
B22: Fixed Asset Turnover Ratio | C22: =PL!C5/AVERAGE(1887,BS!C35) -> 4.405556 | D22: =PL!D5/AVERAGE(BS!C35,BS!D35) -> 4.2362049 | E22: =PL!E5/AVERAGE(BS!D35,BS!E35) -> 4.8698191 | F22: =PL!F5/AVERAGE(BS!E35,BS!F35) -> 4.7142027 | G22: =PL!G5/AVERAGE(BS!F35,BS!G35) -> 4.0314832 | H22: =PL!H5/AVERAGE(BS!G35,BS!H35) -> 4.9598611 | I22: =PL!I5/AVERAGE(BS!H35,BS!I35) -> 6.0331448 | J22: =PL!J5/AVERAGE(BS!I35,BS!J35) -> 7.465216 | K22: =PL!K5/AVERAGE(BS!J35,BS!K35) -> 7.6236498 | ... T22: =PL!T5/AVERAGE(BS!S35,BS!T35) -> 7.2790275
B23: Working Capital Ratios
B24: Receivables days | C24: =AVERAGE(2303,BS!C40)*365/PL!C5 -> 108.79422 | D24: =AVERAGE(BS!C40,BS!D40)*365/PL!D5 -> 120.33962 | E24: =AVERAGE(BS!D40,BS!E40)*365/PL!E5 -> 102.64648 | F24: =AVERAGE(BS!E40,BS!F40)*365/PL!F5 -> 94.445815 | G24: =AVERAGE(BS!F40,BS!G40)*365/PL!G5 -> 100.341 | H24: =AVERAGE(BS!G40,BS!H40)*365/PL!H5 -> 85.699312 | I24: =AVERAGE(BS!H40,BS!I40)*365/PL!I5 -> 82.67876 | J24: =AVERAGE(BS!I40,BS!J40)*365/PL!J5 -> 88.501457 | K24: =AVERAGE(BS!J40,BS!K40)*365/PL!K5 -> 97.774878 | ... T24: =AVERAGE(BS!S40,BS!T40)*365/PL!T5 -> 97
B25: Payables days | C25: =AVERAGE(1019,BS!C19)*365/-PL!C6 -> 79.489692 | D25: =AVERAGE(BS!C19,BS!D19)*365/-PL!D6 -> 107.31431 | E25: =AVERAGE(BS!D19,BS!E19)*365/-PL!E6 -> 105.22119 | F25: =AVERAGE(BS!E19,BS!F19)*365/-PL!F6 -> 88.622952 | G25: =AVERAGE(BS!F19,BS!G19)*365/-PL!G6 -> 99.330109 | H25: =AVERAGE(BS!G19,BS!H19)*365/-PL!H6 -> 96.353087 | I25: =AVERAGE(BS!H19,BS!I19)*365/-PL!I6 -> 94.424035 | J25: =AVERAGE(BS!I19,BS!J19)*365/-PL!J6 -> 104.2359 | K25: =AVERAGE(BS!J19,BS!K19)*365/-PL!K6 -> 111.54847 | ... T25: =AVERAGE(BS!S19,BS!T19)*365/-PL!T6 -> 104
B26: Inventory days | C26: =AVERAGE(1952,BS!C41)*365/-PL!C6 -> 137.44628 | D26: =AVERAGE(BS!C41,BS!D41)*365/-PL!D6 -> 154.06759 | E26: =AVERAGE(BS!D41,BS!E41)*365/-PL!E6 -> 141.6227 | F26: =AVERAGE(BS!E41,BS!F41)*365/-PL!F6 -> 131.24367 | G26: =AVERAGE(BS!F41,BS!G41)*365/-PL!G6 -> 151.06407 | H26: =AVERAGE(BS!G41,BS!H41)*365/-PL!H6 -> 135.20208 | I26: =AVERAGE(BS!H41,BS!I41)*365/-PL!I6 -> 123.10822 | J26: =AVERAGE(BS!I41,BS!J41)*365/-PL!J6 -> 119.76039 | K26: =AVERAGE(BS!J41,BS!K41)*365/-PL!K6 -> 116.20408 | ... T26: =AVERAGE(BS!S41,BS!T41)*365/-PL!T6 -> 135
B27: Valuation Ratios
B28: EV/EBITDA | C28: =C37/PL!C12 -> 32.645814 | D28: =D37/PL!D12 -> 38.021998 | E28: =E37/PL!E12 -> 28.555747 | F28: =F37/PL!F12 -> 22.775493 | G28: =G37/PL!G12 -> 36.048031 | H28: =H37/PL!H12 -> 39.341161 | I28: =I37/PL!I12 -> 39.211418 | J28: =J37/PL!J12 -> 40.21156 | ... T28: =T37/PL!T12 -> 21.023884
B29: EV/Sales | C29: =C37/PL!C5 -> 3.6705483 | D29: =D37/PL!D5 -> 5.3519195 | E29: =E37/PL!E5 -> 4.2609841 | F29: =F37/PL!F5 -> 3.8368649 | G29: =G37/PL!G5 -> 4.661112 | H29: =H37/PL!H5 -> 6.4615358 | I29: =I37/PL!I5 -> 5.2358255 | J29: =J37/PL!J5 -> 7.1038883 | ... T29: =T37/PL!T5 -> 4.2563788
B30: EV/EBIT | C30: =C37/PL!C14 -> 40.315222 | D30: =D37/PL!D14 -> 45.212115 | E30: =E37/PL!E14 -> 33.755407 | F30: =F37/PL!F14 -> 27.829431 | G30: =G37/PL!G14 -> 50.380035 | H30: =H37/PL!H14 -> 48.596113 | I30: =I37/PL!I14 -> 48.996984 | J30: =J37/PL!J14 -> 46.622099 | ... T30: =T37/PL!T14 -> 24.792026
B31: PE Ratio | C31: =C34/PL!C22 -> 339.45333 | D31: =D34/PL!D22 -> 69.738457 | E31: =E34/PL!E22 -> 57.459918 | F31: =F34/PL!F22 -> 57.432485 | G31: =G34/PL!G22 -> 104.45954 | H31: =H34/PL!H22 -> 77.442166 | I31: =I34/PL!I22 -> 50.203393 | J31: =J34/PL!J22 -> 58.274659 | ... T31: =T34/PL!T22 -> 32.005933
B34: Market Cap | C34: =C35*C36 -> 31569.16 | D34: =D35*D36 -> 45462.5 | E34: =E35*E36 -> 39279.6 | F34: =F35*F36 -> 35642.6 | G34: =G35*G36 -> 37824.8 | H34: =H35*H36 -> 62774.62 | I34: =I35*I36 -> 56518.98 | J34: =J35*J36 -> 82050.72 | ... L34: =L35*L36 -> 96453.24 | M34: =L34 -> 96453.24 | N34: =M34 -> 96453.24 | O34: =N34 -> 96453.24 | P34: =O34 -> 96453.24 | Q34: =P34 -> 96453.24 | R34: =Q34 -> 96453.24 | S34: =R34 -> 96453.24 | T34: =S34 -> 96453.24
B35: CMP | C35: 434 | D35: 625 | E35: 540 | F35: 490 | G35: 520 | H35: 863 | I35: 777 | J35: 1128 | K35: 1427 | L35: 1326
B36: Shares outstanding | C36: 72.74 | D36: 72.74 | E36: 72.74 | F36: 72.74 | G36: 72.74 | H36: 72.74 | I36: 72.74 | J36: 72.74 | K36: 72.74 | L36: 72.74 | M36: 72.74 | N36: 72.74 | O36: 72.74 | P36: 72.74 | Q36: 72.74 | R36: 72.74 | S36: 72.74 | T36: 72.74
B37: EV | C37: =C34+BS!C13+BS!C15-BS!C43 -> 32365.06 | D37: =D34+BS!D13+BS!D15-BS!D43 -> 45976.2 | E37: =E34+BS!E13+BS!E15-BS!E43 -> 39801 | F37: =F34+BS!F13+BS!F15-BS!F43 -> 35780.3 | G37: =G34+BS!G13+BS!G15-BS!G43 -> 37900.9 | H37: =H34+BS!H13+BS!H15-BS!H43 -> 62757.02 | I37: =I34+BS!I13+BS!I15-BS!I43 -> 55562.58 | J37: =J34+BS!J13+BS!J15-BS!J43 -> 80423.12 | ... L37: =L34+BS!L13+BS!L15-BS!L43 -> 93726.24 | M37: =L37 -> 93726.24 | N37: =M37 -> 93726.24 | O37: =N37 -> 93726.24 | P37: =O37 -> 93726.24 | Q37: =P37 -> 93726.24 | R37: =Q37 -> 93726.24 | S37: =R37 -> 93726.24 | T37: =S37 -> 93726.24

Sheet PL
B2: Income Statement | T2: ="CURRENTLY RUNNING: "&UPPER(CHOOSE(Scenarios!$D$4,Scenarios!C12,Scenarios!C13,Scenarios!C14))&" SCENARIO" -> CURRENTLY RUNNING: BASE SCENARIO
A4: x | B4: Particulars | C4: 2017 | D4: =C4+1 -> 2018 | E4: =D4+1 -> 2019 | F4: =E4+1 -> 2020 | G4: =F4+1 -> 2021 | H4: =G4+1 -> 2022 | I4: =H4+1 -> 2023 | J4: =I4+1 -> 2024 | K4: =J4+1 -> 2025 | ... T4: =S4+1 -> 2034
B5: Sales | C5: 8817.5 | D5: 8590.6 | E5: 9340.8 | F5: 9325.4 | G5: 8131.3 | H5: 9712.4 | I5: 10612 | J5: 11321 | K5: 12069 | L5: 12467 | M5: =L5*(1+Scenarios!H10) -> 13589.03 | N5: =M5*(1+Scenarios!I10) -> 14812.043 | O5: =N5*(1+Scenarios!J10) -> 15997.006 | P5: =O5*(1+Scenarios!K10) -> 17116.797 | Q5: =P5*(1+Scenarios!L10) -> 18229.388 | R5: =Q5*(1+Scenarios!M10) -> 19414.299 | S5: =R5*(1+Scenarios!N10) -> 20676.228 | T5: =S5*(1+Scenarios!O10) -> 22020.183
B6: Total COGS | C6: -5151.3 | D6: -4557.3 | E6: -4966.4 | F6: -5370 | G6: -4807.5 | H6: -5680.9 | I6: -6503 | J6: -6542 | K6: -6860 | L6: -6674 | M6: =-M5*(1-Scenarios!H19) -> -7406.0213 | N6: =-N5*(1-Scenarios!I19) -> -7998.5031 | O6: =-O5*(1-Scenarios!J19) -> -8558.3983 | P6: =-P5*(1-Scenarios!K19) -> -9071.9022 | Q6: =-Q5*(1-Scenarios!L19) -> -9661.5758 | R6: =-R5*(1-Scenarios!M19) -> -10289.578 | S6: =-S5*(1-Scenarios!N19) -> -10958.401 | T6: =-T5*(1-Scenarios!O19) -> -11670.697
A7: x | B7: Gross Profit | C7: =C5+C6 -> 3666.2 | D7: =D5+D6 -> 4033.3 | E7: =E5+E6 -> 4374.4 | F7: =F5+F6 -> 3955.4 | G7: =G5+G6 -> 3323.8 | H7: =H5+H6 -> 4031.5 | I7: =I5+I6 -> 4109 | J7: =J5+J6 -> 4779 | ... T7: =T5+T6 -> 10349.486
B8: Operating Expenes
B9: Employee Cost | C9: -688.9 | D9: -681.2 | E9: -690.2 | F9: -530.4 | G9: -557 | H9: -653.9 | I9: -613 | J9: -549 | K9: -614 | L9: -635 | M9: =-M5*Assumptions!E7 -> -849.93335 | N9: =-N5*Assumptions!F7 -> -926.42735 | O9: =-O5*Assumptions!G7 -> -1000.5415 | P9: =-P5*Assumptions!H7 -> -1070.5794 | Q9: =-Q5*Assumptions!I7 -> -1140.1671 | R9: =-R5*Assumptions!J7 -> -1214.278 | S9: =-S5*Assumptions!K7 -> -1293.206 | T9: =-T5*Assumptions!L7 -> -1377.2644
B10: Selling and admin | C10: -1985.9 | D10: -2142.9 | E10: -2290.4 | F10: -1854 | G10: -1715.4 | H10: -1782.4 | I10: -2079 | J10: -2230 | K10: -2359 | L10: -2879 | M10: =-M5*Assumptions!E8 -> -2785.7512 | N10: =-N5*Assumptions!F8 -> -3036.4688 | O10: =-O5*Assumptions!G8 -> -3279.3863 | P10: =-P5*Assumptions!H8 -> -3508.9433 | Q10: =-Q5*Assumptions!I8 -> -3737.0246 | R10: =-R5*Assumptions!J8 -> -3979.9312 | S10: =-S5*Assumptions!K8 -> -4238.6267 | T10: =-T5*Assumptions!L8 -> -4514.1375
B11: Total Operating Expenses | C11: =SUM(C9:C10) -> -2674.8 | D11: =SUM(D9:D10) -> -2824.1 | E11: =SUM(E9:E10) -> -2980.6 | F11: =SUM(F9:F10) -> -2384.4 | G11: =SUM(G9:G10) -> -2272.4 | H11: =SUM(H9:H10) -> -2436.3 | I11: =SUM(I9:I10) -> -2692 | J11: =SUM(J9:J10) -> -2779 | ... T11: =SUM(T9:T10) -> -5891.4019
A12: x | B12: EBITDA | C12: =C7+C11 -> 991.4 | D12: =D7+D11 -> 1209.2 | E12: =E7+E11 -> 1393.8 | F12: =F7+F11 -> 1571 | G12: =G7+G11 -> 1051.4 | H12: =H7+H11 -> 1595.2 | I12: =I7+I11 -> 1417 | J12: =J7+J11 -> 2000 | ... T12: =T7+T11 -> 4458.084
B13: Depreciation & Amortization | C13: -188.6 | D13: -192.3 | E13: -214.7 | F13: -285.3 | G13: -299.1 | H13: -303.8 | I13: -283 | J13: -275 | K13: -283 | L13: -289 | M13: ='Working Schedules'!H70 -> -377.0129 | N13: ='Working Schedules'!I70 -> -417.15874 | O13: ='Working Schedules'!J70 -> -458.34414 | P13: ='Working Schedules'!K70 -> -500.18378 | Q13: ='Working Schedules'!L70 -> -542.54183 | R13: ='Working Schedules'!M70 -> -585.84613 | S13: ='Working Schedules'!N70 -> -630.7003 | T13: ='Working Schedules'!O70 -> -677.58456
B14: EBIT | C14: =C12+C13 -> 802.8 | D14: =D12+D13 -> 1016.9 | E14: =E12+E13 -> 1179.1 | F14: =F12+F13 -> 1285.7 | G14: =G12+G13 -> 752.3 | H14: =H12+H13 -> 1291.4 | I14: =I12+I13 -> 1134 | J14: =J12+J13 -> 1725 | ... T14: =T12+T13 -> 3780.4994
B15: Other Income(Inc Interest) | C15: 105.3 | D15: 218.9 | E15: 69.2 | F15: 22 | G15: 39.6 | H15: 35.5 | I15: 73.1 | J15: 225 | K15: 336 | L15: 478 | M15: 0 | N15: 0 | O15: 0 | P15: 0 | Q15: 0 | R15: 0 | S15: 0 | T15: 0
B16: Exceptional Items | C16: -368.1 | D16: -44.5 | E16: 2.6 | F16: 66.6 | G16: -64.3 | H16: -165.2 | I16: 176.4 | J16: -17 | K16: -65 | L16: 38 | M16: 0 | N16: 0 | O16: 0 | P16: 0 | Q16: 0 | R16: 0 | S16: 0 | T16: 0
B17: Interest Paid | C17: -375.1 | D17: -277.5 | E17: -237.2 | F17: -212 | G17: -187.6 | H17: -88 | I17: -104 | J17: -76 | K17: -89 | L17: -158 | M17: =-'Working Schedules'!H33 -> -95.837343 | N17: =-'Working Schedules'!I33 -> -108.83716 | O17: =-'Working Schedules'!J33 -> -123.13957 | P17: =-'Working Schedules'!K33 -> -138.58164 | Q17: =-'Working Schedules'!L33 -> -155.02463 | R17: =-'Working Schedules'!M33 -> -172.45339 | S17: =-'Working Schedules'!N33 -> -190.92618 | T17: =-'Working Schedules'!O33 -> -210.50465
B18: Interest Received | M18: =BS!L43*Assumptions!E9 -> 203.71 | N18: =BS!M43*Assumptions!F9 -> 197.0201 | O18: =BS!N43*Assumptions!G9 -> 247.64641 | P18: =BS!O43*Assumptions!H9 -> 263.59935 | Q18: =BS!P43*Assumptions!I9 -> 325.87271 | R18: =BS!Q43*Assumptions!J9 -> 349.33898 | S18: =BS!R43*Assumptions!K9 -> 417.49706 | T18: =BS!S43*Assumptions!L9 -> 448.14526
A19: x | B19: Profit Before Tax (PBT) | C19: =SUM(C14:C17) -> 164.9 | D19: =SUM(D14:D17) -> 913.8 | E19: =SUM(E14:E18) -> 1013.7 | F19: =SUM(F14:F18) -> 1162.3 | G19: =SUM(G14:G18) -> 540 | H19: =SUM(H14:H18) -> 1073.7 | I19: =SUM(I14:I18) -> 1279.5 | J19: =SUM(J14:J18) -> 1857 | K19: =SUM(K14:K18) -> 2135 | L19: =SUM(L14:L18) -> 2348 | ... T19: =SUM(T14:T18) -> 4018.1401
B20: Tax | C20: -69.7 | D20: -259.9 | E20: -328.1 | F20: -539.7 | G20: -177.9 | H20: -276 | I20: -153 | J20: -449 | K20: -553 | L20: -510 | M20: =-M19*Assumptions!E10 -> -569.54598 | N20: =-N19*Assumptions!F10 -> -630.41694 | O20: =-O19*Assumptions!G10 -> -706.21069 | P20: =-P19*Assumptions!H10 -> -772.55139 | Q20: =-Q19*Assumptions!I10 -> -829.73176 | R20: =-R19*Assumptions!J10 -> -880.38765 | S20: =-S19*Assumptions!K10 -> -945.46624 | T20: =-T19*Assumptions!L10 -> -1004.535
B21: Adjustments | C21: -2.2 | D21: -2 | E21: -2 | F21: -2 | G21: 0 | H21: 12.9 | I21: -0.7 | J21: 0 | K21: 0 | L21: 0 | M21: 0 | N21: 0 | O21: 0 | P21: 0 | Q21: 0 | R21: 0 | S21: 0 | T21: 0
A22: x | B22: Profit After Tax (PAT) | C22: =SUM(C19:C21) -> 93 | D22: =SUM(D19:D21) -> 651.9 | E22: =SUM(E19:E21) -> 683.6 | F22: =SUM(F19:F21) -> 620.6 | G22: =SUM(G19:G21) -> 362.1 | H22: =SUM(H19:H21) -> 810.6 | I22: =SUM(I19:I21) -> 1125.8 | J22: =SUM(J19:J21) -> 1408 | ... L22: =SUM(L19:L21) -> 1838 | M22: =M19+M20 -> 1708.6379 | N22: =N19+N20 -> 1891.2508 | O22: =O19+O20 -> 2118.6321 | P22: =P19+P20 -> 2317.6542 | Q22: =Q19+Q20 -> 2489.1953 | R22: =R19+R20 -> 2641.163 | S22: =S19+S20 -> 2836.3987 | T22: =T19+T20 -> 3013.605

Sheet BS
B2: Balance Sheet | T2: =PL!T2 -> CURRENTLY RUNNING: BASE SCENARIO
B4: Particulars | C4: 2017 | D4: =C4+1 -> 2018 | E4: =D4+1 -> 2019 | F4: =E4+1 -> 2020 | G4: =F4+1 -> 2021 | H4: =G4+1 -> 2022 | I4: =H4+1 -> 2023 | J4: =I4+1 -> 2024 | K4: =J4+1 -> 2025 | ... T4: =S4+1 -> 2034
A6: x | B6: Equities & Liablilities
B7: Shareholders' Fund
B8: Share Capital | C8: 145.3 | D8: 145.3 | E8: 145.3 | F8: 145.3 | G8: 145.3 | H8: 145.3 | I8: 145.5 | J8: 145 | K8: 145 | L8: 145 | M8: =L8 -> 145 | N8: =M8 -> 145 | O8: =N8 -> 145 | P8: =O8 -> 145 | Q8: =P8 -> 145 | R8: =Q8 -> 145 | S8: =R8 -> 145 | T8: =S8 -> 145
B9: Reserve & Surplus | C9: 1640.3 | D9: 2273.8 | E9: 2945 | F9: 3582.7 | G9: 3974.5 | H9: 4808.4 | I9: 5854 | J9: 6976 | K9: 7959 | L9: 8808 | M9: =L9+PL!M22*(1-Assumptions!E11) -> 9371.8505 | N9: =M9+PL!N22*(1-Assumptions!F11) -> 9995.9633 | O9: =N9+PL!O22*(1-Assumptions!G11) -> 10695.112 | P9: =O9+PL!P22*(1-Assumptions!H11) -> 11459.938 | Q9: =P9+PL!Q22*(1-Assumptions!I11) -> 12281.372 | R9: =Q9+PL!R22*(1-Assumptions!J11) -> 13152.956 | S9: =R9+PL!S22*(1-Assumptions!K11) -> 14088.968 | T9: =S9+PL!T22*(1-Assumptions!L11) -> 15083.457
B10: Total Shareholders' Fund | C10: =SUM(C8:C9) -> 1785.6 | D10: =SUM(D8:D9) -> 2419.1 | E10: =SUM(E8:E9) -> 3090.3 | F10: =SUM(F8:F9) -> 3728 | G10: =SUM(G8:G9) -> 4119.8 | H10: =SUM(H8:H9) -> 4953.7 | I10: =SUM(I8:I9) -> 5999.5 | J10: =SUM(J8:J9) -> 7121 | ... T10: =SUM(T8:T9) -> 15228.457
A12: x | B12: Non-Current Liabilities
B13: Long Term Borrowings | C13: 869.7 | D13: 762.8 | E13: 780.4 | F13: 14.7 | G13: 2.2 | H13: 0.9 | I13: 0.3 | J13: 0 | K13: 0 | L13: 0 | M13: =L13 -> 0 | N13: =M13 -> 0 | O13: =N13 -> 0 | P13: =O13 -> 0 | Q13: =P13 -> 0 | R13: =Q13 -> 0 | S13: =R13 -> 0 | T13: =S13 -> 0
B14: Deferred Tax Liabilities [Net] | C14: 0 | D14: 0 | E14: 0 | F14: 7.6 | G14: 26.1 | H14: 48.3 | I14: 45.1 | J14: 73 | K14: 72 | L14: 18 | M14: =L14 -> 18 | N14: =M14 -> 18 | O14: =N14 -> 18 | P14: =O14 -> 18 | Q14: =P14 -> 18 | R14: =Q14 -> 18 | S14: =R14 -> 18 | T14: =S14 -> 18
B15: Lease Liabilities | C15: 13.5 | D15: 7 | E15: 23.9 | F15: 196.5 | G15: 157.8 | H15: 263.9 | I15: 182.4 | J15: 240.4 | K15: 480 | L15: 407 | M15: ='Working Schedules'!H22 -> 552.87866 | N15: ='Working Schedules'!I22 -> 713.878 | O15: ='Working Schedules'!J22 -> 889.40594 | P15: ='Working Schedules'!K22 -> 1077.2208 | Q15: ='Working Schedules'!L22 -> 1276.2999 | R15: ='Working Schedules'!M22 -> 1487.3093 | S15: ='Working Schedules'!N22 -> 1710.9538 | T15: ='Working Schedules'!O22 -> 1947.979
B16: Total Non-Current Liabilities | C16: =SUM(C13:C15) -> 883.2 | D16: =SUM(D13:D15) -> 769.8 | E16: =SUM(E13:E15) -> 804.3 | F16: =SUM(F13:F15) -> 218.8 | G16: =SUM(G13:G15) -> 186.1 | H16: =SUM(H13:H15) -> 313.1 | I16: =SUM(I13:I15) -> 227.8 | J16: =SUM(J13:J15) -> 313.4 | ... T16: =SUM(T13:T15) -> 1965.979
A18: x | B18: Current Liabilities
B19: Trade Payables | C19: 1224.7 | D19: 1455.1 | E19: 1408.3 | F19: 1199.4 | G19: 1417.2 | H19: 1582.1 | I19: 1782.5 | J19: 1954 | K19: 2239 | L19: 2383 | M19: ='Working Capital Schedule'!M15 -> 1837.4176 | N19: ='Working Capital Schedule'!N15 -> 2720.6334 | O19: ='Working Capital Schedule'!O15 -> 2156.4812 | P19: ='Working Capital Schedule'!P15 -> 3013.2603 | Q19: ='Working Capital Schedule'!Q15 -> 2492.5144 | R19: ='Working Capital Schedule'!R15 -> 3371.1356 | S19: ='Working Capital Schedule'!S15 -> 2873.6517 | T19: ='Working Capital Schedule'!T15 -> 3777.0468
B20: Short Term Borrowings | C20: 2906.9 | D20: 2301.3 | E20: 2089.4 | F20: 1606 | G20: 874.5 | H20: 340.8 | I20: 0.8 | J20: 25 | K20: 0 | L20: 6 | M20: =L20 -> 6 | N20: =M20 -> 6 | O20: =N20 -> 6 | P20: =O20 -> 6 | Q20: =P20 -> 6 | R20: =Q20 -> 6 | S20: =R20 -> 6 | T20: =S20 -> 6
B21: ST Provisions | C21: 319.4 | D21: 361.9 | E21: 399.2 | F21: 462.1 | G21: 583.4 | H21: 502.9 | I21: 385.4 | J21: 383 | K21: 391 | L21: 541 | M21: =Assumptions!E23*PL!M5 -> 597.91732 | N21: =Assumptions!F23*PL!N5 -> 651.72988 | O21: =Assumptions!G23*PL!O5 -> 703.86827 | P21: =Assumptions!H23*PL!P5 -> 753.13905 | Q21: =Assumptions!I23*PL!Q5 -> 802.09309 | R21: =Assumptions!J23*PL!R5 -> 854.22914 | S21: =Assumptions!K23*PL!S5 -> 909.75403 | T21: =Assumptions!L23*PL!T5 -> 968.88804
B22: Other Current Liabilities | C22: 1776.1 | D22: 1649.1 | E22: 1317.4 | F22: 1637 | G22: 1356 | H22: 1218.7 | I22: 1365.5 | J22: 1452.6 | K22: 1962 | L22: 2161 | M22: =Assumptions!E24*PL!M5 -> 2174.2448 | N22: =Assumptions!F24*PL!N5 -> 2369.9268 | O22: =Assumptions!G24*PL!O5 -> 2559.521 | P22: =Assumptions!H24*PL!P5 -> 2738.6874 | Q22: =Assumptions!I24*PL!Q5 -> 2916.7021 | R22: =Assumptions!J24*PL!R5 -> 3106.2878 | S22: =Assumptions!K24*PL!S5 -> 3308.1965 | T22: =Assumptions!L24*PL!T5 -> 3523.2292
B23: Total Current Liabilities | C23: =SUM(C19:C22) -> 6227.1 | D23: =SUM(D19:D22) -> 5767.4 | E23: =SUM(E19:E22) -> 5214.3 | F23: =SUM(F19:F22) -> 4904.5 | G23: =SUM(G19:G22) -> 4231.1 | H23: =SUM(H19:H22) -> 3644.5 | I23: =SUM(I19:I22) -> 3534.2 | J23: =SUM(J19:J22) -> 3814.6 | ... T23: =SUM(T19:T22) -> 8275.1641
A25: x | B25: Total Equity & Liabilities | C25: =C10+C16+C23 -> 8895.9 | D25: =D10+D16+D23 -> 8956.3 | E25: =E10+E16+E23 -> 9108.9 | F25: =F10+F16+F23 -> 8851.3 | G25: =G10+G16+G23 -> 8537 | H25: =H10+H16+H23 -> 8911.3 | I25: =I10+I16+I23 -> 9761.5 | J25: =J10+J16+J23 -> 11249 | ... T25: =T10+T16+T23 -> 25469.6
B27: Assets
B28: Non-Current Assets
B29: Fixed Assets
B30: Property Plant & Equip | C30: 1455.4 | D30: 1418.2 | E30: 1371.4 | F30: 1353.8 | G30: 1324.7 | H30: 1215.2 | I30: 978.3 | J30: 844 | K30: 850 | L30: 1215 | M30: ='Working Schedules'!H67 -> 1261.5435 | N30: ='Working Schedules'!I67 -> 1312.2487 | O30: ='Working Schedules'!J67 -> 1365.5459 | P30: ='Working Schedules'!K67 -> 1419.5431 | Q30: ='Working Schedules'!L67 -> 1473.1658 | R30: ='Working Schedules'!M67 -> 1526.3897 | S30: ='Working Schedules'!N67 -> 1579.189 | T30: ='Working Schedules'!O67 -> 1631.5359
B31: Capital Work in Progress | C31: 199.3 | D31: 101.8 | E31: 101.9 | F31: 104.1 | G31: 88.3 | H31: 87.7 | I31: 66.8 | J31: 37 | K31: 72 | L31: 77 | M31: ='Working Schedules'!H44 -> 77 | N31: ='Working Schedules'!I44 -> 77 | O31: ='Working Schedules'!J44 -> 77 | P31: ='Working Schedules'!K44 -> 77 | Q31: ='Working Schedules'!L44 -> 77 | R31: ='Working Schedules'!M44 -> 77 | S31: ='Working Schedules'!N44 -> 77 | T31: ='Working Schedules'!O44 -> 77
B32: ROU Assets | F32: 197.5 | G32: 164.4 | H32: 260.6 | I32: 172.6 | J32: 226.6 | K32: 456.6 | L32: 500.49 | M32: ='Working Schedules'!H55 -> 671.22666 | N32: ='Working Schedules'!I55 -> 746.84386 | O32: ='Working Schedules'!J55 -> 821.93472 | P32: ='Working Schedules'!K55 -> 895.4384 | Q32: ='Working Schedules'!L55 -> 967.69644 | R32: ='Working Schedules'!M55 -> 1040.4349 | S32: ='Working Schedules'!N55 -> 1114.9499 | T32: ='Working Schedules'!O55 -> 1192.2423
B33: Intangible Assets | C33: 393.2 | D33: 383.8 | E33: 373.7 | F33: 383.6 | G33: 375.5 | H33: 358 | I33: 356.7 | J33: 349 | K33: 329 | L33: 76 | M33: ='Working Schedules'!H81 -> 95.48503 | N33: ='Working Schedules'!I81 -> 100.04951 | O33: ='Working Schedules'!J81 -> 105.20647 | P33: ='Working Schedules'!K81 -> 110.84335 | Q33: ='Working Schedules'!L81 -> 116.90814 | R33: ='Working Schedules'!M81 -> 123.42867 | S33: ='Working Schedules'!N81 -> 130.43455 | T33: ='Working Schedules'!O81 -> 137.95735
B34: Goodwill | C34: 68 | D34: 36.1 | E34: 49.3 | F34: 21 | G34: 21 | H34: 21 | I34: 1 | J34: 1 | K34: 1 | L34: 55 | M34: =L34 -> 55 | N34: =M34 -> 55 | O34: =N34 -> 55 | P34: =O34 -> 55 | Q34: =P34 -> 55 | R34: =Q34 -> 55 | S34: =R34 -> 55 | T34: =S34 -> 55
B35: Total Fixed Assets | C35: =SUM(C30:C34) -> 2115.9 | D35: =SUM(D30:D34) -> 1939.9 | E35: =SUM(E30:E34) -> 1896.3 | F35: =SUM(F30:F34) -> 2060 | G35: =SUM(G30:G34) -> 1973.9 | H35: =SUM(H30:H34) -> 1942.5 | I35: =SUM(I30:I34) -> 1575.4 | J35: =SUM(J30:J34) -> 1457.6 | ... T35: =SUM(T30:T34) -> 3093.7356
B36: Other Non Current Assets | C36: 1030.9 | D36: 1280.2 | E36: 1948.8 | F36: 1921 | G36: 1760.1 | H36: 1805.4 | I36: 1951.5 | J36: 2414.4 | K36: 2337.4 | L36: 1982.51 | M36: =M25-M35-M44 -> 1872.526 | N36: =N25-N35-N44 -> 1872.526 | O36: =O25-O35-O44 -> 1872.526 | P36: =P25-P35-P44 -> 1872.526 | Q36: =Q25-Q35-Q44 -> 1872.526 | R36: =R25-R35-R44 -> 1872.526 | S36: =S25-S35-S44 -> 1872.526 | T36: =T25-T35-T44 -> 1872.526
B37: Total Non Current Assets | C37: =SUM(C35:C36) -> 3146.8 | D37: =SUM(D35:D36) -> 3220.1 | E37: =SUM(E35:E36) -> 3845.1 | F37: =SUM(F35:F36) -> 3981 | G37: =SUM(G35:G36) -> 3734 | H37: =SUM(H35:H36) -> 3747.9 | I37: =SUM(I35:I36) -> 3526.9 | J37: =SUM(J35:J36) -> 3872 | ... T37: =SUM(T35:T36) -> 4966.2616
B39: Current Assets
B40: Accounts Receivables | C40: 2953.4 | D40: 2711.2 | E40: 2542.5 | F40: 2283.5 | G40: 2187.2 | H40: 2373.6 | I40: 2434 | J40: 3056 | K40: 3410 | L40: 3609 | M40: ='Working Capital Schedule'!M9 -> 3613.6625 | N40: ='Working Capital Schedule'!N9 -> 4259.0396 | O40: ='Working Capital Schedule'!O9 -> 4243.4787 | P40: ='Working Capital Schedule'!P9 -> 4854.2159 | Q40: ='Working Capital Schedule'!Q9 -> 4834.8288 | R40: ='Working Capital Schedule'!R9 -> 5484.0038 | S40: ='Working Capital Schedule'!S9 -> 5505.553 | T40: ='Working Capital Schedule'!T9 -> 6198.325
B41: Inventories | C41: 1927.6 | D41: 1919.7 | E41: 1934.3 | F41: 1927.5 | G41: 2051.9 | H41: 2156.7 | I41: 2230 | J41: 2063 | K41: 2305 | L41: 2668 | M41: ='Working Capital Schedule'!M12 -> 2810.4268 | N41: ='Working Capital Schedule'!N12 -> 3106.2741 | O41: ='Working Capital Schedule'!O12 -> 3224.5958 | P41: ='Working Capital Schedule'!P12 -> 3486.1263 | Q41: ='Working Capital Schedule'!Q12 -> 3660.7928 | R41: ='Working Capital Schedule'!R12 -> 3950.6761 | S41: ='Working Capital Schedule'!S12 -> 4155.5382 | T41: ='Working Capital Schedule'!T12 -> 4477.58
B42: Other Current Assets | C42: 780.8 | D42: 849.2 | E42: 504.1 | F42: 585.8 | G42: 480 | H42: 350.7 | I42: 431.5 | J42: 390 | K42: 584 | L42: 1152 | M42: =L42*(1+Assumptions!E27) -> 1215.36 | N42: =M42*(1+Assumptions!F27) -> 1282.2048 | O42: =N42*(1+Assumptions!G27) -> 1352.7261 | P42: =O42*(1+Assumptions!H27) -> 1427.126 | Q42: =P42*(1+Assumptions!I27) -> 1505.6179 | R42: =Q42*(1+Assumptions!J27) -> 1588.4269 | S42: =R42*(1+Assumptions!K27) -> 1675.7904 | T42: =S42*(1+Assumptions!L27) -> 1767.9589
B43: Cash Balance(Incl. Bank and Current Investments) | C43: 87.3 | D43: 256.1 | E43: 282.9 | F43: 73.5 | G43: 83.9 | H43: 282.4 | I43: 1139.1 | J43: 1868 | K43: 2903 | L43: 3134 | M43: =CS!M22 -> 3031.0785 | N43: =CS!N22 -> 3809.9448 | O43: =CS!O22 -> 4055.3746 | P43: =CS!P22 -> 5013.4263 | Q43: =CS!Q22 -> 5374.4459 | R43: =CS!R22 -> 6423.0317 | S43: =CS!S22 -> 6894.5425 | T43: =CS!T22 -> 8059.4748
B44: Total Current Assets | C44: =SUM(C40:C43) -> 5749.1 | D44: =SUM(D40:D43) -> 5736.2 | E44: =SUM(E40:E43) -> 5263.8 | F44: =SUM(F40:F43) -> 4870.3 | G44: =SUM(G40:G43) -> 4803 | H44: =SUM(H40:H43) -> 5163.4 | I44: =SUM(I40:I43) -> 6234.6 | J44: =SUM(J40:J43) -> 7377 | ... T44: =SUM(T40:T43) -> 20503.339
B46: Total Assets | C46: =C37+C44 -> 8895.9 | D46: =D37+D44 -> 8956.3 | E46: =E37+E44 -> 9108.9 | F46: =F37+F44 -> 8851.3 | G46: =G37+G44 -> 8537 | H46: =H37+H44 -> 8911.3 | I46: =I37+I44 -> 9761.5 | J46: =J37+J44 -> 11249 | ... T46: =T37+T44 -> 25469.6
B49: Test | C49: =C46-C25 -> 0 | D49: =D46-D25 -> 0 | E49: =E46-E25 -> 0 | F49: =F46-F25 -> 0 | G49: =G46-G25 -> 0 | H49: =H46-H25 -> 0 | I49: =I46-I25 -> 0 | J49: =J46-J25 -> 0 | ... T49: =T46-T25 -> 0

Sheet CS
B2: Cash Flow Statement | T2: =BS!T2 -> CURRENTLY RUNNING: BASE SCENARIO
B4: Particulars | C4: 2017 | D4: =C4+1 -> 2018 | E4: =D4+1 -> 2019 | F4: =E4+1 -> 2020 | G4: =F4+1 -> 2021 | H4: =G4+1 -> 2022 | I4: =H4+1 -> 2023 | J4: =I4+1 -> 2024 | K4: =J4+1 -> 2025 | ... T4: =S4+1 -> 2034
A6: x | B6: Net Profit Aafter Tax (PAT) | C6: =PL!C22 -> 93 | D6: =PL!D22 -> 651.9 | E6: =PL!E22 -> 683.6 | F6: =PL!F22 -> 620.6 | G6: =PL!G22 -> 362.1 | H6: =PL!H22 -> 810.6 | I6: =PL!I22 -> 1125.8 | J6: =PL!J22 -> 1408 | ... T6: =PL!T22 -> 3013.605
B7: D&A | C7: =-PL!C13 -> 188.6 | D7: =-PL!D13 -> 192.3 | E7: =-PL!E13 -> 214.7 | F7: =-PL!F13 -> 285.3 | G7: =-PL!G13 -> 299.1 | H7: =-PL!H13 -> 303.8 | I7: =-PL!I13 -> 283 | J7: =-PL!J13 -> 275 | ... T7: =-PL!T13 -> 677.58456
B8: +/- in other non cash items | C8: 227.2 | D8: 358.9 | E8: 103.9 | F8: 3 | G8: 1752.2 | H8: 611.5 | I8: -468.8 | J8: -431.9 | K8: 94.6 | L8: -37 | M8: =-PL!M18-PL!M17 -> -107.87266 | N8: =-PL!N18-PL!N17 -> -88.182942 | O8: =-PL!O18-PL!O17 -> -124.50684 | P8: =-PL!P18-PL!P17 -> -125.01771 | Q8: =-PL!Q18-PL!Q17 -> -170.84808 | R8: =-PL!R18-PL!R17 -> -176.88559 | S8: =-PL!S18-PL!S17 -> -226.57088 | T8: =-PL!T18-PL!T17 -> -237.64062
B9: +/- change in NWC | C9: 138 | D9: =-'Working Capital Schedule'!D21 -> -278 | E9: =-'Working Capital Schedule'!E21 -> -53.9 | F9: =-'Working Capital Schedule'!F21 -> -125.7 | G9: =-'Working Capital Schedule'!G21 -> -595.7 | H9: =-'Working Capital Schedule'!H21 -> -748.5 | I9: =-'Working Capital Schedule'!I21 -> -324.8 | J9: =-'Working Capital Schedule'!J21 -> -133.1 | K9: =-'Working Capital Schedule'!K21 -> -12.6 | ... T9: =-'Working Capital Schedule'!T21 -> 70.579636
A10: x | B10: Cash flow from Operating Activities | C10: =SUM(C6:C9) -> 646.8 | D10: =SUM(D6:D9) -> 925.1 | E10: =SUM(E6:E9) -> 948.3 | F10: =SUM(F6:F9) -> 783.2 | G10: =SUM(G6:G9) -> 1817.7 | H10: =SUM(H6:H9) -> 977.4 | I10: =SUM(I6:I9) -> 615.2 | J10: =SUM(J6:J9) -> 1118 | ... T10: =SUM(T6:T9) -> 3524.1286
B11: Interest Received | C11: 19.7 | D11: 4.2 | E11: 6.4 | F11: 6.2 | G11: 11.1 | H11: 6.4 | I11: 20.4 | J11: 42 | K11: 36 | L11: 67 | M11: =M21*Assumptions!E9 -> 203.71 | N11: =N21*Assumptions!F9 -> 197.0201 | O11: =O21*Assumptions!G9 -> 247.64641 | P11: =P21*Assumptions!H9 -> 263.59935 | Q11: =Q21*Assumptions!I9 -> 325.87271 | R11: =R21*Assumptions!J9 -> 349.33898 | S11: =S21*Assumptions!K9 -> 417.49706 | T11: =T21*Assumptions!L9 -> 448.14526
B12: Capex | C12: -311 | D12: -184.3 | E12: -173 | F12: -211.6 | G12: -158.9 | H12: -134 | I12: -136.6 | J12: -98 | K12: -162 | L12: -181 | M12: =-'Working Schedules'!H42 -> -203.83545 | N12: =-'Working Schedules'!I42 -> -222.18064 | O12: =-'Working Schedules'!J42 -> -239.95509 | P12: =-'Working Schedules'!K42 -> -256.75195 | Q12: =-'Working Schedules'!L42 -> -273.44082 | R12: =-'Working Schedules'!M42 -> -291.21448 | S12: =-'Working Schedules'!N42 -> -310.14342 | T12: =-'Working Schedules'!O42 -> -330.30274
B13: Others | C13: 64 | D13: 284 | E13: 128 | F13: 12 | G13: 35 | H13: -176 | I13: 12 | J13: -262 | K13: -227 | L13: 75 | M13: 0 | N13: 0 | O13: 0 | P13: 0 | Q13: 0 | R13: 0 | S13: 0 | T13: 0
B14: Cash flow from investing activities | C14: =SUM(C11:C13) -> -227.3 | D14: =SUM(D11:D13) -> 103.9 | E14: =SUM(E11:E13) -> -38.6 | F14: =SUM(F11:F13) -> -193.4 | G14: =SUM(G11:G13) -> -112.8 | H14: =SUM(H11:H13) -> -303.6 | I14: =SUM(I11:I13) -> -104.2 | J14: =SUM(J11:J13) -> -318 | ... T14: =SUM(T11:T13) -> 117.84252
B15: Repayment Lease Liabilities | C15: -8.6 | D15: 0 | E15: 0 | F15: -64.5 | G15: -80.7 | H15: -100.2 | I15: -124 | J15: -126 | K15: -137 | L15: -144 | M15: ='Working Schedules'!H9 -> -154.08 | N15: ='Working Schedules'!I9 -> -164.8656 | O15: ='Working Schedules'!J9 -> -176.40619 | P15: ='Working Schedules'!K9 -> -188.75463 | Q15: ='Working Schedules'!L9 -> -201.96745 | R15: ='Working Schedules'!M9 -> -216.10517 | S15: ='Working Schedules'!N9 -> -231.23253 | T15: ='Working Schedules'!O9 -> -247.41881
B16: Interest Paid | C16: -375.2 | D16: -252.8 | E16: -229.3 | F16: -181.1 | G16: -142 | H16: -50.1 | I16: -36.3 | J16: -21 | K16: -40 | L16: -37 | M16: =PL!M17 -> -95.837343 | N16: =PL!N17 -> -108.83716 | O16: =PL!O17 -> -123.13957 | P16: =PL!P17 -> -138.58164 | Q16: =PL!Q17 -> -155.02463 | R16: =PL!R17 -> -172.45339 | S16: =PL!S17 -> -190.92618 | T16: =PL!T17 -> -210.50465
B17: Dividend Paid | C17: 0 | D17: 0 | E17: 0 | F17: 0 | G17: 0 | H17: 0 | I17: 0 | J17: -284 | K17: -355 | L17: -1263 | M17: =-Assumptions!E11*PL!M22 -> -1144.7874 | N17: =-Assumptions!F11*PL!N22 -> -1267.138 | O17: =-Assumptions!G11*PL!O22 -> -1419.4835 | P17: =-Assumptions!H11*PL!P22 -> -1552.8283 | Q17: =-Assumptions!I11*PL!Q22 -> -1667.7608 | R17: =-Assumptions!J11*PL!R22 -> -1769.5792 | S17: =-Assumptions!K11*PL!S22 -> -1900.3871 | T17: =-Assumptions!L11*PL!T22 -> -2019.1154
B18: Others | C18: -86.4 | D18: -607.4 | E18: -653.6 | F18: -553.6 | G18: -1471.8 | H18: -324.9 | I18: 505.9 | J18: 359.9 | K18: -27 | L18: 255 | M18: 0 | N18: 0 | O18: 0 | P18: 0 | Q18: 0 | R18: 0 | S18: 0 | T18: 0
B19: Cash flow from Financing activities | C19: =SUM(C15:C18) -> -470.2 | D19: =SUM(D15:D18) -> -860.2 | E19: =SUM(E15:E18) -> -882.9 | F19: =SUM(F15:F18) -> -799.2 | G19: =SUM(G15:G18) -> -1694.5 | H19: =SUM(H15:H18) -> -475.2 | I19: =SUM(I15:I18) -> 345.6 | J19: =SUM(J15:J18) -> -71.1 | ... T19: =SUM(T15:T18) -> -2477.0388
A20: x | B20: Net change in Cash | C20: =C10+C14+C19 -> -50.7 | D20: =D10+D14+D19 -> 168.8 | E20: =E10+E14+E19 -> 26.8 | F20: =F10+F14+F19 -> -209.4 | G20: =G10+G14+G19 -> 10.4 | H20: =H10+H14+H19 -> 198.6 | I20: =I10+I14+I19 -> 856.6 | J20: =J10+J14+J19 -> 728.9 | ... T20: =T10+T14+T19 -> 1164.9323
B21: Opening Cash Balance | C21: 138 | D21: =C22 -> 87.3 | E21: =D22 -> 256.1 | F21: =E22 -> 282.9 | G21: =F22 -> 73.5 | H21: =G22 -> 83.9 | I21: =H22 -> 282.5 | J21: =I22 -> 1139.1 | K21: =J22 -> 1868 | ... T21: =S22 -> 6894.5425
A22: x | B22: Closing Cash Balance | C22: =C20+C21 -> 87.3 | D22: =D20+D21 -> 256.1 | E22: =E20+E21 -> 282.9 | F22: =F20+F21 -> 73.5 | G22: =G20+G21 -> 83.9 | H22: =H20+H21 -> 282.5 | I22: =I20+I21 -> 1139.1 | J22: =J20+J21 -> 1868 | ... T22: =T20+T21 -> 8059.4748

Sheet Assumptions
B2: Assumptions
B4: Particulars | E4: 2027 | F4: =E4+1 -> 2028 | G4: =F4+1 -> 2029 | H4: =G4+1 -> 2030 | I4: =H4+1 -> 2031 | J4: =I4+1 -> 2032 | K4: =J4+1 -> 2033 | L4: =K4+1 -> 2034
B6: Cost of Goods Sold(COGS)
B7: Employee Cost as % of Sales | E7: 0.06254555 | F7: 0.06254555 | G7: 0.06254555 | H7: 0.06254555 | I7: 0.06254555 | J7: 0.06254555 | K7: 0.06254555 | L7: 0.06254555 | N7: Median of Last 10 Years
B8: Selling and admin as % of Sales | E8: 0.205 | F8: 0.205 | G8: 0.205 | H8: 0.205 | I8: 0.205 | J8: 0.205 | K8: 0.205 | L8: 0.205 | N8: Median of Last 10 Years
B9: Interest Income | E9: 0.065 | F9: 0.065 | G9: 0.065 | H9: 0.065 | I9: 0.065 | J9: 0.065 | K9: 0.065 | L9: 0.065 | N9: Market Yield on MFs, Depoists, investments
B10: Tax Rate | E10: 0.25 | F10: 0.25 | G10: 0.25 | H10: 0.25 | I10: 0.25 | J10: 0.25 | K10: 0.25 | L10: 0.25
B11: Dividend Payout Ratio | E11: 0.67 | F11: 0.67 | G11: 0.67 | H11: 0.67 | I11: 0.67 | J11: 0.67 | K11: 0.67 | L11: 0.67 | N11: Constant FY 26
B12: Total capex as % of NSV | E12: 0.015 | F12: 0.015 | G12: 0.015 | H12: 0.015 | I12: 0.015 | J12: 0.015 | K12: 0.015 | L12: 0.015 | N12: Median of last 5 years
B13: PPE Capex as % of NSV | E13: 0.014 | F13: 0.014 | G13: 0.014 | H13: 0.014 | I13: 0.014 | J13: 0.014 | K13: 0.014 | L13: 0.014 | N13: Median of last 4 years
B14: Amortisation as % of Opening Balance | E14: 0.04 | F14: 0.04 | G14: 0.04 | H14: 0.04 | I14: 0.04 | J14: 0.04 | K14: 0.04 | L14: 0.04 | N14: Median of last 5 years
B15: ROU additions as % of NSV | E15: 0.022 | F15: 0.022 | G15: 0.022 | H15: 0.022 | I15: 0.022 | J15: 0.022 | K15: 0.022 | L15: 0.022 | N15: Median of last 4 years
B16: ROU amortisation as % of (opening + 1/2 additions) | E16: 0.3 | F16: 0.3 | G16: 0.3 | H16: 0.3 | I16: 0.3 | J16: 0.3 | K16: 0.3 | L16: 0.3
B17: Depreciation useful life | E17: 16 | F17: 16 | G17: 16 | H17: 16 | I17: 16 | J17: 16 | K17: 16 | L17: 16 | N17: 1/6.2%(Average of last 5 years)
B18: Principal Reyament | E18: 0.07 | F18: 0.07 | G18: 0.07 | H18: 0.07 | I18: 0.07 | J18: 0.07 | K18: 0.07 | L18: 0.07 | N18: Historical median of last 4 years
B19: Interest rate on lease liabilities | E19: 0.085 | F19: 0.085 | G19: 0.085 | H19: 0.085 | I19: 0.085 | J19: 0.085 | K19: 0.085 | L19: 0.085 | N19: Historical median intt rate of last 4 years
B20: Interest rate on borrowings | E20: 0 | F20: 0 | G20: 0 | H20: 0 | I20: 0 | J20: 0 | K20: 0 | L20: 0
B21: Interest others | E21: 55 | F21: 55 | G21: 55 | H21: 55 | I21: 55 | J21: 55 | K21: 55 | L21: 55 | N21: Median of last 5 years
B22: Trade Payables | E22: 104 | F22: 104 | G22: 104 | H22: 104 | I22: 104 | J22: 104 | K22: 104 | L22: 104 | N22: Median of last 3 Years
B23: ST Provisions as % of Sales | E23: 0.044 | F23: 0.044 | G23: 0.044 | H23: 0.044 | I23: 0.044 | J23: 0.044 | K23: 0.044 | L23: 0.044 | N23: Average of Last 9 years
B24: Other Current Liabilities as % of Sales | E24: 0.16 | F24: 0.16 | G24: 0.16 | H24: 0.16 | I24: 0.16 | J24: 0.16 | K24: 0.16 | L24: 0.16 | N24: Median of last 10years
B25: Accounts Receivables days | E25: 97 | F25: 97 | G25: 97 | H25: 97 | I25: 97 | J25: 97 | K25: 97 | L25: 97 | N25: Historical Median of Last 10 Years
B26: Inventory Days | E26: 135 | F26: 135 | G26: 135 | H26: 135 | I26: 135 | J26: 135 | K26: 135 | L26: 135 | N26: Historical Median of Last 10 Years
B27: Other Current assets as % of Sales | E27: 0.055 | F27: 0.055 | G27: 0.055 | H27: 0.055 | I27: 0.055 | J27: 0.055 | K27: 0.055 | L27: 0.055 | N27: Historical Median of Last 10 Years

Sheet Working Capital Schedule
B2: Working Capital Schedule | T2: =PL!T2 -> CURRENTLY RUNNING: BASE SCENARIO
B4: Particulars | C4: 2017 | D4: =C4+1 -> 2018 | E4: =D4+1 -> 2019 | F4: =E4+1 -> 2020 | G4: =F4+1 -> 2021 | H4: =G4+1 -> 2022 | I4: =H4+1 -> 2023 | J4: =I4+1 -> 2024 | K4: =J4+1 -> 2025 | ... T4: =S4+1 -> 2034
B6: Revenue | C6: =PL!C5 -> 8817.5 | D6: =PL!D5 -> 8590.6 | E6: =PL!E5 -> 9340.8 | F6: =PL!F5 -> 9325.4 | G6: =PL!G5 -> 8131.3 | H6: =PL!H5 -> 9712.4 | I6: =PL!I5 -> 10612 | J6: =PL!J5 -> 11321 | ... T6: =PL!T5 -> 22020.183
B7: COGS | C7: =-PL!C6 -> 5151.3 | D7: =-PL!D6 -> 4557.3 | E7: =-PL!E6 -> 4966.4 | F7: =-PL!F6 -> 5370 | G7: =-PL!G6 -> 4807.5 | H7: =-PL!H6 -> 5680.9 | I7: =-PL!I6 -> 6503 | J7: =-PL!J6 -> 6542 | ... T7: =-PL!T6 -> 11670.697
B9: Accounts Receivables | C9: =BS!C40 -> 2953.4 | D9: =BS!D40 -> 2711.2 | E9: =BS!E40 -> 2542.5 | F9: =BS!F40 -> 2283.5 | G9: =BS!G40 -> 2187.2 | H9: =BS!H40 -> 2373.6 | I9: =BS!I40 -> 2434 | J9: =BS!J40 -> 3056 | ... L9: =BS!L40 -> 3609 | M9: =(2*(M6*Assumptions!E25)/365)-L9 -> 3613.6625 | N9: =(2*(N6*Assumptions!F25)/365)-M9 -> 4259.0396 | O9: =(2*(O6*Assumptions!G25)/365)-N9 -> 4243.4787 | P9: =(2*(P6*Assumptions!H25)/365)-O9 -> 4854.2159 | Q9: =(2*(Q6*Assumptions!I25)/365)-P9 -> 4834.8288 | R9: =(2*(R6*Assumptions!J25)/365)-Q9 -> 5484.0038 | S9: =(2*(S6*Assumptions!K25)/365)-R9 -> 5505.553 | T9: =(2*(T6*Assumptions!L25)/365)-S9 -> 6198.325
B10: Receivables Days | D10: =AVERAGE(C9:D9)/D6*365 -> 120.33962 | E10: =AVERAGE(D9:E9)/E6*365 -> 102.64648 | F10: =AVERAGE(E9:F9)/F6*365 -> 94.445815 | G10: =AVERAGE(F9:G9)/G6*365 -> 100.341 | H10: =AVERAGE(G9:H9)/H6*365 -> 85.699312 | I10: =AVERAGE(H9:I9)/I6*365 -> 82.67876 | J10: =AVERAGE(I9:J9)/J6*365 -> 88.501457 | K10: =AVERAGE(J9:K9)/K6*365 -> 97.774878 | ... T10: =AVERAGE(S9:T9)/T6*365 -> 97
B12: Inventory | C12: =BS!C41 -> 1927.6 | D12: =BS!D41 -> 1919.7 | E12: =BS!E41 -> 1934.3 | F12: =BS!F41 -> 1927.5 | G12: =BS!G41 -> 2051.9 | H12: =BS!H41 -> 2156.7 | I12: =BS!I41 -> 2230 | J12: =BS!J41 -> 2063 | ... L12: =BS!L41 -> 2668 | M12: =(2*(M7*Assumptions!E26)/365)-L12 -> 2810.4268 | N12: =(2*(N7*Assumptions!F26)/365)-M12 -> 3106.2741 | O12: =(2*(O7*Assumptions!G26)/365)-N12 -> 3224.5958 | P12: =(2*(P7*Assumptions!H26)/365)-O12 -> 3486.1263 | Q12: =(2*(Q7*Assumptions!I26)/365)-P12 -> 3660.7928 | R12: =(2*(R7*Assumptions!J26)/365)-Q12 -> 3950.6761 | S12: =(2*(S7*Assumptions!K26)/365)-R12 -> 4155.5382 | T12: =(2*(T7*Assumptions!L26)/365)-S12 -> 4477.58
B13: Inventory Days | D13: =AVERAGE(C12:D12)/D7*365 -> 154.06759 | E13: =AVERAGE(D12:E12)/E7*365 -> 141.6227 | F13: =AVERAGE(E12:F12)/F7*365 -> 131.24367 | G13: =AVERAGE(F12:G12)/G7*365 -> 151.06407 | H13: =AVERAGE(G12:H12)/H7*365 -> 135.20208 | I13: =AVERAGE(H12:I12)/I7*365 -> 123.10822 | J13: =AVERAGE(I12:J12)/J7*365 -> 119.76039 | K13: =AVERAGE(J12:K12)/K7*365 -> 116.20408 | ... T13: =AVERAGE(S12:T12)/T7*365 -> 135
B15: Trade Payables | C15: =BS!C19 -> 1224.7 | D15: =BS!D19 -> 1455.1 | E15: =BS!E19 -> 1408.3 | F15: =BS!F19 -> 1199.4 | G15: =BS!G19 -> 1417.2 | H15: =BS!H19 -> 1582.1 | I15: =BS!I19 -> 1782.5 | J15: =BS!J19 -> 1954 | ... L15: =BS!L19 -> 2383 | M15: =(2*(M7*Assumptions!E22)/365)-L15 -> 1837.4176 | N15: =(2*(N7*Assumptions!F22)/365)-M15 -> 2720.6334 | O15: =(2*(O7*Assumptions!G22)/365)-N15 -> 2156.4812 | P15: =(2*(P7*Assumptions!H22)/365)-O15 -> 3013.2603 | Q15: =(2*(Q7*Assumptions!I22)/365)-P15 -> 2492.5144 | R15: =(2*(R7*Assumptions!J22)/365)-Q15 -> 3371.1356 | S15: =(2*(S7*Assumptions!K22)/365)-R15 -> 2873.6517 | T15: =(2*(T7*Assumptions!L22)/365)-S15 -> 3777.0468
B16: Payable Days | D16: =AVERAGE(C15:D15)/D7*365 -> 107.31431 | E16: =AVERAGE(D15:E15)/E7*365 -> 105.22119 | F16: =AVERAGE(E15:F15)/F7*365 -> 88.622952 | G16: =AVERAGE(F15:G15)/G7*365 -> 99.330109 | H16: =AVERAGE(G15:H15)/H7*365 -> 96.353087 | I16: =AVERAGE(H15:I15)/I7*365 -> 94.424035 | J16: =AVERAGE(I15:J15)/J7*365 -> 104.2359 | K16: =AVERAGE(J15:K15)/K7*365 -> 111.54847 | ... T16: =AVERAGE(S15:T15)/T7*365 -> 104
B18: Total Current Assets | C18: =BS!C40+BS!C41+BS!C42 -> 5661.8 | D18: =BS!D40+BS!D41+BS!D42 -> 5480.1 | E18: =BS!E40+BS!E41+BS!E42 -> 4980.9 | F18: =BS!F40+BS!F41+BS!F42 -> 4796.8 | G18: =BS!G40+BS!G41+BS!G42 -> 4719.1 | H18: =BS!H40+BS!H41+BS!H42 -> 4881 | I18: =BS!I40+BS!I41+BS!I42 -> 5095.5 | J18: =BS!J40+BS!J41+BS!J42 -> 5509 | ... T18: =BS!T40+BS!T41+BS!T42 -> 12443.864
B19: Total Current Liabilities | C19: =BS!C23 -> 6227.1 | D19: =BS!D23 -> 5767.4 | E19: =BS!E23 -> 5214.3 | F19: =BS!F23 -> 4904.5 | G19: =BS!G23 -> 4231.1 | H19: =BS!H23 -> 3644.5 | I19: =BS!I23 -> 3534.2 | J19: =BS!J23 -> 3814.6 | ... T19: =BS!T23 -> 8275.1641
B20: WC | C20: =C18-C19 -> -565.3 | D20: =D18-D19 -> -287.3 | E20: =E18-E19 -> -233.4 | F20: =F18-F19 -> -107.7 | G20: =G18-G19 -> 488 | H20: =H18-H19 -> 1236.5 | I20: =I18-I19 -> 1561.3 | J20: =J18-J19 -> 1694.4 | ... T20: =T18-T19 -> 4168.6998
B21: Change In NWC | D21: =D20-C20 -> 278 | E21: =E20-D20 -> 53.9 | F21: =F20-E20 -> 125.7 | G21: =G20-F20 -> 595.7 | H21: =H20-G20 -> 748.5 | I21: =I20-H20 -> 324.8 | J21: =J20-I20 -> 133.1 | K21: =K20-J20 -> 12.6 | ... T21: =T20-S20 -> -70.579636

Sheet Working Schedules
B2: Working Schedules | O2: =PL!T2 -> CURRENTLY RUNNING: BASE SCENARIO
B4: Debt Schedule - Lease Liabilities
B5: Particulars | C5: 2022 | D5: =C5+1 -> 2023 | E5: =D5+1 -> 2024 | F5: =E5+1 -> 2025 | G5: =F5+1 -> 2026 | H5: =G5+1 -> 2027 | I5: =H5+1 -> 2028 | J5: =I5+1 -> 2029 | K5: =J5+1 -> 2030 | ... O5: =N5+1 -> 2034
B7: Opening Lease Liability | C7: =BS!G15 -> 157.8 | D7: =C10 -> 263.9 | E7: =D10 -> 182.4 | F7: =E10 -> 240.4 | G7: =F10 -> 480.4 | H7: =G10 -> 408 | I7: =H10 -> 552.87866 | J7: =I10 -> 713.878 | K7: =J10 -> 889.40594 | ... O7: =N10 -> 1710.9538
B8: Additions: New Leases | C8: 206.1 | D8: 42.5 | E8: =E52 -> 184 | F8: 377 | G8: 71.6 | H8: =H52 -> 298.95866 | I8: =I52 -> 325.86494 | J8: =J52 -> 351.93413 | K8: =K52 -> 376.56952 | L8: =L52 -> 401.04654 | M8: =M52 -> 427.11457 | N8: =N52 -> 454.87702 | O8: =O52 -> 484.44402
B9: Less: Principal Repayment | C9: -100 | D9: -124 | E9: -126 | F9: -137 | G9: -144 | H9: =(1+Assumptions!E18)*G9 -> -154.08 | I9: =(1+Assumptions!F18)*H9 -> -164.8656 | J9: =(1+Assumptions!G18)*I9 -> -176.40619 | K9: =(1+Assumptions!H18)*J9 -> -188.75463 | L9: =(1+Assumptions!I18)*K9 -> -201.96745 | M9: =(1+Assumptions!J18)*L9 -> -216.10517 | N9: =(1+Assumptions!K18)*M9 -> -231.23253 | O9: =(1+Assumptions!L18)*N9 -> -247.41881
B10: Closing Lease Liability | C10: =SUM(C7:C9) -> 263.9 | D10: =SUM(D7:D9) -> 182.4 | E10: =SUM(E7:E9) -> 240.4 | F10: =SUM(F7:F9) -> 480.4 | G10: =SUM(G7:G9) -> 408 | H10: =SUM(H7:H9) -> 552.87866 | I10: =SUM(I7:I9) -> 713.878 | J10: =SUM(J7:J9) -> 889.40594 | ... O10: =SUM(O7:O9) -> 1947.979
B11: Interest | C11: 11.9 | D11: 16 | E11: 21 | F11: 40 | G11: 37 | H11: =AVERAGE(H10,H7)*Assumptions!E19 -> 40.837343 | I11: =AVERAGE(I10,I7)*Assumptions!F19 -> 53.837158 | J11: =AVERAGE(J10,J7)*Assumptions!G19 -> 68.139568 | K11: =AVERAGE(K10,K7)*Assumptions!H19 -> 83.581638 | L11: =AVERAGE(L10,L7)*Assumptions!I19 -> 100.02463 | M11: =AVERAGE(M10,M7)*Assumptions!J19 -> 117.45339 | N11: =AVERAGE(N10,N7)*Assumptions!K19 -> 135.92618 | O11: =AVERAGE(O10,O7)*Assumptions!L19 -> 155.50465
B14: Debt Schedule - Working Capital loans/Others
B15: Particulars | C15: 2022 | D15: =C15+1 -> 2023 | E15: =D15+1 -> 2024 | F15: =E15+1 -> 2025 | G15: =F15+1 -> 2026 | H15: =G15+1 -> 2027 | I15: =H15+1 -> 2028 | J15: =I15+1 -> 2029 | K15: =J15+1 -> 2030 | ... O15: =N15+1 -> 2034
B17: Opening | C17: 876 | D17: =C19 -> 341 | E17: =D19 -> 0 | F17: =E19 -> 25 | G17: =F19 -> 0 | H17: =G19 -> 0 | I17: =H19 -> 0 | J17: =I19 -> 0 | K17: =J19 -> 0 | ... O17: =N19 -> 0
B18: (Repayment)/Net proceeds | C18: -535 | D18: -341 | E18: 25 | F18: -25 | G18: 0 | H18: 0 | I18: 0 | J18: 0 | K18: 0 | L18: 0 | M18: 0 | N18: 0 | O18: 0
B19: Closing | C19: =SUM(C17:C18) -> 341 | D19: =SUM(D17:D18) -> 0 | E19: =SUM(E17:E18) -> 25 | F19: =SUM(F17:F18) -> 0 | G19: =SUM(G17:G18) -> 0 | H19: =SUM(H17:H18) -> 0 | I19: =SUM(I17:I18) -> 0 | J19: =SUM(J17:J18) -> 0 | ... O19: =SUM(O17:O18) -> 0
B20: Interest | C20: 38 | D20: 20.3 | E20: 0 | F20: 0 | G20: 0 | H20: 0 | I20: 0 | J20: 0 | K20: 0 | L20: 0 | M20: 0 | N20: 0 | O20: 0
B22: Total Debt | C22: =C19+C10 -> 604.9 | D22: =D19+D10 -> 182.4 | E22: =E19+E10 -> 265.4 | F22: =F19+F10 -> 480.4 | G22: =G19+G10 -> 408 | H22: =H19+H10 -> 552.87866 | I22: =I19+I10 -> 713.878 | J22: =J19+J10 -> 889.40594 | ... O22: =O19+O10 -> 1947.979
B27: Finance cost Schedule
B28: Particulars | C28: 2022 | D28: =C28+1 -> 2023 | E28: =D28+1 -> 2024 | F28: =E28+1 -> 2025 | G28: =F28+1 -> 2026 | H28: =G28+1 -> 2027 | I28: =H28+1 -> 2028 | J28: =I28+1 -> 2029 | K28: =J28+1 -> 2030 | ... O28: =N28+1 -> 2034
B30: Interest on lease liabilities | C30: =C11 -> 11.9 | D30: =D11 -> 16 | E30: =E11 -> 21 | F30: =F11 -> 40 | G30: =G11 -> 37 | H30: =H11 -> 40.837343 | I30: =I11 -> 53.837158 | J30: =J11 -> 68.139568 | ... O30: =O11 -> 155.50465
B31: Interest on Borrowings | C31: =C20 -> 38 | D31: =D20 -> 20.3 | E31: =E20 -> 0 | F31: =F20 -> 0 | G31: =G20 -> 0 | H31: =H20 -> 0 | I31: =I20 -> 0 | J31: =J20 -> 0 | ... O31: =O20 -> 0
B32: Interest Others | C32: 38.1 | D32: 67.6 | E32: 55 | F32: 49 | G32: 121 | H32: =Assumptions!E21 -> 55 | I32: =Assumptions!F21 -> 55 | J32: =Assumptions!G21 -> 55 | K32: =Assumptions!H21 -> 55 | L32: =Assumptions!I21 -> 55 | M32: =Assumptions!J21 -> 55 | N32: =Assumptions!K21 -> 55 | O32: =Assumptions!L21 -> 55
B33: Total | C33: =SUM(C30:C32) -> 88 | D33: =SUM(D30:D32) -> 103.9 | E33: =SUM(E30:E32) -> 76 | F33: =SUM(F30:F32) -> 89 | G33: =SUM(G30:G32) -> 158 | H33: =SUM(H30:H32) -> 95.837343 | I33: =SUM(I30:I32) -> 108.83716 | J33: =SUM(J30:J32) -> 123.13957 | ... O33: =SUM(O30:O32) -> 210.50465
B37: CWIP Schedule
B38: Particulars | C38: 2022 | D38: =C38+1 -> 2023 | E38: =D38+1 -> 2024 | F38: =E38+1 -> 2025 | G38: =F38+1 -> 2026 | H38: =G38+1 -> 2027 | I38: =H38+1 -> 2028 | J38: =I38+1 -> 2029 | K38: =J38+1 -> 2030 | ... O38: =N38+1 -> 2034
B40: Revenue | C40: =PL!H5 -> 9712.4 | D40: =PL!I5 -> 10612 | E40: =PL!J5 -> 11321 | F40: =PL!K5 -> 12069 | G40: =PL!L5 -> 12467 | H40: =PL!M5 -> 13589.03 | I40: =PL!N5 -> 14812.043 | J40: =PL!O5 -> 15997.006 | ... O40: =PL!T5 -> 22020.183
B41: Opening | C41: 88.3 | D41: =C44 -> 87.7 | E41: =D44 -> 66.8 | F41: =E44 -> 36.8 | G41: =F44 -> 71.8 | H41: =G44 -> 77 | I41: =H44 -> 77 | J41: =I44 -> 77 | K41: =J44 -> 77 | ... O41: =N44 -> 77
B42: Additions(Capex) | C42: 123.4 | D42: 114.3 | E42: 96 | F42: 161 | G42: 181 | H42: =H40*Assumptions!E12 -> 203.83545 | I42: =I40*Assumptions!F12 -> 222.18064 | J42: =J40*Assumptions!G12 -> 239.95509 | K42: =K40*Assumptions!H12 -> 256.75195 | L42: =L40*Assumptions!I12 -> 273.44082 | M42: =M40*Assumptions!J12 -> 291.21448 | N42: =N40*Assumptions!K12 -> 310.14342 | O42: =O40*Assumptions!L12 -> 330.30274
B43: Capitalised | C43: -124 | D43: -135.2 | E43: -126 | F43: -126 | G43: -175.8 | H43: =-H42 -> -203.83545 | I43: =-I42 -> -222.18064 | J43: =-J42 -> -239.95509 | K43: =-K42 -> -256.75195 | L43: =-L42 -> -273.44082 | M43: =-M42 -> -291.21448 | N43: =-N42 -> -310.14342 | O43: =-O42 -> -330.30274
B44: Closing | C44: =SUM(C41:C43) -> 87.7 | D44: =SUM(D41:D43) -> 66.8 | E44: =SUM(E41:E43) -> 36.8 | F44: =SUM(F41:F43) -> 71.8 | G44: =SUM(G41:G43) -> 77 | H44: =SUM(H41:H43) -> 77 | I44: =SUM(I41:I43) -> 77 | J44: =SUM(J41:J43) -> 77 | ... O44: =SUM(O41:O43) -> 77
B48: Right of Use of Assets Schedule
B49: Particulars | C49: 2022 | D49: =C49+1 -> 2023 | E49: =D49+1 -> 2024 | F49: =E49+1 -> 2025 | G49: =F49+1 -> 2026 | H49: =G49+1 -> 2027 | I49: =H49+1 -> 2028 | J49: =I49+1 -> 2029 | K49: =J49+1 -> 2030 | ... O49: =N49+1 -> 2034
B51: Opening ROU assets | C51: 164.4 | D51: =C55 -> 260.6 | E51: =D55 -> 172.6 | F51: =E55 -> 226.6 | G51: =F55 -> 456.6 | H51: =G55 -> 595.874 | I51: =H55 -> 671.22666 | J51: =I55 -> 746.84386 | K51: =J55 -> 821.93472 | ... O51: =N55 -> 1114.9499
B52: Additions | C52: 229.2 | D52: 85.8 | E52: 184 | F52: 394 | G52: =G40*0.022 -> 274.274 | H52: =Assumptions!E15*H40 -> 298.95866 | I52: =Assumptions!F15*I40 -> 325.86494 | J52: =Assumptions!G15*J40 -> 351.93413 | K52: =Assumptions!H15*K40 -> 376.56952 | L52: =Assumptions!I15*L40 -> 401.04654 | M52: =Assumptions!J15*M40 -> 427.11457 | N52: =Assumptions!K15*N40 -> 454.87702 | O52: =Assumptions!L15*O40 -> 484.44402
B53: Depreciation | C53: -109.9 | D53: -130.1 | E53: -129 | F53: -147 | G53: -135 | H53: =-Assumptions!E16*('Working Schedules'!H51+0.5*'Working Schedules'!H52) -> -223.606 | I53: =-Assumptions!F16*('Working Schedules'!I51+0.5*'Working Schedules'!I52) -> -250.24774 | J53: =-Assumptions!G16*('Working Schedules'!J51+0.5*'Working Schedules'!J52) -> -276.84328 | K53: =-Assumptions!H16*('Working Schedules'!K51+0.5*'Working Schedules'!K52) -> -303.06584 | L53: =-Assumptions!I16*('Working Schedules'!L51+0.5*'Working Schedules'!L52) -> -328.7885 | M53: =-Assumptions!J16*('Working Schedules'!M51+0.5*'Working Schedules'!M52) -> -354.37612 | N53: =-Assumptions!K16*('Working Schedules'!N51+0.5*'Working Schedules'!N52) -> -380.36202 | O53: =-Assumptions!L16*('Working Schedules'!O51+0.5*'Working Schedules'!O52) -> -407.15157
B54: Termination/Transfer | C54: -23.1 | D54: -43.7 | E54: -1 | F54: -17
B55: Closing ROU assets | C55: =SUM(C51:C54) -> 260.6 | D55: =SUM(D51:D54) -> 172.6 | E55: =SUM(E51:E54) -> 226.6 | F55: =SUM(F51:F54) -> 456.6 | G55: =SUM(G51:G54) -> 595.874 | H55: =SUM(H51:H54) -> 671.22666 | I55: =SUM(I51:I54) -> 746.84386 | J55: =SUM(J51:J54) -> 821.93472 | ... O55: =SUM(O51:O54) -> 1192.2423
B59: Property Plant & Equipment Schedule
B60: Particulars | C60: 2022 | D60: =C60+1 -> 2023 | E60: =D60+1 -> 2024 | F60: =E60+1 -> 2025 | G60: =F60+1 -> 2026 | H60: =G60+1 -> 2027 | I60: =H60+1 -> 2028 | J60: =I60+1 -> 2029 | K60: =J60+1 -> 2030 | ... O60: =N60+1 -> 2034
B62: Gross PPE Opening | C62: 2247 | D62: =C65 -> 2250 | E62: =D65 -> 2012 | F62: =E65 -> 1893 | G62: =F65 -> 1939 | H62: =G65 -> 2109 | I62: =H65 -> 2299.2464 | J62: =I65 -> 2506.615 | K62: =J65 -> 2730.5731 | ... O62: =N65 -> 3786.6871
B63: Capex | C63: 124 | D63: 145.2 | E63: 126 | F63: 126 | G63: 170 | H63: =H40*Assumptions!E13 -> 190.24642 | I63: =I40*Assumptions!F13 -> 207.3686 | J63: =J40*Assumptions!G13 -> 223.95809 | K63: =K40*Assumptions!H13 -> 239.63515 | L63: =L40*Assumptions!I13 -> 255.21144 | M63: =M40*Assumptions!J13 -> 271.80018 | N63: =N40*Assumptions!K13 -> 289.46719 | O63: =O40*Assumptions!L13 -> 308.28256
B64: Disposal/transfer | C64: -121 | D64: -383.2 | E64: -245 | F64: -80
B65: Closing | C65: =SUM(C62:C64) -> 2250 | D65: =SUM(D62:D64) -> 2012 | E65: =SUM(E62:E64) -> 1893 | F65: =SUM(F62:F64) -> 1939 | G65: =SUM(G62:G64) -> 2109 | H65: =SUM(H62:H64) -> 2299.2464 | I65: =SUM(I62:I64) -> 2506.615 | J65: =SUM(J62:J64) -> 2730.5731 | ... O65: =SUM(O62:O64) -> 4094.9696
B66: Accumulated Depreciation | C66: -1035 | D66: -1033.7 | E66: -1049 | F66: -1089 | G66: =-(G65-G67) -> -894 | H66: =G66+H99 -> -1037.7029 | I66: =H66+I99 -> -1194.3663 | J66: =I66+J99 -> -1365.0272 | K66: =J66+K99 -> -1550.6652 | L66: =K66+L99 -> -1752.2539 | M66: =L66+M99 -> -1970.8301 | N66: =M66+N99 -> -2207.4981 | O66: =N66+O99 -> -2463.4337
B67: Net Block | C67: =SUM(C65:C66) -> 1215 | D67: =SUM(D65:D66) -> 978.3 | E67: =SUM(E65:E66) -> 844 | F67: =SUM(F65:F66) -> 850 | G67: 1215 | H67: =SUM(H65:H66) -> 1261.5435 | I67: =SUM(I65:I66) -> 1312.2487 | J67: =SUM(J65:J66) -> 1365.5459 | K67: =SUM(K65:K66) -> 1419.5431 | L67: =SUM(L65:L66) -> 1473.1658 | M67: =SUM(M65:M66) -> 1526.3897 | N67: =SUM(N65:N66) -> 1579.189 | O67: =SUM(O65:O66) -> 1631.5359
B70: Total Depreciation & Amortisation | H70: =H53+H82+H99 -> -377.0129 | I70: =I53+I82+I99 -> -417.15874 | J70: =J53+J82+J99 -> -458.34414 | K70: =K53+K82+K99 -> -500.18378 | L70: =L53+L82+L99 -> -542.54183 | M70: =M53+M82+M99 -> -585.84613 | N70: =N53+N82+N99 -> -630.7003 | O70: =O53+O82+O99 -> -677.58456
B73: Intangible Assests Schedule
B74: Particulars | C74: 2022 | D74: =C74+1 -> 2023 | E74: =D74+1 -> 2024 | F74: =E74+1 -> 2025 | G74: =F74+1 -> 2026 | H74: =G74+1 -> 2027 | I74: =H74+1 -> 2028 | J74: =I74+1 -> 2029 | K74: =J74+1 -> 2030 | ... O74: =N74+1 -> 2034
B76: Gross IA Opening | C76: 461.8 | D76: =C79 -> 464.8 | E76: =D79 -> 480.6 | F76: =E79 -> 498.6 | G76: =F79 -> 500.6 | H76: =G79 -> 242.6 | I76: =H79 -> 256.18903 | J76: =I79 -> 271.00107 | K76: =J79 -> 286.99808 | ... O76: =N79 -> 362.43479
B77: Additions | C77: 3 | D77: 19 | E77: 18 | F77: 2 | G77: 11 | H77: =H42-H63 -> 13.58903 | I77: =I42-I63 -> 14.812043 | J77: =J42-J63 -> 15.997006 | K77: =K42-K63 -> 17.116797 | L77: =L42-L63 -> 18.229388 | M77: =M42-M63 -> 19.414299 | N77: =N42-N63 -> 20.676228 | O77: =O42-O63 -> 22.020183
B78: Disposal/transfer | D78: -3.2 | G78: -269
B79: Closing | C79: =SUM(C76:C78) -> 464.8 | D79: =SUM(D76:D78) -> 480.6 | E79: =SUM(E76:E78) -> 498.6 | F79: =SUM(F76:F78) -> 500.6 | G79: =SUM(G76:G78) -> 242.6 | H79: =SUM(H76:H78) -> 256.18903 | I79: =SUM(I76:I78) -> 271.00107 | J79: =SUM(J76:J78) -> 286.99808 | ... O79: =SUM(O76:O78) -> 384.45497
B80: Accumulated Amortisation | C80: -106.8 | D80: -124 | E80: -150 | F80: -172 | G80: =F80-G82 -> -151 | H80: =G80+H82 -> -160.704 | I80: =H80+I82 -> -170.95156 | J80: =I80+J82 -> -181.7916 | K80: =J80+K82 -> -193.27153 | L80: =K80+L82 -> -205.43612 | M80: =L80+M82 -> -218.32989 | N80: =M80+N82 -> -232.00024 | O80: =N80+O82 -> -246.49763
B81: Net Block | C81: =SUM(C79:C80) -> 358 | D81: =SUM(D79:D80) -> 356.6 | E81: =SUM(E79:E80) -> 348.6 | F81: =SUM(F79:F80) -> 328.6 | G81: 76 | H81: =SUM(H79:H80) -> 95.48503 | I81: =SUM(I79:I80) -> 100.04951 | J81: =SUM(J79:J80) -> 105.20647 | K81: =SUM(K79:K80) -> 110.84335 | L81: =SUM(L79:L80) -> 116.90814 | M81: =SUM(M79:M80) -> 123.42867 | N81: =SUM(N79:N80) -> 130.43455 | O81: =SUM(O79:O80) -> 137.95735
B82: Amortisation Expense | C82: -20.6 | D82: -19 | E82: -25 | F82: -22 | G82: -21 | H82: =-H76*Assumptions!E14 -> -9.704 | I82: =-I76*Assumptions!F14 -> -10.247561 | J82: =-J76*Assumptions!G14 -> -10.840043 | K82: =-K76*Assumptions!H14 -> -11.479923 | L82: =-L76*Assumptions!I14 -> -12.164595 | M82: =-M76*Assumptions!J14 -> -12.893771 | N82: =-N76*Assumptions!K14 -> -13.670342 | O82: =-O76*Assumptions!L14 -> -14.497392
B85: Depreciation on PPE Schedule
B86: Particulars | C86: 2022 | D86: =C86+1 -> 2023 | E86: =D86+1 -> 2024 | F86: =E86+1 -> 2025 | G86: =F86+1 -> 2026 | H86: =G86+1 -> 2027 | I86: =H86+1 -> 2028 | J86: =I86+1 -> 2029 | K86: =J86+1 -> 2030 | ... O86: =N86+1 -> 2034 | Q86: Useful life | R86: 16
B88: Opening | H88: =H62 -> 2109 | I88: =I62 -> 2299.2464 | J88: =J62 -> 2506.615 | K88: =K62 -> 2730.5731 | L88: =L62 -> 2970.2083 | M88: =M62 -> 3225.4197 | N88: =N62 -> 3497.2199 | O88: =O62 -> 3786.6871
B89: Capex | H89: =H63 -> 190.24642 | I89: =I63 -> 207.3686 | J89: =J63 -> 223.95809 | K89: =K63 -> 239.63515 | L89: =L63 -> 255.21144 | M89: =M63 -> 271.80018 | N89: =N63 -> 289.46719 | O89: =O63 -> 308.28256
B90: Depreciation | H90: =-H88/R86 -> -131.8125 | I90: =H90 -> -131.8125 | J90: =I90 -> -131.8125 | K90: =J90 -> -131.8125 | L90: =K90 -> -131.8125 | M90: =L90 -> -131.8125 | N90: =M90 -> -131.8125 | O90: =N90 -> -131.8125
B91: Dep year 1 capex | H91: =-H$89/$R$86 -> -11.890401 | I91: =H91 -> -11.890401 | J91: =I91 -> -11.890401 | K91: =J91 -> -11.890401 | L91: =K91 -> -11.890401 | M91: =L91 -> -11.890401 | N91: =M91 -> -11.890401 | O91: =N91 -> -11.890401
B92: Dep year 2 capex | I92: =-I$89/$R$86 -> -12.960537 | J92: =I92 -> -12.960537 | K92: =J92 -> -12.960537 | L92: =K92 -> -12.960537 | M92: =L92 -> -12.960537 | N92: =M92 -> -12.960537 | O92: =N92 -> -12.960537
B93: Dep year 3 capex | J93: =-J$89/$R$86 -> -13.99738 | K93: =J93 -> -13.99738 | L93: =K93 -> -13.99738 | M93: =L93 -> -13.99738 | N93: =M93 -> -13.99738 | O93: =N93 -> -13.99738
B94: Dep year 4 capex | K94: =-K$89/$R$86 -> -14.977197 | L94: =K94 -> -14.977197 | M94: =L94 -> -14.977197 | N94: =M94 -> -14.977197 | O94: =N94 -> -14.977197
B95: Dep year 5 capex | L95: =-L$89/$R$86 -> -15.950715 | M95: =L95 -> -15.950715 | N95: =M95 -> -15.950715 | O95: =N95 -> -15.950715
B96: Dep year 6 capex | M96: =-M$89/$R$86 -> -16.987511 | N96: =M96 -> -16.987511 | O96: =N96 -> -16.987511
B97: Dep year 7 capex | N97: =-N$89/$R$86 -> -18.091699 | O97: =N97 -> -18.091699
B98: Dep year 8 capex | O98: =-O$89/$R$86 -> -19.26766
B99: Depreciation | H99: =SUM(H90:H98) -> -143.7029 | I99: =SUM(I90:I98) -> -156.66344 | J99: =SUM(J90:J98) -> -170.66082 | K99: =SUM(K90:K98) -> -185.63802 | L99: =SUM(L90:L98) -> -201.58873 | M99: =SUM(M90:M98) -> -218.57624 | N99: =SUM(N90:N98) -> -236.66794 | O99: =SUM(O90:O98) -> -255.9356

Sheet Beta Calculation
B2: Beta Calculation | E2: Beta Calculation Using Weekly Prices of last 5 years | I2: Beta | K2: Beta Calculation Using Monthly Prices of last 5 years | O2: Beta
I3: =SLOPE(G5:G273,I5:I273) -> 0.8809281 | O3: =SLOPE(M5:M65,O5:O65) -> 0.88515324
B4: Adjusted Beta | C4: 0.67×Raw Beta+0.33 | E4: Date | F4: Price | G4: % Change | H4: Nifty FMCG | I4: % Change | K4: Date | L4: Price | M4: % Change | N4: Nifty FMCG | O4: % Change
E5: 46173 | F5: 1246.7 | G5: =LN(F5/F6) -> -0.01851684 | H5: 48302.45 | I5: =LN(H5/H6) -> -0.022131039 | K5: 46143 | L5: 1270 | M5: =LN(L5/L6) -> -0.042848287 | N5: 49383.35 | O5: =LN(N5/N6) -> -0.033625037
B6: Raw Beta | C6: =O3 -> 0.88515324 | E6: 46166 | F6: 1270 | G6: =LN(F6/F7) -> -0.0094824581 | H6: 49383.35 | I6: =LN(H6/H7) -> -0.017393244 | K6: 46113 | L6: 1325.6 | M6: =LN(L6/L7) -> 0.083998419 | N6: 51072.1 | O6: =LN(N6/N7) -> 0.11467694
B7: Adjusted Beta | C7: =0.67*C6+0.33 -> 0.92305267 | E7: 46159 | F7: 1282.1 | G7: =LN(F7/F8) -> -0.02966254 | H7: 50249.8 | I7: =LN(H7/H8) -> -0.015825422 | K7: 46082 | L7: 1218.8 | M7: =LN(L7/L8) -> -0.12479627 | N7: 45538.65 | O7: =LN(N7/N8) -> -0.11604857
E8: 46152 | F8: 1320.7 | G8: =LN(F8/F9) -> 0.030677016 | H8: 51051.35 | I8: =LN(H8/H9) -> -0.0022413056 | K8: 46054 | L8: 1380.8 | M8: =LN(L8/L9) -> 0.013268402 | N8: 51142.2 | O8: =LN(N8/N9) -> -0.0014263749
E9: 46145 | F9: 1280.8 | G9: =LN(F9/F10) -> -0.034380304 | H9: 51165.9 | I9: =LN(H9/H10) -> 0.0018349347 | K9: 46023 | L9: 1362.6 | M9: =LN(L9/L10) -> -0.057814623 | N9: 51215.2 | O9: =LN(N9/N10) -> -0.079907823
E10: 46138 | F10: 1325.6 | G10: =LN(F10/F11) -> -0.048804533 | H10: 51072.1 | I10: =LN(H10/H11) -> 0.0060065961 | K10: 45992 | L10: 1443.7 | M10: =LN(L10/L11) -> -0.0054571337 | N10: 55475.65 | O10: =LN(N10/N11) -> -0.0021634731
E11: 46131 | F11: 1391.9 | G11: =LN(F11/F12) -> 0.066077171 | H11: 50766.25 | I11: =LN(H11/H12) -> 0.022077293 | K11: 45962 | L11: 1451.6 | M11: =LN(L11/L12) -> 0.01401341 | N11: 55595.8 | O11: =LN(N11/N12) -> -0.010960332
E12: 46124 | F12: 1302.9 | G12: =LN(F12/F13) -> 0.026993977 | H12: 49657.75 | I12: =LN(H12/H13) -> 0.029918902 | K12: 45931 | L12: 1431.4 | M12: =LN(L12/L13) -> 0.077768968 | N12: 56208.5 | O12: =LN(N12/N13) -> 0.027008688
E13: 46117 | F13: 1268.2 | G13: =LN(F13/F14) -> 0.03776459 | H13: 48194.05 | I13: =LN(H13/H14) -> 0.041560126 | K13: 45901 | L13: 1324.3 | M13: =LN(L13/L14) -> 0.010093813 | N13: 54710.7 | O13: =LN(N13/N14) -> -0.025822221
E14: 46110 | F14: 1221.2 | G14: =LN(F14/F15) -> -0.026344958 | H14: 46232.15 | I14: =LN(H14/H15) -> -0.0042100509 | K14: 45870 | L14: 1311 | M14: =LN(L14/L15) -> -0.022028652 | N14: 56141.85 | O14: =LN(N14/N15) -> 0.0058899361
E15: 46103 | F15: 1253.8 | G15: =LN(F15/F16) -> -0.036262245 | H15: 46427.2 | I15: =LN(H15/H16) -> -0.012422733 | K15: 45839 | L15: 1340.2 | M15: =LN(L15/L16) -> -0.063526033 | N15: 55812.15 | O15: =LN(N15/N16) -> 0.016771543
E16: 46096 | F16: 1300.1 | G16: =LN(F16/F17) -> -0.010939103 | H16: 47007.55 | I16: =LN(H16/H17) -> -0.019311326 | K16: 45809 | L16: 1428.1 | M16: =LN(L16/L17) -> -0.062431233 | N16: 54883.9 | O16: =LN(N16/N17) -> -0.0072454021
E17: 46089 | F17: 1314.4 | G17: =LN(F17/F18) -> -0.055779564 | H17: 47924.15 | I17: =LN(H17/H18) -> -0.04181528 | K17: 45778 | L17: 1520.1 | M17: =LN(L17/L18) -> -0.028406579 | N17: 55283 | O17: =LN(N17/N18) -> -0.020807466
E18: 46082 | F18: 1389.8 | G18: =LN(F18/F19) -> 0.0064968106 | H18: 49970.6 | I18: =LN(H18/H19) -> -0.023175156 | K18: 45748 | L18: 1563.9 | M18: =LN(L18/L19) -> 0.10978232 | N18: 56445.35 | O18: =LN(N18/N19) -> 0.051914162
E19: 46075 | F19: 1380.8 | G19: =LN(F19/F20) -> 0.0010869172 | H19: 51142.2 | I19: =LN(H19/H20) -> -0.012252995 | K19: 45717 | L19: 1401.3 | M19: =LN(L19/L20) -> 0.087069766 | N19: 53589.8 | O19: =LN(N19/N20) -> 0.055649827
... E65: 45753 | F65: 1476.9 | G65: =LN(F65/F66) -> 0.034125718 | H65: 55741.1 | I65: =LN(H65/H66) -> 0.03487382 | K65: 44317 | L65: 612.45 | M65: =LN(L65/L66) -> 0.16450425 | N65: 35243.1 | O65: =LN(N65/N66) -> 0.047046025
E66: 45746 | F66: 1427.35 | G66: =LN(F66/F67) -> 0.018419201 | H66: 53830.7 | I66: =LN(H66/H67) -> 0.0044851849 | K66: 44287 | L66: 519.55 | N66: 33623.45
E67: 45739 | F67: 1401.3 | G67: =LN(F67/F68) -> 0.0069462129 | H67: 53589.8 | I67: =LN(H67/H68) -> 0.01133008
E68: 45732 | F68: 1391.6 | G68: =LN(F68/F69) -> 0.02761258 | H68: 52986.05 | I68: =LN(H68/H69) -> 0.021109768
E69: 45725 | F69: 1353.7 | G69: =LN(F69/F70) -> 0.019280491 | H69: 51879.25 | I69: =LN(H69/H70) -> -0.00024187864
E70: 45718 | F70: 1327.85 | G70: =LN(F70/F71) -> 0.033230482 | H70: 51891.8 | I70: =LN(H70/H71) -> 0.023451857
E71: 45711 | F71: 1284.45 | G71: =LN(F71/F72) -> -0.017021195 | H71: 50689 | I71: =LN(H71/H72) -> -0.027420515
E72: 45704 | F72: 1306.5 | G72: =LN(F72/F73) -> -0.043362966 | H72: 52098.15 | I72: =LN(H72/H73) -> -0.019773214
E73: 45697 | F73: 1364.4 | G73: =LN(F73/F74) -> -0.045209891 | H73: 53138.55 | I73: =LN(H73/H74) -> -0.036488413
E74: 45690 | F74: 1427.5 | G74: =LN(F74/F75) -> 0.0024548496 | H74: 55113.3 | I74: =LN(H74/H75) -> -0.028241159
E75: 45683 | F75: 1424 | G75: =LN(F75/F76) -> -0.031622505 | H75: 56691.95 | I75: =LN(H75/H76) -> 0.011042908
E76: 45676 | F76: 1469.75 | G76: =LN(F76/F77) -> 0.02913263 | H76: 56069.35 | I76: =LN(H76/H77) -> 0.0048002152
E77: 45669 | F77: 1427.55 | G77: =LN(F77/F78) -> -0.075270628 | H77: 55800.85 | I77: =LN(H77/H78) -> -0.023324949
E78: 45662 | F78: 1539.15 | G78: =LN(F78/F79) -> -0.089020748 | H78: 57117.7 | I78: =LN(H78/H79) -> -0.012168799
... E273: 44297 | F273: 519.05 | G273: =LN(F273/F274) -> -0.034370247 | H273: 34853.15 | I273: =LN(H273/H274) -> -0.011409948
E274: 44290 | F274: 537.2 | H274: 35253.1

Sheet Company & Market Insights
B2: United Spirits Company Insights
N3: (in Millions)
B4: Product Segments | C4: 2014 | D4: =C4+1 -> 2015 | E4: =D4+1 -> 2016 | F4: =E4+1 -> 2017 | G4: =F4+1 -> 2018 | H4: =G4+1 -> 2019 | I4: =H4+1 -> 2020 | J4: =I4+1 -> 2021 | K4: =J4+1 -> 2022 | ... N4: =M4+1 -> 2025
B6: Popular Vol | C6: 87.7 | D6: 82.06 | E6: 59 | F6: 53.2 | G6: 41.3 | H6: 40 | I6: 38.85 | J6: 33.5 | K6: 36.41 | L6: 24.65 | M6: 11.1 | N6: 10.88
D7: =LN(D6/C6) -> -0.066471212 | E7: =LN(E6/D6) -> -0.32991324 | F7: =LN(F6/E6) -> -0.10347905 | G7: =LN(G6/F6) -> -0.2531959 | H7: =LN(H6/G6) -> -0.031983046 | I7: =LN(I6/H6) -> -0.029171377 | J7: =LN(J6/I6) -> -0.14816264 | K7: =LN(K6/J6) -> 0.083298023 | ... N7: =LN(N6/M6) -> -0.020018867
B8: Prestige & Above (P&A) Vol | C8: 33 | D8: 35 | E8: 34 | F8: 36.8 | G8: 37.2 | H8: 41.6 | I8: 40.9 | J8: 37.2 | K8: 42.74 | L8: 47.85 | M8: 50.3 | N8: 53.12
D9: =LN(D8/C8) -> 0.0588405 | E9: =LN(E8/D8) -> -0.028987537 | F9: =LN(F8/E8) -> 0.079137321 | G9: =LN(G8/F8) -> 0.010810916 | H9: =LN(H8/G8) -> 0.11179141 | I9: =LN(I8/H8) -> -0.016970104 | J9: =LN(J8/I8) -> -0.094821302 | K9: =LN(K8/J8) -> 0.13882649 | ... N9: =LN(N8/M8) -> 0.054548428
B10: Total Sales Volume | C10: =C8+C6 -> 120.7 | D10: =D8+D6 -> 117.06 | E10: =E8+E6 -> 93 | F10: =F8+F6 -> 90 | G10: =G8+G6 -> 78.5 | H10: =H8+H6 -> 81.6 | I10: =I8+I6 -> 79.75 | J10: =J8+J6 -> 70.7 | ... N10: =N8+N6 -> 64
D11: =LN(D10/C10) -> -0.030621504 | E11: =LN(E10/D10) -> -0.23008713 | F11: =LN(F10/E10) -> -0.032789823 | G11: =LN(G10/F10) -> -0.13671105 | H11: =LN(H10/G10) -> 0.038730637 | I11: =LN(I10/H10) -> -0.02293252 | J11: =LN(J10/I10) -> -0.12045117 | K11: =LN(K10/J10) -> 0.11289921 | ... N11: =LN(N10/M10) -> 0.041473248
B13: CAGR in P&A Segment | C13: =_xlfn.RRI(10,C8,N8) -> 0.048755889
B15: Segment Tier | C15: Category / Product Name | D15: Brand Positioning & Pricing Sub-Tier | E15: Consolidated Value Matrices & Revenue Benchmarks
B16: Prestige & Above (P&A) | C16: McDowell's No.1 Whisky | D16: Lower Prestige | E16: > ₹1,000 Crore Brand
B17: Prestige & Above (P&A) | C17: Royal Challenge | D17: Mid Prestige | E17: > ₹1,000 Crore Brand
B18: Prestige & Above (P&A) | C18: Johnnie Walker (Blue, Gold, Black, Double Black, Red, Blonde Label) | D18: Luxury & Premium Scotch | E18: > ₹1,000 Crore Brand
B19: Prestige & Above (P&A) | C19: Black & White | D19: Premium Scotch | E19: ₹500 - ₹1,000 Crore Brand
B20: Prestige & Above (P&A) | C20: Black Dog (Triple Gold Reserve, Black Reserve, Millard's Private Reserve) | D20: Premium Scotch | E20: ₹500 - ₹1,000 Crore Brand
B21: Prestige & Above (P&A) | C21: Signature (Premier, Rare) | D21: Upper Prestige | E21: ₹500 - ₹1,000 Crore Brand
B22: Prestige & Above (P&A) | C22: Royal Challenge American Pride | D22: Upper Prestige | E22: Prestige Sub-Tier
B23: Prestige & Above (P&A) | C23: Godawan (01 Rich & Rounded, 02 Fruit & Spice) | D23: Luxury Malts (Artisanal Craft) | E23: High-Growth Luxury Core
B24: Prestige & Above (P&A) | C24: McDowell's & Co Distiller's Batch | D24: Luxury Malts | E24: Premium Innovation Core
B25: Prestige & Above (P&A) | C25: Don Julio Tequila | D25: Premium Luxury Spirits | E25: High-Growth Tequila Tier
B26: Prestige & Above (P&A) | C26: Smirnoff Vodka (Core & Flavors: Mirchi Mango, Minty Jamun, Zesty Lime) | D26: White Spirits / Flavour Range | E26: Premium Spirit Core
... B32: Popular Segment | C32: Mass-Market Brandies / Regional Spirits | D32: Value / Heritage Spirit Lines | E32: Mass Value Contribution

Sheet Notes to accounts
B2: Notes to Accounts
B3: Other Income
C4: 2022 | D4: =C4+1 -> 2023 | E4: =D4+1 -> 2024 | F4: =E4+1 -> 2025 | G4: =F4+1 -> 2026
M5: 42064 | N5: 42430 | O5: 42795 | P5: 43160 | Q5: 43525 | R5: 43891 | S5: 44256 | T5: 44621 | U5: 44986 | V5: 45352 | W5: 45717 | X5: 46082
B6: Interest income on financial assets held at amortised cost | C6: 6.1 | D6: 32 | E6: 0 | F6: 0 | G6: 0 | L6: Debtor Days | M6: 69 | N6: 99 | O6: 122 | P6: 115 | Q6: 99 | R6: 89 | S6: 98 | T6: 89 | U6: 84 | V6: 99 | W6: 103 | X6: 106
B7: Exchange gain (net) | C7: 0.4 | D7: 0 | E7: 0 | F7: 0 | G7: 0 | L7: Inventory Days | M7: 123 | N7: 150 | O7: 226 | P7: 263 | Q7: 235 | R7: 199 | S7: 254 | T7: 229 | U7: 193 | V7: 186 | W7: 197 | X7: 146
B8: Gain on disposal of property plant and equipment (net) | C8: 12.3 | D8: 20.3 | E8: 12 | F8: 99 | G8: 0 | L8: Days Payable | M8: 56 | N8: 78 | O8: 144 | P8: 195 | Q8: 171 | R8: 124 | S8: 176 | T8: 168 | U8: 154 | V8: 176 | W8: 191 | X8: 130
B9: Profit on sale of investment | C9: 0.6 | D9: 16.6 | E9: 0 | F9: 0 | G9: 0 | L9: Cash Conversion Cycle | M9: 136 | N9: 171 | O9: 205 | P9: 183 | Q9: 163 | R9: 165 | S9: 177 | T9: 150 | U9: 122 | V9: 108 | W9: 109 | X9: 121
B10: Fair value gains on current investments (net) | C10: 0 | D10: 2.5 | E10: 0 | F10: 0 | G10: 0 | L10: Working Capital Days | M10: -61 | N10: -30 | O10: -22 | P10: -12 | Q10: -8 | R10: -8 | S10: 17 | T10: 39 | U10: 51 | V10: 52 | W10: 48 | X10: 101
B11: Liabilities no longer required written back | C11: 13.4 | D11: 0.4 | E11: 0 | F11: 0 | G11: 0
B12: Bad debts / advances recovered | C12: 0 | D12: 0.3 | E12: 4 | F12: 1 | G12: 0
B13: Miscellaneous income | C13: 2.7 | D13: 1 | E13: 14 | F13: 38 | G13: 0
B14: Interest income on term deposits and investments held at amortised cost | C14: 0 | D14: 0 | E14: 42 | F14: 59 | G14: 0
B15: Interest income on direct and indirect tax refunds | C15: 0 | D15: 0 | E15: 88 | F15: 48 | G15: 0
B16: Interest income from loan to a joint venture held at amortised cost | C16: 0 | D16: 0 | E16: 0 | F16: 1 | G16: 0
B17: Profit on redemption of mutual fund units | C17: 0 | D17: 0 | E17: 47 | F17: 74 | G17: 0
B18: Increase in fair value of current investments (net) | C18: 0 | D18: 0 | E18: 18 | F18: 16 | G18: 0
B19: Total Other Income | C19: =SUM(C6:C18) -> 35.5 | D19: =SUM(D6:D18) -> 73.1 | E19: =SUM(E6:E18) -> 225 | F19: =SUM(F6:F18) -> 336 | G19: 478
B20: Exceptional Items | C20: -165.2 | D20: 176.4 | E20: -17 | F20: -65 | G20: -91
B21: Extraordinary Items | C21: 0 | D21: 0 | E21: 0 | F21: 0 | G21: 129
B23: Total other income For analysis | C23: =C19-SUM(C7:C11) -> 8.8 | D23: =D19-SUM(D8:D11) -> 33.3 | E23: =E19-E8-E12-E15 -> 121 | F23: =F19-F8-F12-F15 -> 188 | G23: =G19 -> 478
B24: Exceptional items for analysis | C24: =C19-C23 -> 26.7 | D24: =D19-D23 -> 39.8 | E24: =E19-E23 -> 104 | F24: =F19-F23 -> 148 | G24: =G20+G21 -> 38
C26: =C23/C19 -> 0.24788732 | D26: =D23/D19 -> 0.45554036 | E26: =E23/E19 -> 0.53777778 | F26: =F23/F19 -> 0.55952381 | G26: =G23/G19 -> 1
D27: =LN(D23/C23) -> 1.3308057 | E27: =LN(E23/D23) -> 1.2902331 | F27: =LN(F23/E23) -> 0.44065142 | G27: =LN(G23/F23) -> 0.93316877
B29: Finance costs
C30: 2022 | D30: =C30+1 -> 2023 | E30: =D30+1 -> 2024 | F30: =E30+1 -> 2025 | G30: =F30+1 -> 2026
B31: Interest charges on lease liabilities | C31: 11.9 | D31: 16 | E31: 21 | F31: 40
B32: Interest expense on borrowings at amortised cost | C32: 38 | D32: 20.3
B33: Interest- others | C33: 38.1 | D33: 67.6 | E33: 55 | F33: 49
C34: =SUM(C31:C33) -> 88 | D34: =SUM(D31:D33) -> 103.9 | E34: =SUM(E31:E33) -> 76 | F34: =SUM(F31:F33) -> 89 | G34: 158
B36: Depreciation and Amortisation
C37: 2022 | D37: =C37+1 -> 2023 | E37: =D37+1 -> 2024 | F37: =E37+1 -> 2025 | G37: =F37+1 -> 2026
B38: Depreciation / impairment of property, plant and equipmen | C38: 173.3 | D38: 133.4 | E38: 121 | F38: 114 | G38: =G44*$G$41 -> 131.81469
B39: Depreciation of right-of-use assets | C39: 109.9 | D39: 130.1 | E39: 129 | F39: 147 | G39: =G45*$G$41 -> 134.33036
B40: Amortisation / impairment of intangible assets | C40: 20.6 | D40: 19 | E40: 25 | F40: 22 | G40: =G46*$G$41 -> 21.031438
B41: Total D&A | C41: =SUM(C38:C40) -> 303.8 | D41: =SUM(D38:D40) -> 282.5 | E41: =SUM(E38:E40) -> 275 | F41: =SUM(F38:F40) -> 283 | G41: 289
B44: Depreciation / impairment of PPE as % of total dep | C44: =C38/$C$41 -> 0.57044108 | D44: =D38/$D$41 -> 0.47221239 | E44: =E38/$E$41 -> 0.44 | F44: =F38/$F$41 -> 0.40282686 | G44: =MEDIAN(C44:F44) -> 0.45610619 | I44: =_xlfn.FORMULATEXT(G44) -> =MEDIAN(C44:F44)
B45: Depreciation of right-of-use assets as % of total dep | C45: =C39/$C$41 -> 0.36175115 | D45: =D39/$D$41 -> 0.46053097 | E45: =E39/$E$41 -> 0.46909091 | F45: =F39/$F$41 -> 0.51943463 | G45: =MEDIAN(C45:F45) -> 0.46481094 | I45: =_xlfn.FORMULATEXT(G45) -> =MEDIAN(C45:F45)
B46: Amortisation / impairment of intangible assets as %of total dep | C46: =C40/$C$41 -> 0.067807768 | D46: =D40/$D$41 -> 0.067256637 | E46: =E40/$E$41 -> 0.090909091 | F46: =F40/$F$41 -> 0.077738516 | G46: =MEDIAN(C46:F46) -> 0.072773142 | I46: =_xlfn.FORMULATEXT(G46) -> =MEDIAN(C46:F46)
