Workbook

Sheet README
B2: UNITED SPIRITS LIMITED (USL)
B3: Debt Schedule & Cash Schedule | Consolidated | Net-interest forecast
B6: Purpose | C6: Model USL's borrowings, lease liabilities and treasury (cash + bank deposits + current investments) to forecast finance cost, investment income and NET INTEREST.
B7: Key finding | C7: USL is effectively debt-free (external borrowings ~0 since FY2024). Its only interest-bearing 'debt' is lease liabilities (Ind AS 116). It is cash-rich, so investment income exceeds finance cost and NET INTEREST is positive and growing.
B8: Units | C8: All figures in Rs crore unless stated. FY = year ended 31 March.
B9: History | C9: FY2022-FY2025 are ACTUALS from the consolidated financial statements.
B10: Sources | C10: FY2023 Annual Report (figures originally in Rs million, converted /10) for FY2022 & FY2023; FY2025 Annual Report (Rs crore) for FY2024 & FY2025.
B11: Forecast | C11: FY2026E-FY2030E are driver-based. FY2027E-FY2030E is the requested horizon; FY2026E is included as a bridge from the FY2025 actual.
B12: How to use | C12: Edit the yellow cells on the 'Assumptions' sheet only. Every other number is a live formula that recalculates automatically.
B13: No circularity | C13: Investment income is earned on the OPENING treasury balance and lease interest on the OPENING lease liability, so the model solves without iterative calculation.
B14: Sheets | C14: 1) Assumptions 2) Debt Schedule 3) Cash Schedule 4) P&L & Net Interest
B16: BASE-YEAR DATA TRACE (Rs crore, consolidated)
B17: Line item | C17: FY2022 | D17: FY2023 | E17: FY2024 | F17: FY2025
B18: Borrowings (current + non-current) | C18: 341.7 | D18: 1.1 | E18: 25 | F18: 0
B19: Lease liabilities (current + non-current) | C19: 263.7 | D19: 182.2 | E19: 240 | F19: 480
B20: Cash & cash equivalents | C20: 54.5 | D20: 115.1 | E20: 1052 | F20: 1328
B21: Bank balances (other deposits) | C21: 5.8 | D21: 768.2 | E21: 217 | F21: 702
B22: Current investments | C22: 222.1 | D22: 255.8 | E22: 599 | F22: 873
B23: Finance costs (P&L) | C23: 88 | D23: 103.9 | E23: 76 | F23: 89
B24: Net revenue (rev. less excise) | C24: 9712.4 | D24: 10611.6 | E24: 11321 | F24: 12069
B25: Profit after tax | C25: 810.6 | D25: 1125.8 | E25: 1408 | F25: 1582

Sheet Assumptions
A1: USL | KEY ASSUMPTIONS (edit yellow cells only)
A3: Driver | B3: FY2022A | C3: FY2023A | D3: FY2024A | E3: FY2025A | F3: FY2026E | G3: FY2027E | H3: FY2028E | I3: FY2029E | J3: FY2030E
A4: Income statement drivers
A5: Net revenue growth % | C5: 0.093 | D5: 0.067 | E5: 0.066 | F5: 0.08 | G5: 0.08 | H5: 0.08 | I5: 0.07 | J5: 0.07 | K5: Hist FY23-25 ~6-9%
A6: EBITDA margin % (on net revenue) | D6: 0.168 | E6: 0.186 | F6: 0.185 | G6: 0.19 | H6: 0.193 | I6: 0.195 | J6: 0.198 | K6: FY25 actual 18.6%
A7: Depreciation & amortisation % of net revenue | B7: 0.031 | C7: 0.027 | D7: 0.024 | E7: 0.023 | F7: 0.023 | G7: 0.023 | H7: 0.023 | I7: 0.023 | J7: 0.023
A8: Effective / cash tax rate % | D8: 0.242 | E8: 0.258 | F8: 0.255 | G8: 0.255 | H8: 0.255 | I8: 0.255 | J8: 0.255
A9: Cash-flow drivers
A10: Capex % of net revenue | B10: 0.014 | C10: 0.013 | D10: 0.009 | E10: 0.013 | F10: 0.016 | G10: 0.016 | H10: 0.017 | I10: 0.017 | J10: 0.018
A11: Incremental net working capital % of revenue growth | F11: 0.22 | G11: 0.22 | H11: 0.2 | I11: 0.2 | J11: 0.2 | K11: Hist core NWC ~25-29% of sales
A12: Dividend payout % (of prior-year PAT) | E12: 0.45 | F12: 0.6 | G12: 0.65 | H12: 0.65 | I12: 0.7 | J12: 0.7 | K12: FY25 ~45%, Diageo raising payout
A13: Debt & lease drivers
A14: New lease additions (Rs cr) | B14: 229.2 | C14: 85.8 | D14: 184 | E14: 394 | F14: 300 | G14: 300 | H14: 320 | I14: 340 | J14: 360 | K14: RoU additions; FY25 was high
A15: Lease principal repayment % of opening lease liability | F15: 0.4 | G15: 0.4 | H15: 0.4 | I15: 0.4 | J15: 0.4 | K15: FY25 ~29% of opening
A16: Lease interest rate % (on opening lease liability) | D16: 0.115 | E16: 0.111 | F16: 0.095 | G16: 0.095 | H16: 0.095 | I16: 0.095 | J16: 0.095 | K16: Implied FY24-25 ~10-11%
A17: Other (non-lease) finance cost (Rs cr) | B17: 37.9 | C17: 67.6 | D17: 55 | E17: 49 | F17: 50 | G17: 52 | H17: 54 | I17: 56 | J17: 58 | K17: Unwind of discounts, bank charges
A18: New borrowings drawn (Rs cr) | D18: 25 | E18: 0 | F18: 0 | G18: 0 | H18: 0 | I18: 0 | J18: 0 | K18: Co. funds from internal cash
A19: Borrowings repaid (Rs cr) | F19: 0 | G19: 0 | H19: 0 | I19: 0 | J19: 0
A20: Borrowing interest rate % | F20: 0.085 | G20: 0.085 | H20: 0.085 | I20: 0.085 | J20: 0.085 | K20: WC loan rate
A21: Treasury / investment drivers
A22: Blended yield on average treasury % | D22: 0.064 | E22: 0.063 | F22: 0.065 | G22: 0.065 | H22: 0.065 | I22: 0.065 | J22: 0.065 | K22: Deposits + debt MF; ex one-off tax-refund interest

Sheet Debt Schedule
A1: USL | DEBT SCHEDULE (borrowings + lease liabilities)
A3: Rs crore (consolidated) | B3: FY2022A | C3: FY2023A | D3: FY2024A | E3: FY2025A | F3: FY2026E | G3: FY2027E | H3: FY2028E | I3: FY2029E | J3: FY2030E
A4: A. External borrowings (working-capital / term loans)
A5: Opening borrowings | B5: 879.4 | C5: 341.7 | D5: 1.1 | E5: 25 | F5: =E8 | G5: =F8 | H5: =G8 | I5: =H8 | J5: =I8
A6: Add: new borrowings drawn | F6: =Assumptions!F18 | G6: =Assumptions!G18 | H6: =Assumptions!H18 | I6: =Assumptions!I18 | J6: =Assumptions!J18
A7: Less: repayments | F7: =-Assumptions!F19 | G7: =-Assumptions!G19 | H7: =-Assumptions!H19 | I7: =-Assumptions!I19 | J7: =-Assumptions!J19
A8: Closing borrowings | B8: 341.7 | C8: 1.1 | D8: 25 | E8: 0 | F8: =F5+F6+F7 | G8: =G5+G6+G7 | H8: =H5+H6+H7 | I8: =I5+I6+I7 | J8: =J5+J6+J7
A9: Interest on borrowings | B9: 38.2 | C9: 20.3 | D9: 0 | E9: 0 | F9: =F5*Assumptions!F20 | G9: =G5*Assumptions!G20 | H9: =H5*Assumptions!H20 | I9: =I5*Assumptions!I20 | J9: =J5*Assumptions!J20
A11: B. Lease liabilities (Ind AS 116)
A12: Opening lease liability | B12: 264.2 | C12: 263.7 | D12: 182.2 | E12: 240 | F12: =E16 | G12: =F16 | H12: =G16 | I12: =H16 | J12: =I16
A13: Add: new lease additions | B13: 229.2 | C13: 85.8 | D13: 184 | E13: 394 | F13: =Assumptions!F14 | G13: =Assumptions!G14 | H13: =Assumptions!H14 | I13: =Assumptions!I14 | J13: =Assumptions!J14
A14: Add: interest accrued (finance cost) | B14: =B18 | C14: =C18 | D14: =D18 | E14: =E18 | F14: =F12*Assumptions!F16 | G14: =G12*Assumptions!G16 | H14: =H12*Assumptions!H16 | I14: =I12*Assumptions!I16 | J14: =J12*Assumptions!J16
A15: Less: lease payments (principal + interest) | B15: =B17+B18 | C15: =C17+C18 | D15: =D17+D18 | E15: =E17+E18 | F15: =-(F17+F18) | G15: =-(G17+G18) | H15: =-(H17+H18) | I15: =-(I17+I18) | J15: =-(J17+J18)
A16: Closing lease liability | B16: 263.7 | C16: 182.2 | D16: 240 | E16: 480 | F16: =F12+F13+F14+F15 | G16: =G12+G13+G14+G15 | H16: =H12+H13+H14+H15 | I16: =I12+I13+I14+I15 | J16: =J12+J13+J14+J15
A17: memo: principal repayment | B17: 100.2 | C17: 124 | D17: 126 | E17: 137 | F17: =F12*Assumptions!F15 | G17: =G12*Assumptions!G15 | H17: =H12*Assumptions!H15 | I17: =I12*Assumptions!I15 | J17: =J12*Assumptions!J15
A18: memo: lease interest expense | B18: 11.9 | C18: 16 | D18: 21 | E18: 40 | F18: =F14 | G18: =G14 | H18: =H14 | I18: =I14 | J18: =J14
A20: C. Total debt & finance cost
A21: Total debt (borrowings + leases), closing | B21: =B8+B16 | C21: =C8+C16 | D21: =D8+D16 | E21: =E8+E16 | F21: =F8+F16 | G21: =G8+G16 | H21: =H8+H16 | I21: =I8+I16 | J21: =J8+J16
A22: Finance cost: borrowing interest | B22: =B9 | C22: =C9 | D22: =D9 | E22: =E9 | F22: =F9 | G22: =G9 | H22: =H9 | I22: =I9 | J22: =J9
A23: Finance cost: lease interest | B23: =B18 | C23: =C18 | D23: =D18 | E23: =E18 | F23: =F18 | G23: =G18 | H23: =H18 | I23: =I18 | J23: =J18
A24: Finance cost: other (unwind/charges) | B24: 37.9 | C24: 67.6 | D24: 55 | E24: 49 | F24: =Assumptions!F17 | G24: =Assumptions!G17 | H24: =Assumptions!H17 | I24: =Assumptions!I17 | J24: =Assumptions!J17
A25: TOTAL FINANCE COST (P&L) | B25: 88 | C25: 103.9 | D25: 76 | E25: 89 | F25: =F22+F23+F24 | G25: =G22+G23+G24 | H25: =H22+H23+H24 | I25: =I22+I23+I24 | J25: =J22+J23+J24

Sheet Cash Schedule
A1: USL | CASH / TREASURY SCHEDULE
A3: Rs crore (consolidated) | B3: FY2022A | C3: FY2023A | D3: FY2024A | E3: FY2025A | F3: FY2026E | G3: FY2027E | H3: FY2028E | I3: FY2029E | J3: FY2030E
A4: A. Treasury composition (closing, Rs cr)
A5: Cash & cash equivalents | B5: 54.5 | C5: 115.1 | D5: 1052 | E5: 1328 | F5: =F19*0.46 | G5: =G19*0.46 | H5: =H19*0.46 | I5: =I19*0.46 | J5: =J19*0.46
A6: Bank balances (other deposits) | B6: 5.8 | C6: 768.2 | D6: 217 | E6: 702 | F6: =F19*0.24 | G6: =G19*0.24 | H6: =H19*0.24 | I6: =I19*0.24 | J6: =J19*0.24
A7: Current investments (debt mutual funds etc.) | B7: 222.1 | C7: 255.8 | D7: 599 | E7: 873 | F7: =F19-F5-F6 | G7: =G19-G5-G6 | H7: =H19-H5-H6 | I7: =I19-I5-I6 | J7: =J19-J5-J6
A8: Total treasury (cash + deposits + investments) | B8: =B5+B6+B7 | C8: =C5+C6+C7 | D8: =D5+D6+D7 | E8: =E5+E6+E7 | F8: =F5+F6+F7 | G8: =G5+G6+G7 | H8: =H5+H6+H7 | I8: =I5+I6+I7 | J8: =J5+J6+J7
A10: B. Treasury roll-forward (cash build, FCFE basis)
A11: Opening treasury | B11: 300 | C11: 282.4 | D11: 1139.1 | E11: 1868 | F11: =E19 | G11: =F19 | H11: =G19 | I11: =H19 | J11: =I19
A12: Add: Profit after tax (from P&L sheet) | B12: 810.6 | C12: 1125.8 | D12: 1408 | E12: 1582 | F12: ='P&L & Net Interest'!F13 | G12: ='P&L & Net Interest'!G13 | H12: ='P&L & Net Interest'!H13 | I12: ='P&L & Net Interest'!I13 | J12: ='P&L & Net Interest'!J13
A13: Add: Depreciation & amortisation (non-cash) | B13: 303.8 | C13: 282.5 | D13: 275 | E13: 283 | F13: =-'P&L & Net Interest'!F7 | G13: =-'P&L & Net Interest'!G7 | H13: =-'P&L & Net Interest'!H7 | I13: =-'P&L & Net Interest'!I7 | J13: =-'P&L & Net Interest'!J7
A14: Less: increase in net working capital | B14: =B19-B11-B12-B13-B15-B16-B17 | C14: =C19-C11-C12-C13-C15-C16-C17 | D14: =D19-D11-D12-D13-D15-D16-D17 | E14: =E19-E11-E12-E13-E15-E16-E17 | F14: =-'P&L & Net Interest'!F17 | G14: =-'P&L & Net Interest'!G17 | H14: =-'P&L & Net Interest'!H17 | I14: =-'P&L & Net Interest'!I17 | J14: =-'P&L & Net Interest'!J17
A15: Less: capital expenditure | B15: -134 | C15: -136.6 | D15: -98 | E15: -162 | F15: =-'P&L & Net Interest'!F16 | G15: =-'P&L & Net Interest'!G16 | H15: =-'P&L & Net Interest'!H16 | I15: =-'P&L & Net Interest'!I16 | J15: =-'P&L & Net Interest'!J16
A16: Less: lease principal repayment | B16: =-'Debt Schedule'!B17 | C16: =-'Debt Schedule'!C17 | D16: =-'Debt Schedule'!D17 | E16: =-'Debt Schedule'!E17 | F16: =-'Debt Schedule'!F17 | G16: =-'Debt Schedule'!G17 | H16: =-'Debt Schedule'!H17 | I16: =-'Debt Schedule'!I17 | J16: =-'Debt Schedule'!J17
A17: Less: dividends paid | B17: 0 | C17: 0 | D17: -284 | E17: -355 | F17: =-'P&L & Net Interest'!F18 | G17: =-'P&L & Net Interest'!G18 | H17: =-'P&L & Net Interest'!H18 | I17: =-'P&L & Net Interest'!I18 | J17: =-'P&L & Net Interest'!J18
A18: Net change in treasury | B18: =B19-B11 | C18: =C19-C11 | D18: =D19-D11 | E18: =E19-E11 | F18: =F12+F13+F14+F15+F16+F17 | G18: =G12+G13+G14+G15+G16+G17 | H18: =H12+H13+H14+H15+H16+H17 | I18: =I12+I13+I14+I15+I16+I17 | J18: =J12+J13+J14+J15+J16+J17
A19: Closing treasury | B19: =B8 | C19: =C8 | D19: =D8 | E19: =E8 | F19: =F11+F18 | G19: =G11+G18 | H19: =H11+H18 | I19: =I11+I18 | J19: =J11+J18
A21: C. Investment / interest income
A22: Average treasury (opening + closing)/2 | B22: =(B11+B19)/2 | C22: =(C11+C19)/2 | D22: =(D11+D19)/2 | E22: =(E11+E19)/2 | F22: =(F11+F19)/2 | G22: =(G11+G19)/2 | H22: =(H11+H19)/2 | I22: =(I11+I19)/2 | J22: =(J11+J19)/2
A23: Investment & interest income (yield x opening treasury) | B23: 6.1 | C23: 32 | D23: 107 | E23: 150 | F23: =F11*Assumptions!F22 | G23: =G11*Assumptions!G22 | H23: =H11*Assumptions!H22 | I23: =I11*Assumptions!I22 | J23: =J11*Assumptions!J22
A24: memo: dividend payout this year | B24: =-B17 | C24: =-C17 | D24: =-D17 | E24: =-E17 | F24: =-F17 | G24: =-G17 | H24: =-H17 | I24: =-I17 | J24: =-J17

Sheet P&L & Net Interest
A1: USL | CONDENSED P&L & NET INTEREST
A3: Rs crore (consolidated) | B3: FY2022A | C3: FY2023A | D3: FY2024A | E3: FY2025A | F3: FY2026E | G3: FY2027E | H3: FY2028E | I3: FY2029E | J3: FY2030E
A4: A. Condensed P&L (drives the schedules)
A5: Net revenue (revenue less excise duty) | B5: 9712.4 | C5: 10611.6 | D5: 11321 | E5: 12069 | F5: =E5*(1+Assumptions!F5) | G5: =F5*(1+Assumptions!G5) | H5: =G5*(1+Assumptions!H5) | I5: =H5*(1+Assumptions!I5) | J5: =I5*(1+Assumptions!J5)
A6: EBITDA | B6: 1608 | C6: 1416.6 | D6: 1898 | E6: 2243 | F6: =F5*Assumptions!F6 | G6: =G5*Assumptions!G6 | H6: =H5*Assumptions!H6 | I6: =I5*Assumptions!I6 | J6: =J5*Assumptions!J6
A7: Less: Depreciation & amortisation | B7: -303.8 | C7: -282.5 | D7: -275 | E7: -283 | F7: =-F5*Assumptions!F7 | G7: =-G5*Assumptions!G7 | H7: =-H5*Assumptions!H7 | I7: =-I5*Assumptions!I7 | J7: =-J5*Assumptions!J7
A8: EBIT | B8: =B6+B7 | C8: =C6+C7 | D8: =D6+D7 | E8: =E6+E7 | F8: =F6+F7 | G8: =G6+G7 | H8: =H6+H7 | I8: =I6+I7 | J8: =J6+J7
A9: Less: Finance cost (Debt Schedule) | B9: -88 | C9: -103.9 | D9: -76 | E9: -89 | F9: =-'Debt Schedule'!F25 | G9: =-'Debt Schedule'!G25 | H9: =-'Debt Schedule'!H25 | I9: =-'Debt Schedule'!I25 | J9: =-'Debt Schedule'!J25
A10: Add: Investment & interest income (Cash Schedule) | B10: 6.1 | C10: 32 | D10: 107 | E10: 150 | F10: ='Cash Schedule'!F23 | G10: ='Cash Schedule'!G23 | H10: ='Cash Schedule'!H23 | I10: ='Cash Schedule'!I23 | J10: ='Cash Schedule'!J23
A11: Profit before tax | B11: 1086.6 | C11: 1278.6 | D11: 1857 | E11: 2135 | F11: =F8+F9+F10 | G11: =G8+G9+G10 | H11: =H8+H9+H10 | I11: =I8+I9+I10 | J11: =J8+J9+J10
A12: Less: Tax | B12: =B11-B13 | C12: =C11-C13 | D12: =D11-D13 | E12: =E11-E13 | F12: =-F11*Assumptions!F8 | G12: =-G11*Assumptions!G8 | H12: =-H11*Assumptions!H8 | I12: =-I11*Assumptions!I8 | J12: =-J11*Assumptions!J8
A13: Profit after tax (PAT) | B13: 810.6 | C13: 1125.8 | D13: 1408 | E13: 1582 | F13: =F11+F12 | G13: =G11+G12 | H13: =H11+H12 | I13: =I11+I12 | J13: =J11+J12
A15: B. Cash-flow feeder lines
A16: Capital expenditure | B16: 134 | C16: 136.6 | D16: 98 | E16: 162 | F16: =F5*Assumptions!F10 | G16: =G5*Assumptions!G10 | H16: =H5*Assumptions!H10 | I16: =I5*Assumptions!I10 | J16: =J5*Assumptions!J10
A17: Increase in net working capital | F17: =(F5-E5)*Assumptions!F11 | G17: =(G5-F5)*Assumptions!G11 | H17: =(H5-G5)*Assumptions!H11 | I17: =(I5-H5)*Assumptions!I11 | J17: =(J5-I5)*Assumptions!J11
A18: Dividends paid (payout x prior-year PAT) | B18: 0 | C18: 0 | D18: 284 | E18: 355 | F18: =E13*Assumptions!F12 | G18: =F13*Assumptions!G12 | H18: =G13*Assumptions!H12 | I18: =H13*Assumptions!I12 | J18: =I13*Assumptions!J12
A20: C. NET INTEREST (the headline output)
A21: Investment & interest income | B21: =B10 | C21: =C10 | D21: =D10 | E21: =E10 | F21: =F10 | G21: =G10 | H21: =H10 | I21: =I10 | J21: =J10
A22: Finance cost | B22: =B9 | C22: =C9 | D22: =D9 | E22: =E9 | F22: =F9 | G22: =G9 | H22: =H9 | I22: =I9 | J22: =J9
A23: NET INTEREST (income - cost) | B23: =B21+B22 | C23: =C21+C22 | D23: =D21+D22 | E23: =E21+E22 | F23: =F21+F22 | G23: =G21+G22 | H23: =H21+H22 | I23: =I21+I22 | J23: =J21+J22
A24: memo: incl. one-off tax-refund interest (hist.) | B24: =B23+0.0 | C24: =C23+0.0 | D24: =D23+88.0 | E24: =E23+48.0 | F24: =F23 | G24: =G23 | H24: =H23 | I24: =I23 | J24: =J23
