Workbook

Sheet Cover
A1: UNITED SPIRITS LIMITED (USL) | Debt Schedule & Cash Schedule
A3: Consolidated | Interest computation model | All figures in Rs crore unless stated
A6: Prepared by | B6: Equity Research – Financial Modelling
A7: Company | B7: United Spirits Limited (a Diageo Group company), NSE/BSE: UNITDSPR / 532432
A8: Reporting currency | B8: Indian Rupee (Rs), figures in Rs crore (1 crore = 10 million)
A9: Historical period | B9: FY2022 to FY2025 (year ended 31 March) - Actuals
A10: Forecast period | B10: FY2026 to FY2030 (year ended 31 March) - Estimates
A11: Primary sources | B11: USL Integrated Annual Report FY2022-23 (figures in Rs million) and FY2024-25 (figures in Rs crore)
A13: KEY INSIGHT | B13: USL is structurally NET-CASH / debt-free. Its only contractual borrowings are negligible;
B14: the material interest-bearing item is LEASE LIABILITIES under Ind AS 116.
B15: Per FY23 AR: "As the Company is debt-free, exposure to interest rate risk is negligible."
A17: Workbook structure
A18: 1. Cover | B18: This sheet
A19: 2. Assumptions | B19: All forecast drivers (blue font = input) with justifications
A20: 3. Historicals | B20: Reconstructed consolidated financials FY22A-FY25A from the annual reports
A21: 4. Debt Schedule | B21: Lease liabilities + borrowings roll-forward; computes INTEREST EXPENSE / finance cost
A22: 5. Cash Schedule | B22: Free-cash-flow build, treasury (cash+deposits+MF) roll; computes INTEREST INCOME
A23: 6. Output Summary | B23: Total debt, net debt, net interest, leverage & coverage ratios
A25: Convention | B25: Lease interest = rate x average lease balance. Interest income = yield x opening treasury
B26: (both non-circular). Blue figures are hard-coded inputs; black figures are formulas.

Sheet Assumptions
A1: ASSUMPTIONS (blue = input) - Rs crore unless stated
A3: Rs crore | C3: FY22A | D3: FY23A | E3: FY24A | F3: FY25A | G3: FY26E | H3: FY27E | I3: FY28E | J3: FY29E | K3: FY30E | L3: Justification / basis
A4: OPERATING DRIVERS
A5: Net sales (ex-excise) - actual | C5: 9712.4 | D5: 10611.6 | E5: 11321 | F5: 12069 | L5: From P&L: Revenue from operations less Excise duty. FY22-23 converted from Rs mn (AR FY23); FY24-25 from AR FY25.
A6: Net sales growth % | D6: =D5/C5-1 | E6: =E5/D5-1 | F6: =F5/E5-1 | G6: 0.095 | H6: 0.1 | I6: 0.1 | J6: 0.09 | K6: 0.09 | L6: FY26-30 inputs. USL reaffirmed double-digit topline guidance; premiumization (P&A ~90% of mix). Industry premium-spirits value CAGR ~12%, IMFL value ~13%; kept conservative for state excise/regulatory risk.
A7: EBITDA margin (% of net sales) | C7: 0.166 | D7: 0.133 | E7: 0.177 | F7: 0.185 | G7: 0.19 | H7: 0.195 | I7: 0.2 | J7: 0.205 | K7: 0.21 | L7: Hist derived (FY23 dip = input-cost inflation). FY26-30 expansion on premiumization & operating leverage (H1FY26 reported EBITDA +31%).
A8: Depreciation & amortisation | C8: 303.8 | D8: 282.5 | E8: 275 | F8: 283 | G8: 290 | H8: 300 | I8: 315 | J8: 330 | K8: 345 | L8: Hist actual. Forecast grows with capex & rising ROU asset base (Ind AS 116).
A9: Effective tax rate % | C9: 0.254 | D9: 0.119 | E9: 0.242 | F9: 0.259 | G9: 0.255 | H9: 0.255 | I9: 0.255 | J9: 0.255 | K9: 0.255 | L9: Hist actual (FY23 low due to prior-year credits). ~25.5% normalised (India corporate rate).
A10: Dividend payout (% of PAT) | C10: 0 | D10: 0 | E10: 0.202 | F10: 0.224 | G10: 0.3 | H10: 0.3 | I10: 0.3 | J10: 0.3 | K10: 0.3 | L10: USL resumed dividends FY24. Rising payout assumed as company is cash-generative & net-cash.
A11: Working-capital outflow (% of net-sales increase) | G11: 0.05 | H11: 0.05 | I11: 0.05 | J11: 0.05 | K11: 0.05 | L11: Incremental net working-capital investment as sales grow (inventory/receivables drag), funded internally.
A12: Capex (PP&E + intangibles) | C12: 134 | D12: 136.6 | E12: 150 | F12: 160 | G12: 175 | H12: 200 | I12: 225 | J12: 250 | K12: 250 | L12: Hist actual/estimate. Forecast: capacity, premiumization & supply-restructuring; asset-light model keeps capex modest.
A14: DEBT / LEASE DRIVERS
A15: Lease incremental borrowing rate % | C15: 0.085 | D15: 0.085 | E15: 0.085 | F15: 0.085 | G15: 0.085 | H15: 0.085 | I15: 0.085 | J15: 0.085 | K15: 0.085 | L15: Ind AS 116 discount rate. Implied FY25 lease interest 40 / avg lease ~360 = ~8-9%. Held at 8.5%.
A16: New lease additions (ROU) | C16: 229.2 | D16: 85.8 | E16: 184 | F16: 394 | G16: 200 | H16: 190 | I16: 190 | J16: 200 | K16: 210 | L16: Hist actual (FY25 spike 394 = plant & equipment leases). Forecast normalised to recurring warehouse/plant leases.
A17: Lease principal repayment | C17: 100.2 | D17: 124 | E17: 126 | F17: 137 | G17: 150 | H17: 160 | I17: 170 | J17: 180 | K17: 190 | L17: Hist actual (financing CF). Forecast grows with the larger lease book.
A18: Lease terminations / adjustments | C18: 0 | D18: 0 | E18: 0 | F18: 17 | G18: 0 | H18: 0 | I18: 0 | J18: 0 | K18: 0 | L18: FY25 had Rs 17 cr lease terminations (ROU note). None assumed forward.
A19: Borrowings - opening (FY22 only) | C19: 497 | L19: FY22 opening short-term/working-capital borrowings (repaid during FY22). Backed out from FY22 repayment & closing.
A20: Borrowings drawdown | C20: 0 | D20: 0 | E20: 25 | F20: 28 | G20: 0 | H20: 0 | I20: 0 | J20: 0 | K20: 0 | L20: Hist actual working-capital loan draws. Nil forward: USL follows a debt-free policy with large undrawn facilities (~Rs 1,300 cr).
A21: Borrowings repayment | C21: 537.7 | D21: 0.4 | E21: 0 | F21: 53 | G21: 0 | H21: 0 | I21: 0 | J21: 0 | K21: 0 | L21: Hist actual. (FY22 repaid Rs 537.7 cr working-capital loans; FY25 repaid Rs 53 cr.)
A22: Interest rate on borrowings % | C22: 0 | D22: 0 | E22: 0 | F22: 0 | G22: 0.085 | H22: 0.085 | I22: 0.085 | J22: 0.085 | K22: 0.085 | L22: Applied to average borrowings (nil forward, so no P&L impact).
A23: Other interest expense (non-lease) | C23: 76.1 | D23: 87.9 | E23: 55 | F23: 49 | G23: 47 | H23: 45 | I23: 43 | J23: 42 | K23: 40 | L23: Interest 'others' in finance-cost note (deferred sales-tax, MSME, unwinding of discount, bank charges). Held ~flat, easing.
A25: CASH / TREASURY DRIVERS
A26: Treasury yield (interest income) % | G26: 0.0675 | H26: 0.0675 | I26: 0.0675 | J26: 0.0675 | K26: 0.0675 | L26: Earned on cash + bank deposits + debt mutual funds. ~6.75% reflects Indian short-term debt/MF yields.
A27: Non-interest other income (operating) | G27: 60 | H27: 65 | I27: 70 | J27: 75 | K27: 80 | L27: Recurring portion of 'Other income' excluding treasury interest (scrap sale, write-backs, misc.).
A29: Legend:
A30: Blue figures = hard-coded inputs/assumptions
A31: Black figures = actuals or formula-driven

Sheet Historicals
A1: HISTORICAL CONSOLIDATED FINANCIALS (as reported) - Rs crore
A2: Source: USL Annual Reports FY2022-23 (Rs mn, /10) and FY2024-25 (Rs cr). Only actual columns populated.
A4: Rs crore | C4: FY22A | D4: FY23A | E4: FY24A | F4: FY25A | G4: FY26E | H4: FY27E | I4: FY28E | J4: FY29E | K4: FY30E
A5: PROFIT & LOSS
A6: Revenue from operations (gross, incl excise) | C6: 31061.8 | D6: 27815.4 | E6: 26018 | F6: 27276
A7: Less: Excise duty | C7: 21349.4 | D7: 17203.8 | E7: 14697 | F7: 15207
A8: Net sales (ex-excise) | C8: =C6-C7 | D8: =D6-D7 | E8: =E6-E7 | F8: =F6-F7
A9: Other income | C9: 35.5 | D9: 73.1 | E9: 225 | F9: 336
A10: EBITDA (derived, pre-exceptional) | C10: 1608.1 | D10: 1415.5 | E10: 2000 | F10: 2236
A11: EBITDA margin % (of net sales) | C11: =C10/C8 | D11: =D10/D8 | E11: =E10/E8 | F11: =F10/F8
A12: Depreciation & amortisation | C12: 303.8 | D12: 282.5 | E12: 275 | F12: 283
A13: Finance costs (total) | C13: 88 | D13: 103.9 | E13: 76 | F13: 89
A14: of which: lease interest | C14: 11.9 | D14: 16 | E14: 21 | F14: 40
A15: of which: other interest | C15: 76.1 | D15: 87.9 | E15: 55 | F15: 49
A16: Exceptional items (net) | C16: -165.2 | D16: 176.4 | E16: -17 | F16: -65
A17: Profit before tax | C17: 1086.6 | D17: 1278.6 | E17: 1857 | F17: 2135
A18: Total tax expense | C18: 276 | D18: 152.8 | E18: 449 | F18: 553
A19: Profit after tax (PAT) | C19: 810.6 | D19: 1125.8 | E19: 1408 | F19: 1582
A21: DEBT, LEASES & LIQUIDITY (Balance Sheet)
A22: Borrowings - non-current | C22: 0.9 | D22: 0.3 | E22: 0 | F22: 0
A23: Borrowings - current | C23: 340.8 | D23: 0.8 | E23: 25 | F23: 0
A24: Total borrowings | C24: =C22+C23 | D24: =D22+D23 | E24: =E22+E23 | F24: =F22+F23
A25: Lease liabilities - non-current | C25: 134.1 | D25: 80 | E25: 137 | F25: 334
A26: Lease liabilities - current | C26: 129.6 | D26: 102.2 | E26: 103 | F26: 146
A27: Total lease liabilities | C27: =C25+C26 | D27: =D25+D26 | E27: =E25+E26 | F27: =F25+F26
A28: Total debt (borrowings + leases) | C28: =C24+C27 | D28: =D24+D27 | E28: =E24+E27 | F28: =F24+F27
A29: Cash & cash equivalents | C29: 54.5 | D29: 115.1 | E29: 1052 | F29: 1328
A30: Bank balances other than cash (deposits) | C30: 5.8 | D30: 768.2 | E30: 217 | F30: 702
A31: Current investments (debt mutual funds) | C31: 222.1 | D31: 255.8 | E31: 599 | F31: 873
A32: Treasury (cash + deposits + MF) | C32: =SUM(C29:C31) | D32: =SUM(D29:D31) | E32: =SUM(E29:E31) | F32: =SUM(F29:F31)
A33: Net debt / (net cash) | C33: =C28-C32 | D33: =D28-D32 | E33: =E28-E32 | F33: =F28-F32
A34: Total equity | C34: 4874.8 | D34: 5999.5 | E34: 7121 | F34: 8104

Sheet Debt Schedule
A1: DEBT SCHEDULE - Lease liabilities + Borrowings -> INTEREST EXPENSE (Rs crore)
A3: Rs crore | C3: FY22A | D3: FY23A | E3: FY24A | F3: FY25A | G3: FY26E | H3: FY27E | I3: FY28E | J3: FY29E | K3: FY30E
A4: A. LEASE LIABILITIES (Ind AS 116)
A5: Opening lease liability | C5: ='Historicals'!C27-Assumptions!C16+Assumptions!C17+Assumptions!C18 | D5: =C9 | E5: =D9 | F5: =E9 | G5: =F9 | H5: =G9 | I5: =H9 | J5: =I9 | K5: =J9
A6: (+) New lease additions (ROU) | C6: =Assumptions!C16 | D6: =Assumptions!D16 | E6: =Assumptions!E16 | F6: =Assumptions!F16 | G6: =Assumptions!G16 | H6: =Assumptions!H16 | I6: =Assumptions!I16 | J6: =Assumptions!J16 | K6: =Assumptions!K16
A7: (-) Terminations / adjustments | C7: =-Assumptions!C18 | D7: =-Assumptions!D18 | E7: =-Assumptions!E18 | F7: =-Assumptions!F18 | G7: =-Assumptions!G18 | H7: =-Assumptions!H18 | I7: =-Assumptions!I18 | J7: =-Assumptions!J18 | K7: =-Assumptions!K18
A8: (-) Principal repayment | C8: =-Assumptions!C17 | D8: =-Assumptions!D17 | E8: =-Assumptions!E17 | F8: =-Assumptions!F17 | G8: =-Assumptions!G17 | H8: =-Assumptions!H17 | I8: =-Assumptions!I17 | J8: =-Assumptions!J17 | K8: =-Assumptions!K17
A9: Closing lease liability | C9: ='Historicals'!C27 | D9: ='Historicals'!D27 | E9: ='Historicals'!E27 | F9: ='Historicals'!F27 | G9: =G5+G6+G7+G8 | H9: =H5+H6+H7+H8 | I9: =I5+I6+I7+I8 | J9: =J5+J6+J7+J8 | K9: =K5+K6+K7+K8
A10: Interest on leases (rate x avg balance) | C10: ='Historicals'!C14 | D10: ='Historicals'!D14 | E10: ='Historicals'!E14 | F10: ='Historicals'!F14 | G10: =Assumptions!G15*AVERAGE(G5,G9) | H10: =Assumptions!H15*AVERAGE(H5,H9) | I10: =Assumptions!I15*AVERAGE(I5,I9) | J10: =Assumptions!J15*AVERAGE(J5,J9) | K10: =Assumptions!K15*AVERAGE(K5,K9)
A11: implied interest rate % | C11: =IF(AVERAGE(C5,C9)=0,0,C10/AVERAGE(C5,C9)) | D11: =IF(AVERAGE(D5,D9)=0,0,D10/AVERAGE(D5,D9)) | E11: =IF(AVERAGE(E5,E9)=0,0,E10/AVERAGE(E5,E9)) | F11: =IF(AVERAGE(F5,F9)=0,0,F10/AVERAGE(F5,F9)) | G11: =IF(AVERAGE(G5,G9)=0,0,G10/AVERAGE(G5,G9)) | H11: =IF(AVERAGE(H5,H9)=0,0,H10/AVERAGE(H5,H9)) | I11: =IF(AVERAGE(I5,I9)=0,0,I10/AVERAGE(I5,I9)) | J11: =IF(AVERAGE(J5,J9)=0,0,J10/AVERAGE(J5,J9)) | K11: =IF(AVERAGE(K5,K9)=0,0,K10/AVERAGE(K5,K9))
A13: B. BORROWINGS (working-capital / short-term)
A14: Opening borrowings | C14: =Assumptions!C19 | D14: =C17 | E14: =D17 | F14: =E17 | G14: =F17 | H14: =G17 | I14: =H17 | J14: =I17 | K14: =J17
A15: (+) Drawdowns | C15: =Assumptions!C20 | D15: =Assumptions!D20 | E15: =Assumptions!E20 | F15: =Assumptions!F20 | G15: =Assumptions!G20 | H15: =Assumptions!H20 | I15: =Assumptions!I20 | J15: =Assumptions!J20 | K15: =Assumptions!K20
A16: (-) Repayments | C16: =-Assumptions!C21 | D16: =-Assumptions!D21 | E16: =-Assumptions!E21 | F16: =-Assumptions!F21 | G16: =-Assumptions!G21 | H16: =-Assumptions!H21 | I16: =-Assumptions!I21 | J16: =-Assumptions!J21 | K16: =-Assumptions!K21
A17: Closing borrowings | C17: ='Historicals'!C24 | D17: ='Historicals'!D24 | E17: ='Historicals'!E24 | F17: ='Historicals'!F24 | G17: =G14+G15+G16 | H17: =H14+H15+H16 | I17: =I14+I15+I16 | J17: =J14+J15+J16 | K17: =K14+K15+K16
A18: Interest on borrowings (rate x avg) | C18: =Assumptions!C22*AVERAGE(C14,C17) | D18: =Assumptions!D22*AVERAGE(D14,D17) | E18: =Assumptions!E22*AVERAGE(E14,E17) | F18: =Assumptions!F22*AVERAGE(F14,F17) | G18: =Assumptions!G22*AVERAGE(G14,G17) | H18: =Assumptions!H22*AVERAGE(H14,H17) | I18: =Assumptions!I22*AVERAGE(I14,I17) | J18: =Assumptions!J22*AVERAGE(J14,J17) | K18: =Assumptions!K22*AVERAGE(K14,K17)
A20: C. TOTAL FINANCE COST (P&L interest expense)
A21: Lease interest | C21: =C10 | D21: =D10 | E21: =E10 | F21: =F10 | G21: =G10 | H21: =H10 | I21: =I10 | J21: =J10 | K21: =K10
A22: Borrowing interest | C22: =C18 | D22: =D18 | E22: =E18 | F22: =F18 | G22: =G18 | H22: =H18 | I22: =I18 | J22: =J18 | K22: =K18
A23: Other interest (non-lease, non-borrowing) | C23: =Assumptions!C23 | D23: =Assumptions!D23 | E23: =Assumptions!E23 | F23: =Assumptions!F23 | G23: =Assumptions!G23 | H23: =Assumptions!H23 | I23: =Assumptions!I23 | J23: =Assumptions!J23 | K23: =Assumptions!K23
A24: Total finance cost | C24: =SUM(C21:C23) | D24: =SUM(D21:D23) | E24: =SUM(E21:E23) | F24: =SUM(F21:F23) | G24: =SUM(G21:G23) | H24: =SUM(H21:H23) | I24: =SUM(I21:I23) | J24: =SUM(J21:J23) | K24: =SUM(K21:K23)
A25: Memo: Total debt (closing) | C25: =C9+C17 | D25: =D9+D17 | E25: =E9+E17 | F25: =F9+F17 | G25: =G9+G17 | H25: =H9+H17 | I25: =I9+I17 | J25: =J9+J17 | K25: =K9+K17
A26: Memo: Reported finance cost (actual) | C26: 88 | D26: 103.9 | E26: 76 | F26: 89
A27: Memo: Variance (model - reported) | C27: =C24-C26 | D27: =D24-D26 | E27: =E24-E26 | F27: =F24-F26
A28: Memo: model lease interest @ rate x avg | C28: =Assumptions!C15*AVERAGE(C5,C9) | D28: =Assumptions!D15*AVERAGE(D5,D9) | E28: =Assumptions!E15*AVERAGE(E5,E9) | F28: =Assumptions!F15*AVERAGE(F5,F9) | G28: =Assumptions!G15*AVERAGE(G5,G9) | H28: =Assumptions!H15*AVERAGE(H5,H9) | I28: =Assumptions!I15*AVERAGE(I5,I9) | J28: =Assumptions!J15*AVERAGE(J5,J9) | K28: =Assumptions!K15*AVERAGE(K5,K9)

Sheet Cash Schedule
A1: CASH SCHEDULE - FCF build & treasury roll -> INTEREST INCOME (Rs crore)
A3: Rs crore | C3: FY22A | D3: FY23A | E3: FY24A | F3: FY25A | G3: FY26E | H3: FY27E | I3: FY28E | J3: FY29E | K3: FY30E
A4: A. P&L BRIDGE (drives cash)
A5: Net sales (ex-excise) | C5: ='Historicals'!C8 | D5: ='Historicals'!D8 | E5: ='Historicals'!E8 | F5: ='Historicals'!F8 | G5: =F5*(1+Assumptions!G6) | H5: =G5*(1+Assumptions!H6) | I5: =H5*(1+Assumptions!I6) | J5: =I5*(1+Assumptions!J6) | K5: =J5*(1+Assumptions!K6)
A6: growth % | D6: =D5/C5-1 | E6: =E5/D5-1 | F6: =F5/E5-1 | G6: =G5/F5-1 | H6: =H5/G5-1 | I6: =I5/H5-1 | J6: =J5/I5-1 | K6: =K5/J5-1
A7: EBITDA | C7: ='Historicals'!C10 | D7: ='Historicals'!D10 | E7: ='Historicals'!E10 | F7: ='Historicals'!F10 | G7: =G5*Assumptions!G7 | H7: =H5*Assumptions!H7 | I7: =I5*Assumptions!I7 | J7: =J5*Assumptions!J7 | K7: =K5*Assumptions!K7
A8: (-) Depreciation & amortisation | C8: =-'Historicals'!C12 | D8: =-'Historicals'!D12 | E8: =-'Historicals'!E12 | F8: =-'Historicals'!F12 | G8: =-Assumptions!G8 | H8: =-Assumptions!H8 | I8: =-Assumptions!I8 | J8: =-Assumptions!J8 | K8: =-Assumptions!K8
A9: EBIT | C9: =C7+C8 | D9: =D7+D8 | E9: =E7+E8 | F9: =F7+F8 | G9: =G7+G8 | H9: =H7+H8 | I9: =I7+I8 | J9: =J7+J8 | K9: =K7+K8
A10: (+) Interest income (treasury) | G10: =Assumptions!G26*G33 | H10: =Assumptions!H26*H33 | I10: =Assumptions!I26*I33 | J10: =Assumptions!J26*J33 | K10: =Assumptions!K26*K33
A11: (-) Finance cost (from Debt Schedule) | C11: =-'Historicals'!C13 | D11: =-'Historicals'!D13 | E11: =-'Historicals'!E13 | F11: =-'Historicals'!F13 | G11: =-'Debt Schedule'!G24 | H11: =-'Debt Schedule'!H24 | I11: =-'Debt Schedule'!I24 | J11: =-'Debt Schedule'!J24 | K11: =-'Debt Schedule'!K24
A12: (+) Other operating income | G12: =Assumptions!G27 | H12: =Assumptions!H27 | I12: =Assumptions!I27 | J12: =Assumptions!J27 | K12: =Assumptions!K27
A13: Profit before tax | C13: ='Historicals'!C17 | D13: ='Historicals'!D17 | E13: ='Historicals'!E17 | F13: ='Historicals'!F17 | G13: =G9+G10+G11+G12 | H13: =H9+H10+H11+H12 | I13: =I9+I10+I11+I12 | J13: =J9+J10+J11+J12 | K13: =K9+K10+K11+K12
A14: (-) Tax | C14: =-'Historicals'!C18 | D14: =-'Historicals'!D18 | E14: =-'Historicals'!E18 | F14: =-'Historicals'!F18 | G14: =-G13*Assumptions!G9 | H14: =-H13*Assumptions!H9 | I14: =-I13*Assumptions!I9 | J14: =-J13*Assumptions!J9 | K14: =-K13*Assumptions!K9
A15: Profit after tax (PAT) | C15: ='Historicals'!C19 | D15: ='Historicals'!D19 | E15: ='Historicals'!E19 | F15: ='Historicals'!F19 | G15: =G13+G14 | H15: =H13+H14 | I15: =I13+I14 | J15: =J13+J14 | K15: =K13+K14
A17: B. FREE CASH FLOW
A18: EBITDA | C18: =C7 | D18: =D7 | E18: =E7 | F18: =F7 | G18: =G7 | H18: =H7 | I18: =I7 | J18: =J7 | K18: =K7
A19: (-) Cash tax | C19: =C14 | D19: =D14 | E19: =E14 | F19: =F14 | G19: =G14 | H19: =H14 | I19: =I14 | J19: =J14 | K19: =K14
A20: (-) Increase in working capital | G20: =-(G5-F5)*Assumptions!G11 | H20: =-(H5-G5)*Assumptions!H11 | I20: =-(I5-H5)*Assumptions!I11 | J20: =-(J5-I5)*Assumptions!J11 | K20: =-(K5-J5)*Assumptions!K11
A21: Operating cash flow | C21: =C18+C19+IF(C20="",0,C20) | D21: =D18+D19+IF(D20="",0,D20) | E21: =E18+E19+IF(E20="",0,E20) | F21: =F18+F19+IF(F20="",0,F20) | G21: =G18+G19+IF(G20="",0,G20) | H21: =H18+H19+IF(H20="",0,H20) | I21: =I18+I19+IF(I20="",0,I20) | J21: =J18+J19+IF(J20="",0,J20) | K21: =K18+K19+IF(K20="",0,K20)
A22: (-) Capex | C22: =-Assumptions!C12 | D22: =-Assumptions!D12 | E22: =-Assumptions!E12 | F22: =-Assumptions!F12 | G22: =-Assumptions!G12 | H22: =-Assumptions!H12 | I22: =-Assumptions!I12 | J22: =-Assumptions!J12 | K22: =-Assumptions!K12
A23: (-) Lease principal repayment | C23: =-Assumptions!C17 | D23: =-Assumptions!D17 | E23: =-Assumptions!E17 | F23: =-Assumptions!F17 | G23: =-Assumptions!G17 | H23: =-Assumptions!H17 | I23: =-Assumptions!I17 | J23: =-Assumptions!J17 | K23: =-Assumptions!K17
A24: (-) Lease interest paid | C24: =-'Debt Schedule'!C21 | D24: =-'Debt Schedule'!D21 | E24: =-'Debt Schedule'!E21 | F24: =-'Debt Schedule'!F21 | G24: =-'Debt Schedule'!G21 | H24: =-'Debt Schedule'!H21 | I24: =-'Debt Schedule'!I21 | J24: =-'Debt Schedule'!J21 | K24: =-'Debt Schedule'!K21
A25: (-) Other interest paid | C25: =-'Debt Schedule'!C23 | D25: =-'Debt Schedule'!D23 | E25: =-'Debt Schedule'!E23 | F25: =-'Debt Schedule'!F23 | G25: =-'Debt Schedule'!G23 | H25: =-'Debt Schedule'!H23 | I25: =-'Debt Schedule'!I23 | J25: =-'Debt Schedule'!J23 | K25: =-'Debt Schedule'!K23
A26: (+/-) Net borrowings draw/(repay) | C26: =Assumptions!C20-Assumptions!C21 | D26: =Assumptions!D20-Assumptions!D21 | E26: =Assumptions!E20-Assumptions!E21 | F26: =Assumptions!F20-Assumptions!F21 | G26: =Assumptions!G20-Assumptions!G21 | H26: =Assumptions!H20-Assumptions!H21 | I26: =Assumptions!I20-Assumptions!I21 | J26: =Assumptions!J20-Assumptions!J21 | K26: =Assumptions!K20-Assumptions!K21
A27: Cash flow before dividends & interest income | C27: =C21+C22+C23+C24+C25+C26 | D27: =D21+D22+D23+D24+D25+D26 | E27: =E21+E22+E23+E24+E25+E26 | F27: =F21+F22+F23+F24+F25+F26 | G27: =G21+G22+G23+G24+G25+G26 | H27: =H21+H22+H23+H24+H25+H26 | I27: =I21+I22+I23+I24+I25+I26 | J27: =J21+J22+J23+J24+J25+J26 | K27: =K21+K22+K23+K24+K25+K26
A28: (+) Interest income received | G28: =G10 | H28: =H10 | I28: =I10 | J28: =J10 | K28: =K10
A29: (-) Dividends paid | G29: =-G15*Assumptions!G10 | H29: =-H15*Assumptions!H10 | I29: =-I15*Assumptions!I10 | J29: =-J15*Assumptions!J10 | K29: =-K15*Assumptions!K10
A30: Net change in treasury | G30: =G27+G28+G29 | H30: =H27+H28+H29 | I30: =I27+I28+I29 | J30: =J27+J28+J29 | K30: =K27+K28+K29
A32: C. TREASURY ROLL-FORWARD (cash + deposits + MF)
A33: Opening treasury | D33: ='Historicals'!C32 | E33: ='Historicals'!D32 | F33: ='Historicals'!E32 | G33: =F35 | H33: =G35 | I33: =H35 | J33: =I35 | K33: =J35
A34: (+) Net change in treasury | G34: =G30 | H34: =H30 | I34: =I30 | J34: =J30 | K34: =K30
A35: Closing treasury | C35: ='Historicals'!C32 | D35: ='Historicals'!D32 | E35: ='Historicals'!E32 | F35: ='Historicals'!F32 | G35: =G33+G34 | H35: =H33+H34 | I35: =I33+I34 | J35: =J33+J34 | K35: =K33+K34
A36: Memo: interest income (yield x opening) | C36: =Assumptions!C26*C33 | D36: =Assumptions!D26*D33 | E36: =Assumptions!E26*E33 | F36: =Assumptions!F26*F33 | G36: =Assumptions!G26*G33 | H36: =Assumptions!H26*H33 | I36: =Assumptions!I26*I33 | J36: =Assumptions!J26*J33 | K36: =Assumptions!K26*K33

Sheet Output Summary
A1: OUTPUT SUMMARY - Debt, Net Debt, Interest & Ratios (Rs crore)
A3: Rs crore | C3: FY22A | D3: FY23A | E3: FY24A | F3: FY25A | G3: FY26E | H3: FY27E | I3: FY28E | J3: FY29E | K3: FY30E
A4: DEBT & LIQUIDITY
A5: Total lease liabilities | C5: ='Debt Schedule'!C9 | D5: ='Debt Schedule'!D9 | E5: ='Debt Schedule'!E9 | F5: ='Debt Schedule'!F9 | G5: ='Debt Schedule'!G9 | H5: ='Debt Schedule'!H9 | I5: ='Debt Schedule'!I9 | J5: ='Debt Schedule'!J9 | K5: ='Debt Schedule'!K9
A6: Total borrowings | C6: ='Debt Schedule'!C17 | D6: ='Debt Schedule'!D17 | E6: ='Debt Schedule'!E17 | F6: ='Debt Schedule'!F17 | G6: ='Debt Schedule'!G17 | H6: ='Debt Schedule'!H17 | I6: ='Debt Schedule'!I17 | J6: ='Debt Schedule'!J17 | K6: ='Debt Schedule'!K17
A7: Total debt | C7: ='Debt Schedule'!C25 | D7: ='Debt Schedule'!D25 | E7: ='Debt Schedule'!E25 | F7: ='Debt Schedule'!F25 | G7: ='Debt Schedule'!G25 | H7: ='Debt Schedule'!H25 | I7: ='Debt Schedule'!I25 | J7: ='Debt Schedule'!J25 | K7: ='Debt Schedule'!K25
A8: Treasury (cash + deposits + MF) | C8: ='Cash Schedule'!C35 | D8: ='Cash Schedule'!D35 | E8: ='Cash Schedule'!E35 | F8: ='Cash Schedule'!F35 | G8: ='Cash Schedule'!G35 | H8: ='Cash Schedule'!H35 | I8: ='Cash Schedule'!I35 | J8: ='Cash Schedule'!J35 | K8: ='Cash Schedule'!K35
A9: Net debt / (net cash) | C9: =C7-C8 | D9: =D7-D8 | E9: =E7-E8 | F9: =F7-F8 | G9: =G7-G8 | H9: =H7-H8 | I9: =I7-I8 | J9: =J7-J8 | K9: =K7-K8
A11: INTEREST
A12: Interest expense (finance cost) | C12: ='Debt Schedule'!C24 | D12: ='Debt Schedule'!D24 | E12: ='Debt Schedule'!E24 | F12: ='Debt Schedule'!F24 | G12: ='Debt Schedule'!G24 | H12: ='Debt Schedule'!H24 | I12: ='Debt Schedule'!I24 | J12: ='Debt Schedule'!J24 | K12: ='Debt Schedule'!K24
A13: Interest income | G13: ='Cash Schedule'!G10 | H13: ='Cash Schedule'!H10 | I13: ='Cash Schedule'!I10 | J13: ='Cash Schedule'!J10 | K13: ='Cash Schedule'!K10
A14: Net interest expense / (income) | G14: =G12-G13 | H14: =H12-H13 | I14: =I12-I13 | J14: =J12-J13 | K14: =K12-K13
A16: KEY RATIOS
A17: EBITDA | C17: ='Cash Schedule'!C7 | D17: ='Cash Schedule'!D7 | E17: ='Cash Schedule'!E7 | F17: ='Cash Schedule'!F7 | G17: ='Cash Schedule'!G7 | H17: ='Cash Schedule'!H7 | I17: ='Cash Schedule'!I7 | J17: ='Cash Schedule'!J7 | K17: ='Cash Schedule'!K7
A18: Net debt / EBITDA (x) | C18: =C9/C17 | D18: =D9/D17 | E18: =E9/E17 | F18: =F9/F17 | G18: =G9/G17 | H18: =H9/H17 | I18: =I9/I17 | J18: =J9/J17 | K18: =K9/K17
A19: EBITDA / interest expense (x) | C19: =IF(C12=0,0,C17/C12) | D19: =IF(D12=0,0,D17/D12) | E19: =IF(E12=0,0,E17/E12) | F19: =IF(F12=0,0,F17/F12) | G19: =IF(G12=0,0,G17/G12) | H19: =IF(H12=0,0,H17/H12) | I19: =IF(I12=0,0,I17/I12) | J19: =IF(J12=0,0,J17/J12) | K19: =IF(K12=0,0,K17/K12)
A20: Gross debt / equity (x) | C20: =C7/C26 | D20: =D7/D26 | E20: =E7/E26 | F20: =F7/F26 | G20: =G7/G26 | H20: =H7/H26 | I20: =I7/I26 | J20: =J7/J26 | K20: =K7/K26
A22: MEMO: EQUITY ROLL
A23: Opening equity | D23: ='Historicals'!C34 | E23: ='Historicals'!D34 | F23: ='Historicals'!E34 | G23: =F26 | H23: =G26 | I23: =H26 | J23: =I26 | K23: =J26
A24: (+) PAT | C24: ='Cash Schedule'!C15 | D24: ='Cash Schedule'!D15 | E24: ='Cash Schedule'!E15 | F24: ='Cash Schedule'!F15 | G24: ='Cash Schedule'!G15 | H24: ='Cash Schedule'!H15 | I24: ='Cash Schedule'!I15 | J24: ='Cash Schedule'!J15 | K24: ='Cash Schedule'!K15
A25: (-) Dividends | G25: ='Cash Schedule'!G29 | H25: ='Cash Schedule'!H29 | I25: ='Cash Schedule'!I29 | J25: ='Cash Schedule'!J29 | K25: ='Cash Schedule'!K29
A26: Closing equity | C26: ='Historicals'!C34 | D26: ='Historicals'!D34 | E26: ='Historicals'!E34 | F26: ='Historicals'!F34 | G26: =G23+G24+G25 | H26: =H23+H24+H25 | I26: =I23+I24+I25 | J26: =J23+J24+J25 | K26: =K23+K24+K25
